Workbook

Sheet mcantu_STRU_BRBacklog_20260128_
A1: OrderDate | B1: RequestedShipDate | C1: ScheduledShipDate | D1: PromisedShipDate | E1: SONumber | F1: LineNumber | G1: ShipToCode | H1: ItemCode | I1: ItemDescription | J1: OrderQuantity | K1: UnitPrice | L1: ExtendedLineAmount | M1: CustomerCode | N1: ItemSalesClassCode | O1: DropShip | P1: SOTypeCode | Q1: FinalDestination | R1: CustomerName | S1: ShipToAddress1 | T1: ShipToAddress2 | U1: ShipToStateCode | V1: ShipToZip | W1: ParentDocumentNumber | X1: Weight | Y1: OrderMessage | Z1: ShipToName | AA1: ShipToCity | AB1: ShippingInstructions | AC1: WarehouseCode | AD1: WarehouseName
A2: 45944 | B2: 46034 | C2: 2 | D2: 46050 | E2: 0000064684 | F2: 1 | G2: MAYNARD | H2: 003843 | I2: DeRoyal Episeal Tan 3 Inch Non-Reinforced Material | J2: 28000 | K2: 0.396 | L2: 11088 | M2: DEROYAL | N2: MEDICAL | O2: FALSE | P2: SO | R2: DeRoyal Accounts Payable Dept | S2: 185 Richardson Way | U2: TN | V2: 37807 | X2: 0 | Z2: DeRoyal Foam/ Convertin | AA2: Maynardville | AC2: PCI-01 | AD2: STRUKMYER, LLC
A3: 45974 | B3: 45996 | C3: 2 | D3: 2 | E3: 0000064757 | F3: 2 | G3: LAND | H3: 006370 | I3: TB DRY MOUTH TINGLING RINSE 16 OZ BULK 40101908 | J3: 20000 | K3: 1.7789 | L3: 35578 | M3: ORORA | N3: Filling OP | O3: FALSE | P3: SO | R3: Orora Business Service Center | S3: 13397 Marlay Ave Ste A | U3: CA | V3: 92337-6946 | X3: 0 | Z3: Landsberg-Fullfillment Solutions | AA3: Fontana | AB3: Need special certificate COA before shipped | AC3: PCI-01 | AD3: STRUKMYER, LLC
A4: 46020 | B4: 46089 | C4: 2 | D4: 2 | E4: 0000064846 | F4: 1 | G4: lawson | H4: 005121 | I4: IMPLUS CANADA BLISTER PADS 4740700 | J4: 15600 | K4: 2.9 | L4: 45240 | M4: IMPLUS CAN | N4: MEDICAL | O4: FALSE | P4: SO | R4: Implus Canada | S4: 8399 LAWSON ROAD, UNIT 104 | U4: ON | V4: L9T9L1 | X4: 0 | Z4: SPENCO CANADA/IMPLUS CANADA | AA4: MILTON | AB4: For all Collect shipments to Implus Canada email Graham Patterson gpatterson@4implus.com, Shipments@4implus.com, and our Canadian carrier One For Freight support team at Implus@oneforfreight.com.
A5: Please include the following information: PO # | B5: pallet count | C5: pallet dims & weights | D5: product NMFC | E5: freight class | F5: ship from address | G5: pickup hours | H5: ship to location.
A7: PCI-01 STRUKMYER | B7: LLC"
A8: 46042 | B8: 2 | C8: 2 | D8: 2 | E8: 0000064923 | F8: 1 | H8: N-4001 | I8: 1,000 L Obelix Bulk Wound Wash Solution | J8: 1 | K8: 2912 | L8: 2912 | M8: URGO | N8: MEDICAL | O8: FALSE | P8: SO | R8: URGO Medical | S8: 100 Lexington Street, Suite 400 | U8: TX | V8: 76102 | X8: 0 | Z8: URGO Medical | AA8: Fort Worth | AC8: PCI-01 | AD8: STRUKMYER, LLC
A9: 46057 | B9: 2 | C9: 2 | D9: 2 | E9: 0000064956 | F9: 1 | G9: BILL | H9: 007217 | I9: DERMACLIP EXT 3 CLIP PAD NS -31005 | J9: 300 | K9: 6.7991 | L9: 2039.73 | M9: Dermaclip | N9: MEDICAL | O9: FALSE | P9: SO | R9: DermaClip US, LLC | S9: 730 N Post Oak Rd., Ste. 202 | U9: TX | V9: 77024 | X9: 0 | Z9: DermaClip US, LLC | AA9: Houston | AC9: PCI-01 | AD9: STRUKMYER, LLC
A10: 46064 | B10: 2 | C10: 2 | D10: 2 | E10: 0000064985 | F10: 1 | H10: N-4001 | I10: Cleaning validation for Delight production | J10: 1 | K10: 3000 | L10: 3000 | M10: Bloomi | N10: MEDICAL | O10: FALSE | P10: SO | R10: The Bloomi Inc | S10: 74 Royal Ridge Ct | U10: CA | V10: 94507 | X10: 0 | Z10: The Bloomi Inc | AA10: Alamo | AC10: PCI-01 | AD10: STRUKMYER, LLC
A11: 46064 | B11: 2 | C11: 2 | D11: 2 | E11: 0000064986 | F11: 1 | H11: 007991 | I11: Bloomi Delight 3oz | J11: 5000 | K11: 3.45 | L11: 17250 | M11: Bloomi | N11: Default | O11: FALSE | P11: SO | R11: The Bloomi Inc | S11: 74 Royal Ridge Ct | U11: CA | V11: 94507 | X11: 0 | Z11: The Bloomi Inc | AA11: Alamo | AB11: Bloomi to arrange freight | AC11: PCI-01 | AD11: STRUKMYER, LLC
A12: 46064 | B12: 46108 | C12: 2 | D12: 2 | E12: 0000064990 | F12: 1 | H12: 007993 | I12: 200 RC Filter | J12: 10000 | K12: 1.675 | L12: 16750 | M12: HARM IRE | N12: MEDICAL | O12: FALSE | P12: SO | R12: Harmac Medical Products | S12: IDA Business Park | U12: .. | V12: ... | X12: 0 | Z12: Harmac Medical Products | AA12: Castlerea, County Roscommon | AC12: PCI-01 | AD12: STRUKMYER, LLC
A13: 46064 | B13: 46108 | C13: 2 | D13: 2 | E13: 0000064990 | F13: 2 | H13: 007992 | I13: Port Drape | J13: 10000 | K13: 0.625 | L13: 6250 | M13: HARM IRE | N13: MEDICAL | O13: FALSE | P13: SO | R13: Harmac Medical Products | S13: IDA Business Park | U13: .. | V13: ... | X13: 0 | Z13: Harmac Medical Products | AA13: Castlerea, County Roscommon | AC13: PCI-01 | AD13: STRUKMYER, LLC
A14: 46066 | B14: 2 | C14: 2 | D14: 2 | E14: 0000064992 | F14: 1 | G14: BILL | H14: 008012 | I14: Bloomi Delight 3oz (1K Use Only) | J14: 1 | K14: 1000 | L14: 1000 | M14: Bloomi | N14: Filling OP | O14: FALSE | P14: SO | R14: The Bloomi Inc | S14: 74 Royal Ridge Ct | U14: CA | V14: 94507 | X14: 0 | Z14: The Bloomi Inc | AA14: Alamo | AC14: PCI-01 | AD14: STRUKMYER, LLC
A15: 46071 | B15: 2 | C15: 2 | D15: 2 | E15: 0000065007 | F15: 1 | H15: N-4001 | I15: 1 of 3 Bulk Validations | J15: 1 | K15: 1910 | L15: 1910 | M15: TURN | N15: MEDICAL | O15: FALSE | P15: SO | R15: Turn Therapeutics | S15: 250 N. Westlake Blvd, Suite 210 | U15: CA | V15: 91362 | X15: 0 | Z15: Turn Therapeutics | AA15: Westlake Village | AC15: PCI-01 | AD15: STRUKMYER, LLC
A16: 46071 | B16: 2 | C16: 2 | D16: 2 | E16: 0000065007 | F16: 2 | H16: 007997 | I16: Turn Therapeutics Hexagen Bulk - 55 Gallon Drum | J16: 8 | K16: 1910 | L16: 15280 | M16: TURN | N16: Filling OP | O16: FALSE | P16: SO | R16: Turn Therapeutics | S16: 250 N. Westlake Blvd, Suite 210 | U16: CA | V16: 91362 | X16: 0 | Z16: Turn Therapeutics | AA16: Westlake Village | AC16: PCI-01 | AD16: STRUKMYER, LLC
A17: 46071 | B17: 2 | C17: 2 | D17: 2 | E17: 0000065007 | F17: 3 | H17: N-4001 | I17: Cleaning Validation | J17: 1 | K17: 10000 | L17: 10000 | M17: TURN | N17: MEDICAL | O17: FALSE | P17: SO | R17: Turn Therapeutics | S17: 250 N. Westlake Blvd, Suite 210 | U17: CA | V17: 91362 | X17: 0 | Z17: Turn Therapeutics | AA17: Westlake Village | AC17: PCI-01 | AD17: STRUKMYER, LLC
A18: 46076 | B18: 46191 | C18: 2 | D18: 2 | E18: 0000065010 | F18: 1 | G18: ATLANTA | H18: 007488 | I18: CARDINAL HEALTH TELFA NON-ADHERENT DRESSING 3"x4" 2132 | J18: 1080 | K18: 170.4 | L18: 184032 | M18: COVIDMA | N18: MEDICAL | O18: FALSE | P18: SO | R18: Patient Recovery | S18: 110 Kendall Park Lane | U18: GA | V18: 30336 | X18: 0 | Z18: Atlanta RC - US | AA18: Atlanta | AB18: **Effective 7/28/18 www.routingguides.com/cardinal%20health
A19: For Small orders and LTL use fedex 3rd party 920710310 | B19: less than or equal to 150lbs | C19: refer to LTL/TL routing guide *requires special cert*" | D19: PCI-01 | E19: STRUKMYER, LLC
A20: 46077 | B20: 46225 | C20: 2 | D20: 2 | E20: 0000065011 | F20: 1 | G20: G-Global | H20: 000609 | I20: MEDISTRIP 1/4 IN X 3 IN BULK | J20: 17 | K20: 119 | L20: 2023 | M20: CENTURION | N20: MEDICAL | O20: FALSE | P20: SO | R20: Centurion Medical Products Corp | S20: C/O G-Global Logistics Inc | T20: 1776 Pan American St. Building B Suite 100 | U20: CA | V20: 92231 | X20: 1 | Z20: Centurion Medical | AA20: Calexico | AC20: PCI-01 | AD20: STRUKMYER, LLC
A21: 46077 | B21: 46225 | C21: 2 | D21: 2 | E21: 0000065011 | F21: 2 | G21: G-Global | H21: 000610 | I21: MEDISTRIP 1 IN X 4 IN BULK | J21: 55 | K21: 196.5 | L21: 10807.5 | M21: CENTURION | N21: MEDICAL | O21: FALSE | P21: SO | R21: Centurion Medical Products Corp | S21: C/O G-Global Logistics Inc | T21: 1776 Pan American St. Building B Suite 100 | U21: CA | V21: 92231 | X21: 4 | Z21: Centurion Medical | AA21: Calexico | AC21: PCI-01 | AD21: STRUKMYER, LLC
A22: 46077 | B22: 46176 | C22: 2 | D22: 2 | E22: 0000065012 | F22: 1 | G22: G-Global | H22: 002977 | I22: MEDLINE DRSG SURESITE 4.75 X 4 FRAME/LABL (MSC52281) | J22: 63 | K22: 340 | L22: 21420 | M22: CENTURION | N22: MEDICAL | O22: FALSE | P22: SO | R22: Centurion Medical Products Corp | S22: C/O G-Global Logistics Inc | T22: 1776 Pan American St. Building B Suite 100 | U22: CA | V22: 92231 | X22: 26 | Z22: Centurion Medical | AA22: Calexico | AC22: PCI-01 | AD22: STRUKMYER, LLC
A23: 46077 | B23: 46105 | C23: 2 | D23: 2 | E23: 0000065013 | F23: 1 | H23: 007861 | I23: ViaCLYR Flip Top 8oz | J23: 5000 | K23: 2.7 | L23: 13500 | M23: CLYRA | N23: Filling OP | O23: FALSE | P23: SO | R23: Clyra Medical Technologies, Inc. | S23: 10770 N 46th Street, Unit C-300 | U23: FL | V23: 33617 | X23: 0 | Z23: Clyra Medical Technologies, Inc. | AA23: Tampa | AC23: PCI-01 | AD23: STRUKMYER, LLC
A24: 46077 | B24: 46105 | C24: 2 | D24: 2 | E24: 0000065013 | F24: 2 | H24: 007862 | I24: ViaCLYR Flip Top 16oz | J24: 5000 | K24: 3.5 | L24: 17500 | M24: CLYRA | N24: Filling OP | O24: FALSE | P24: SO | R24: Clyra Medical Technologies, Inc. | S24: 10770 N 46th Street, Unit C-300 | U24: FL | V24: 33617 | X24: 0 | Z24: Clyra Medical Technologies, Inc. | AA24: Tampa | AC24: PCI-01 | AD24: STRUKMYER, LLC
A25: 46077 | B25: 46105 | C25: 2 | D25: 2 | E25: 0000065013 | F25: 3 | H25: 007863 | I25: ViaCLYR Flip Top 32oz | J25: 1000 | K25: 7.52 | L25: 7520 | M25: CLYRA | N25: Filling OP | O25: FALSE | P25: SO | R25: Clyra Medical Technologies, Inc. | S25: 10770 N 46th Street, Unit C-300 | U25: FL | V25: 33617 | X25: 0 | Z25: Clyra Medical Technologies, Inc. | AA25: Tampa | AC25: PCI-01 | AD25: STRUKMYER, LLC
A26: 46077 | B26: 46237 | C26: 2 | D26: 2 | E26: 0000065014 | F26: 1 | G26: 3440 | H26: 005045 | I26: FREUDENBERG 30cm X 47cm Nonwoven Sheets 122P0463 | J26: 25000 | K26: 1.63 | L26: 40750 | M26: FREUD | N26: MEDICAL | O26: FALSE | P26: SO | R26: Freudenberg Performance Materials LP | S26: 3440 Industrial Drive | U26: NC | V26: 27704 | X26: 0 | Z26: Freudenberg Performance Materials LP | AA26: Durham | AB26: **DO NOT DOUBLE STACK LABEL - TAKE PHOTO**
A27: SHIP VIA CH ROBINSON. CONTACT Dustin Seong 813-840-4526 OR dustin.seong@chrobinson.com. Freight is 3rd party bill to Freudenberg
A28: Receiving hours M-F 8am -4pm
A29: PCI-01 STRUKMYER | B29: LLC"
A30: 45903 | B30: 2 | C30: 46063 | D30: 46021 | E30: 0000064540 | F30: 1 | H30: 007898 | I30: MPM DryMax/DrySAP Extra Super Absorbent Drsg, Sterile, 8X8; | J30: 10000 | K30: 0.99 | L30: 9900 | M30: MPM | N30: MEDICAL | O30: FALSE | P30: SO | R30: MPM Medical, Inc. | S30: 1801 Big Town Blvd, Suite 300 | U30: TX | V30: 75149 | X30: 0 | Z30: MPM Medical, Inc. | AA30: Mesquite | AC30: PCI-01 | AD30: STRUKMYER, LLC
A31: 45987 | B31: 46104 | C31: 46073 | D31: 46086 | E31: 0000064784 | F31: 2 | G31: ICS | H31: 007153 | I31: URGO - VASHE 250 ml Flip Top 00313 | J31: 50004 | K31: 1.88 | L31: 94007.52 | M31: URGO | N31: Filling OP | O31: FALSE | P31: SO | R31: URGO Medical | S31: 167 International Blvd, Suite 550 | U31: KY | V31: 40109 | X31: 0 | Z31: ICS (Urgo Medical) | AA31: Brooks | AB31: ReceivingBrooks@icsconnect.com
A32: 502-955-3671" | B32: PCI-01 | C32: STRUKMYER, LLC
A33: 45987 | B33: 46118 | C33: 46073 | D33: 46086 | E33: 0000064786 | F33: 1 | G33: ICS | H33: 007153 | I33: URGO - VASHE 250 ml Flip Top 00313 | J33: 45000 | K33: 1.88 | L33: 84600 | M33: URGO | N33: Filling OP | O33: FALSE | P33: SO | R33: URGO Medical | S33: 167 International Blvd, Suite 550 | U33: KY | V33: 40109 | X33: 0 | Z33: ICS (Urgo Medical) | AA33: Brooks | AB33: ReceivingBrooks@icsconnect.com
A34: 502-955-3671" | B34: PCI-01 | C34: STRUKMYER, LLC
A35: 45987 | B35: 46125 | C35: 46073 | D35: 46086 | E35: 0000064787 | F35: 1 | G35: ICS | H35: 007153 | I35: URGO - VASHE 250 ml Flip Top 00313 | J35: 50004 | K35: 1.88 | L35: 94007.52 | M35: URGO | N35: Filling OP | O35: FALSE | P35: SO | R35: URGO Medical | S35: 167 International Blvd, Suite 550 | U35: KY | V35: 40109 | X35: 0 | Z35: ICS (Urgo Medical) | AA35: Brooks | AB35: ReceivingBrooks@icsconnect.com
A36: 502-955-3671" | B36: PCI-01 | C36: STRUKMYER, LLC
A37: 45974 | B37: 45996 | C37: 46076 | D37: 46064 | E37: 0000064757 | F37: 1 | G37: LAND | H37: 006370 | I37: TB DRY MOUTH TINGLING RINSE 16 OZ BULK 40101908 | J37: 17475 | K37: 1.7789 | L37: 31086.28 | M37: ORORA | N37: Filling OP | O37: FALSE | P37: SO | R37: Orora Business Service Center | S37: 13397 Marlay Ave Ste A | U37: CA | V37: 92337-6946 | X37: 0 | Z37: Landsberg-Fullfillment Solutions | AA37: Fontana | AB37: Need special certificate COA before shipped | AC37: PCI-01 | AD37: STRUKMYER, LLC
A38: 45987 | B38: 46097 | C38: 46077 | D38: 46090 | E38: 0000064788 | F38: 1 | G38: ICS | H38: 007154 | I38: URGO - VASHE 475 ml Flip Top 00314 | J38: 30000 | K38: 2.59 | L38: 77700 | M38: URGO | N38: Filling OP | O38: FALSE | P38: SO | R38: URGO Medical | S38: 167 International Blvd, Suite 550 | U38: KY | V38: 40109 | X38: 0 | Z38: ICS (Urgo Medical) | AA38: Brooks | AB38: ReceivingBrooks@icsconnect.com
A39: 502-955-3671" | B39: PCI-01 | C39: STRUKMYER, LLC
A40: 45594 | B40: 45685 | C40: 46078 | D40: 45709 | E40: 0000063455 | F40: 30 | G40: C02 | H40: 006011 | I40: MEDLINE CURAD MEDISTRIP 1/4 X 4 IN STERILE NON250414 | J40: 182 | K40: 127.14 | L40: 23139.48 | M40: MEDL | N40: MEDICAL | O40: FALSE | P40: SO | R40: Medline Industries, Inc. | S40: 2200 Cornerstone Pkwy, Ste 100 | U40: IL | V40: 60030 | X40: 0 | Z40: Medline Industries LP | AA40: Grayslake | AC40: PCI-01 | AD40: STRUKMYER, LLC
A41: 45618 | B41: 45709 | C41: 46078 | D41: 45709 | E41: 0000063558 | F41: 10 | G41: B25 | H41: 006011 | I41: MEDLINE CURAD MEDISTRIP 1/4 X 4 IN STERILE NON250414 | J41: 26 | K41: 127.14 | L41: 3305.64 | M41: MEDL | N41: MEDICAL | O41: FALSE | P41: SO | R41: Medline Industries, Inc. | S41: 1401 N. Universal Ave. | U41: MO | V41: 641202139 | X41: 0 | Z41: Medline Industries LP | AA41: KANSAS CITY | AC41: PCI-01 | AD41: STRUKMYER, LLC
A42: 45618 | B42: 45709 | C42: 46078 | D42: 45709 | E42: 0000063559 | F42: 30 | G42: C57 | H42: 006011 | I42: MEDLINE CURAD MEDISTRIP 1/4 X 4 IN STERILE NON250414 | J42: 8 | K42: 127.14 | L42: 1017.12 | M42: MEDL | N42: MEDICAL | O42: FALSE | P42: SO | R42: Medline Industries, Inc. | S42: 5511 West Ten Rd | U42: NC | V42: 27302 | X42: 0 | Z42: Medline Industries LP | AA42: Mebane | AC42: PCI-01 | AD42: STRUKMYER, LLC
A43: 45636 | B43: 45726 | C43: 46078 | D43: 45761 | E43: 0000063612 | F43: 60 | G43: C09 | H43: 006011 | I43: MEDLINE CURAD MEDISTRIP 1/4 X 4 IN STERILE NON250414 | J43: 104 | K43: 127.14 | L43: 13222.56 | M43: MEDL | N43: MEDICAL | O43: FALSE | P43: SO | R43: Medline Industries, Inc. | S43: 1960 W Miro Way | U43: CA | V43: 92376 | X43: 0 | Z43: Medline Industries LP | AA43: Rialto | AC43: PCI-01 | AD43: STRUKMYER, LLC
A44: 45706 | B44: 45790 | C44: 46078 | D44: 45919 | E44: 0000063836 | F44: 10 | G44: C47 | H44: 006013 | I44: MEDLINE CURAD MEDI STRIP 1 X 5 NON250501 | J44: 3 | K44: 123 | L44: 369 | M44: MEDL | N44: MEDICAL | O44: FALSE | P44: SO | R44: Medline Industries, Inc. | S44: 239 Belvidere Rd | U44: MD | V44: 21903 | X44: 0 | Z44: Medline Industries LP | AA44: Perryville | AC44: PCI-01 | AD44: STRUKMYER, LLC
A45: 45706 | B45: 45790 | C45: 46078 | D45: 45919 | E45: 0000063843 | F45: 20 | G45: B11 | H45: 006013 | I45: MEDLINE CURAD MEDI STRIP 1 X 5 NON250501 | J45: 1 | K45: 123 | L45: 123 | M45: MEDL | N45: MEDICAL | O45: FALSE | P45: SO | R45: Medline Industries, Inc. | S45: 21111 E. 36th Drive | U45: CO | V45: 80011 | X45: 0 | Z45: Medline Industries LP | AA45: Aurora | AC45: PCI-01 | AD45: STRUKMYER, LLC
A46: 45706 | B46: 45790 | C46: 46078 | D46: 45919 | E46: 0000063854 | F46: 20 | G46: C02 | H46: 006013 | I46: MEDLINE CURAD MEDI STRIP 1 X 5 NON250501 | J46: 5 | K46: 123 | L46: 615 | M46: MEDL | N46: MEDICAL | O46: FALSE | P46: SO | R46: Medline Industries, Inc. | S46: 2200 Cornerstone Pkwy, Ste 100 | U46: IL | V46: 60030 | X46: 0 | Z46: Medline Industries LP | AA46: Grayslake | AC46: PCI-01 | AD46: STRUKMYER, LLC
A47: 45706 | B47: 45790 | C47: 46078 | D47: 45919 | E47: 0000063855 | F47: 10 | G47: B01 | H47: 006013 | I47: MEDLINE CURAD MEDI STRIP 1 X 5 NON250501 | J47: 37 | K47: 123 | L47: 4551 | M47: MEDL | N47: MEDICAL | O47: FALSE | P47: SO | R47: Medline Industries, Inc. | S47: 1200 Townline Rd. | U47: IL | V47: 60060 | X47: 0 | Z47: Medline Industries LP | AA47: Mundelein | AC47: PCI-01 | AD47: STRUKMYER, LLC
A48: 45720 | B48: 45805 | C48: 46078 | D48: 45919 | E48: 0000063882 | F48: 20 | G48: C40 | H48: 006013 | I48: MEDLINE CURAD MEDI STRIP 1 X 5 NON250501 | J48: 5 | K48: 123 | L48: 615 | M48: MEDL | N48: MEDICAL | O48: FALSE | P48: SO | R48: Medline Industries, Inc. | S48: 81 Campanelli Drive | U48: MA | V48: 01569 | X48: 0 | Z48: Medline Industries LP | AA48: UXBRIDGE | AC48: PCI-01 | AD48: STRUKMYER, LLC
A49: 45720 | B49: 45805 | C49: 46078 | D49: 45919 | E49: 0000063883 | F49: 30 | G49: B06 | H49: 006013 | I49: MEDLINE CURAD MEDI STRIP 1 X 5 NON250501 | J49: 9 | K49: 123 | L49: 1107 | M49: MEDL | N49: MEDICAL | O49: FALSE | P49: SO | R49: Medline Industries, Inc. | S49: 1 Medline Drive, Suite 100 | U49: TX | V49: 75172 | X49: 0 | Z49: Medline Industries LP | AA49: Wilmer | AC49: PCI-01 | AD49: STRUKMYER, LLC
A50: 45720 | B50: 45805 | C50: 46078 | D50: 45919 | E50: 0000063885 | F50: 10 | G50: B11 | H50: 006013 | I50: MEDLINE CURAD MEDI STRIP 1 X 5 NON250501 | J50: 3 | K50: 123 | L50: 369 | M50: MEDL | N50: MEDICAL | O50: FALSE | P50: SO | R50: Medline Industries, Inc. | S50: 21111 E. 36th Drive | U50: CO | V50: 80011 | X50: 0 | Z50: Medline Industries LP | AA50: Aurora | AC50: PCI-01 | AD50: STRUKMYER, LLC
A51: 45720 | B51: 45805 | C51: 46078 | D51: 45919 | E51: 0000063886 | F51: 30 | G51: C50 | H51: 006013 | I51: MEDLINE CURAD MEDI STRIP 1 X 5 NON250501 | J51: 2 | K51: 123 | L51: 246 | M51: MEDL | N51: MEDICAL | O51: FALSE | P51: SO | R51: Medline Industries, Inc. | S51: 8787 W BUCKEYE RD | U51: AZ | V51: 853539399 | X51: 0 | Z51: Medline Industries LP | AA51: TOLLESON | AC51: PCI-01 | AD51: STRUKMYER, LLC
... A55: 45720 | B55: 45805 | C55: 46078 | D55: 45919 | E55: 0000063891 | F55: 30 | G55: B24 | H55: 006013 | I55: MEDLINE CURAD MEDI STRIP 1 X 5 NON250501 | J55: 8 | K55: 123 | L55: 984 | M55: MEDL | N55: MEDICAL | O55: FALSE | P55: SO | R55: Medline Industries, Inc. | S55: 8001 SW 47th St. | U55: OK | V55: 73179 | X55: 0 | Z55: Medline Industries LP | AA55: Oklahoma City | AC55: PCI-01 | AD55: STRUKMYER, LLC
A56: 45720 | B56: 45805 | C56: 46078 | D56: 45919 | E56: 0000063892 | F56: 20 | G56: C54 | H56: 006013 | I56: MEDLINE CURAD MEDI STRIP 1 X 5 NON250501 | J56: 4 | K56: 123 | L56: 492 | M56: MEDL | N56: MEDICAL | O56: FALSE | P56: SO | R56: Medline Industries, Inc. | S56: 494 State Route 416 | T56: 494 State Route 416 | U56: NY | V56: 12549 | X56: 0 | Z56: Medline Industries LP | AA56: Montgomery | AC56: PCI-01 | AD56: STRUKMYER, LLC
A57: 45720 | B57: 45805 | C57: 46078 | D57: 45919 | E57: 0000063897 | F57: 20 | G57: C59 | H57: 006013 | I57: MEDLINE CURAD MEDI STRIP 1 X 5 NON250501 | J57: 2 | K57: 123 | L57: 246 | M57: MEDL | N57: MEDICAL | O57: FALSE | P57: SO | R57: Medline Industries, Inc. | S57: 2100 Industrial Park Rd | U57: LA | V57: 70401 | X57: 0 | Z57: Medline Industries, LP | AA57: Hammond | AC57: PCI-01 | AD57: STRUKMYER, LLC
A58: 45720 | B58: 45805 | C58: 46078 | D58: 45919 | E58: 0000063899 | F58: 10 | G58: C02 | H58: 006013 | I58: MEDLINE CURAD MEDI STRIP 1 X 5 NON250501 | J58: 6 | K58: 123 | L58: 738 | M58: MEDL | N58: MEDICAL | O58: FALSE | P58: SO | R58: Medline Industries, Inc. | S58: 2200 Cornerstone Pkwy, Ste 100 | U58: IL | V58: 60030 | X58: 0 | Z58: Medline Industries LP | AA58: Grayslake | AC58: PCI-01 | AD58: STRUKMYER, LLC
A59: 45720 | B59: 45805 | C59: 46078 | D59: 45919 | E59: 0000063901 | F59: 20 | G59: B25 | H59: 006013 | I59: MEDLINE CURAD MEDI STRIP 1 X 5 NON250501 | J59: 8 | K59: 123 | L59: 984 | M59: MEDL | N59: MEDICAL | O59: FALSE | P59: SO | R59: Medline Industries, Inc. | S59: 1401 N. Universal Ave. | U59: MO | V59: 641202139 | X59: 0 | Z59: Medline Industries LP | AA59: KANSAS CITY | AC59: PCI-01 | AD59: STRUKMYER, LLC
A60: 45720 | B60: 45805 | C60: 46078 | D60: 45919 | E60: 0000063902 | F60: 20 | G60: K46 | H60: 006013 | I60: MEDLINE CURAD MEDI STRIP 1 X 5 NON250501 | J60: 1 | K60: 123 | L60: 123 | M60: MEDL | N60: MEDICAL | O60: FALSE | P60: SO | R60: Medline Industries, Inc. | S60: 18601 Christopher Way, STE 100 | T60: 18601 Christopher Way, STE 100 | U60: CA | V60: 95330 | X60: 0 | Z60: Medline Industries, Inc. | AA60: Lathrop | AC60: PCI-01 | AD60: STRUKMYER, LLC
A61: 45726 | B61: 46006 | C61: 46078 | D61: 46006 | E61: 0000063917 | F61: 1 | H61: 005342 | I61: ISI LARGE ALUMI-HAND 760 | J61: 6900 | K61: 7.7 | L61: 53130 | M61: ISI | N61: MEDICAL | O61: FALSE | P61: SO | R61: Instrument Specialists Inc | S61: 32390 IH 10 West | U61: TX | V61: 78006 | X61: 0 | Z61: Instrument Specialists Inc | AA61: Boerne | AC61: PCI-01 | AD61: STRUKMYER, LLC
A62: 45734 | B62: 45819 | C62: 46078 | D62: 45919 | E62: 0000063941 | F62: 30 | G62: B06 | H62: 006013 | I62: MEDLINE CURAD MEDI STRIP 1 X 5 NON250501 | J62: 4 | K62: 123 | L62: 492 | M62: MEDL | N62: MEDICAL | O62: FALSE | P62: SO | R62: Medline Industries, Inc. | S62: 1 Medline Drive, Suite 100 | U62: TX | V62: 75172 | X62: 0 | Z62: Medline Industries LP | AA62: Wilmer | AC62: PCI-01 | AD62: STRUKMYER, LLC
A63: 45734 | B63: 45819 | C63: 46078 | D63: 45919 | E63: 0000063942 | F63: 10 | G63: K46 | H63: 006013 | I63: MEDLINE CURAD MEDI STRIP 1 X 5 NON250501 | J63: 1 | K63: 123 | L63: 123 | M63: MEDL | N63: MEDICAL | O63: FALSE | P63: SO | R63: Medline Industries, Inc. | S63: 18601 Christopher Way, STE 100 | T63: 18601 Christopher Way, STE 100 | U63: CA | V63: 95330 | X63: 0 | Z63: Medline Industries, Inc. | AA63: Lathrop | AC63: PCI-01 | AD63: STRUKMYER, LLC
A64: 45734 | B64: 45819 | C64: 46078 | D64: 45919 | E64: 0000063943 | F64: 30 | G64: C32 | H64: 006013 | I64: MEDLINE CURAD MEDI STRIP 1 X 5 NON250501 | J64: 3 | K64: 123 | L64: 369 | M64: MEDL | N64: MEDICAL | O64: FALSE | P64: SO | R64: Medline Industries, Inc. | S64: 29895 US HWY 90 BUS | U64: TX | V64: 77494 | X64: 0 | Z64: Medline Industries LP | AA64: Katy | AC64: PCI-01 | AD64: STRUKMYER, LLC
A65: 45734 | B65: 45819 | C65: 46078 | D65: 45919 | E65: 0000063945 | F65: 10 | G65: C37 | H65: 006013 | I65: MEDLINE CURAD MEDI STRIP 1 X 5 NON250501 | J65: 3 | K65: 123 | L65: 369 | M65: MEDL | N65: MEDICAL | O65: FALSE | P65: SO | R65: Medline Industries, Inc. | S65: 5000 Premier Pkwy Ste 100 | U65: MO | V65: 63376 | X65: 0 | Z65: Medline Industries LP | AA65: Saint Peters | AC65: PCI-01 | AD65: STRUKMYER, LLC
A66: 45734 | B66: 45819 | C66: 46078 | D66: 45919 | E66: 0000063947 | F66: 40 | G66: C02 | H66: 006013 | I66: MEDLINE CURAD MEDI STRIP 1 X 5 NON250501 | J66: 4 | K66: 123 | L66: 492 | M66: MEDL | N66: MEDICAL | O66: FALSE | P66: SO | R66: Medline Industries, Inc. | S66: 2200 Cornerstone Pkwy, Ste 100 | U66: IL | V66: 60030 | X66: 0 | Z66: Medline Industries LP | AA66: Grayslake | AC66: PCI-01 | AD66: STRUKMYER, LLC
A67: 45734 | B67: 45819 | C67: 46078 | D67: 45919 | E67: 0000063948 | F67: 10 | G67: B25 | H67: 006013 | I67: MEDLINE CURAD MEDI STRIP 1 X 5 NON250501 | J67: 4 | K67: 123 | L67: 492 | M67: MEDL | N67: MEDICAL | O67: FALSE | P67: SO | R67: Medline Industries, Inc. | S67: 1401 N. Universal Ave. | U67: MO | V67: 641202139 | X67: 0 | Z67: Medline Industries LP | AA67: KANSAS CITY | AC67: PCI-01 | AD67: STRUKMYER, LLC
A68: 45734 | B68: 45819 | C68: 46078 | D68: 45919 | E68: 0000063949 | F68: 10 | G68: C40 | H68: 006013 | I68: MEDLINE CURAD MEDI STRIP 1 X 5 NON250501 | J68: 2 | K68: 123 | L68: 246 | M68: MEDL | N68: MEDICAL | O68: FALSE | P68: SO | R68: Medline Industries, Inc. | S68: 81 Campanelli Drive | U68: MA | V68: 01569 | X68: 0 | Z68: Medline Industries LP | AA68: UXBRIDGE | AC68: PCI-01 | AD68: STRUKMYER, LLC
A69: 45734 | B69: 45819 | C69: 46078 | D69: 45919 | E69: 0000063951 | F69: 10 | G69: C57 | H69: 006013 | I69: MEDLINE CURAD MEDI STRIP 1 X 5 NON250501 | J69: 4 | K69: 123 | L69: 492 | M69: MEDL | N69: MEDICAL | O69: FALSE | P69: SO | R69: Medline Industries, Inc. | S69: 5511 West Ten Rd | U69: NC | V69: 27302 | X69: 0 | Z69: Medline Industries LP | AA69: Mebane | AC69: PCI-01 | AD69: STRUKMYER, LLC
A70: 45734 | B70: 45819 | C70: 46078 | D70: 45919 | E70: 0000063955 | F70: 10 | G70: B01 | H70: 006013 | I70: MEDLINE CURAD MEDI STRIP 1 X 5 NON250501 | J70: 6 | K70: 123 | L70: 738 | M70: MEDL | N70: MEDICAL | O70: FALSE | P70: SO | R70: Medline Industries, Inc. | S70: 1200 Townline Rd. | U70: IL | V70: 60060 | X70: 0 | Z70: Medline Industries LP | AA70: Mundelein | AC70: PCI-01 | AD70: STRUKMYER, LLC
A71: 45734 | B71: 45819 | C71: 46078 | D71: 45919 | E71: 0000063957 | F71: 10 | G71: C71 | H71: 006013 | I71: MEDLINE CURAD MEDI STRIP 1 X 5 NON250501 | J71: 1 | K71: 123 | L71: 123 | M71: MEDL | N71: MEDICAL | O71: FALSE | P71: SO | R71: Medline Industries, Inc. | S71: 264 South 5750 West | U71: UT | V71: 84104 | X71: 0 | Z71: MEDLINE INDUSTRIES, Inc. | AA71: Salt Lake City | AC71: PCI-01 | AD71: STRUKMYER, LLC
A72: 45734 | B72: 45819 | C72: 46078 | D72: 45919 | E72: 0000063960 | F72: 10 | G72: B11 | H72: 006013 | I72: MEDLINE CURAD MEDI STRIP 1 X 5 NON250501 | J72: 1 | K72: 123 | L72: 123 | M72: MEDL | N72: MEDICAL | O72: FALSE | P72: SO | R72: Medline Industries, Inc. | S72: 21111 E. 36th Drive | U72: CO | V72: 80011 | X72: 0 | Z72: Medline Industries LP | AA72: Aurora | AC72: PCI-01 | AD72: STRUKMYER, LLC
A73: 45734 | B73: 45819 | C73: 46078 | D73: 45919 | E73: 0000063961 | F73: 20 | G73: C54 | H73: 006013 | I73: MEDLINE CURAD MEDI STRIP 1 X 5 NON250501 | J73: 4 | K73: 123 | L73: 492 | M73: MEDL | N73: MEDICAL | O73: FALSE | P73: SO | R73: Medline Industries, Inc. | S73: 494 State Route 416 | T73: 494 State Route 416 | U73: NY | V73: 12549 | X73: 0 | Z73: Medline Industries LP | AA73: Montgomery | AC73: PCI-01 | AD73: STRUKMYER, LLC
A74: 45734 | B74: 45819 | C74: 46078 | D74: 45919 | E74: 0000063962 | F74: 30 | G74: C09 | H74: 006013 | I74: MEDLINE CURAD MEDI STRIP 1 X 5 NON250501 | J74: 4 | K74: 123 | L74: 492 | M74: MEDL | N74: MEDICAL | O74: FALSE | P74: SO | R74: Medline Industries, Inc. | S74: 1960 W Miro Way | U74: CA | V74: 92376 | X74: 0 | Z74: Medline Industries LP | AA74: Rialto | AC74: PCI-01 | AD74: STRUKMYER, LLC
A75: 45734 | B75: 45819 | C75: 46078 | D75: 45919 | E75: 0000063963 | F75: 30 | G75: C41 | H75: 006013 | I75: MEDLINE CURAD MEDI STRIP 1 X 5 NON250501 | J75: 2 | K75: 123 | L75: 246 | M75: MEDL | N75: MEDICAL | O75: FALSE | P75: SO | R75: Medline Industries, Inc. | S75: 1040 Enterprise Parkway | U75: OH | V75: 43162 | X75: 0 | Z75: Medline Industries LP | AA75: West Jefferson | AC75: PCI-01 | AD75: STRUKMYER, LLC
A76: 45734 | B76: 45819 | C76: 46078 | D76: 45919 | E76: 0000063964 | F76: 30 | G76: C50 | H76: 006013 | I76: MEDLINE CURAD MEDI STRIP 1 X 5 NON250501 | J76: 6 | K76: 123 | L76: 738 | M76: MEDL | N76: MEDICAL | O76: FALSE | P76: SO | R76: Medline Industries, Inc. | S76: 8787 W BUCKEYE RD | U76: AZ | V76: 853539399 | X76: 0 | Z76: Medline Industries LP | AA76: TOLLESON | AC76: PCI-01 | AD76: STRUKMYER, LLC
A77: 45757 | B77: 45961 | C77: 46078 | D77: 45961 | E77: 0000064057 | F77: 1 | G77: 3440 | H77: 005045 | I77: FREUDENBERG 30cm X 47cm Nonwoven Sheets 122P0463 | J77: 25000 | K77: 1.63 | L77: 40750 | M77: FREUD | N77: MEDICAL | O77: FALSE | P77: SO | R77: Freudenberg Performance Materials LP | S77: 3440 Industrial Drive | U77: NC | V77: 27704 | X77: 0 | Z77: Freudenberg Performance Materials LP | AA77: Durham | AB77: **DO NOT DOUBLE STACK LABEL - TAKE PHOTO**
A78: SHIP VIA CH ROBINSON. CONTACT Dustin Seong 813-840-4526 OR dustin.seong@chrobinson.com. Freight is 3rd party bill to Freudenberg
A79: Receiving hours M-F 8am -4pm
A80: PCI-01 STRUKMYER | B80: LLC"
A81: 45761 | B81: 45847 | C81: 46078 | D81: 45919 | E81: 0000064069 | F81: 10 | G81: K46 | H81: 006013 | I81: MEDLINE CURAD MEDI STRIP 1 X 5 NON250501 | J81: 13 | K81: 123 | L81: 1599 | M81: MEDL | N81: MEDICAL | O81: FALSE | P81: SO | R81: Medline Industries, Inc. | S81: 18601 Christopher Way, STE 100 | T81: 18601 Christopher Way, STE 100 | U81: CA | V81: 95330 | X81: 0 | Z81: Medline Industries, Inc. | AA81: Lathrop | AC81: PCI-01 | AD81: STRUKMYER, LLC
A82: 45761 | B82: 45847 | C82: 46078 | D82: 45919 | E82: 0000064070 | F82: 30 | G82: B24 | H82: 006013 | I82: MEDLINE CURAD MEDI STRIP 1 X 5 NON250501 | J82: 4 | K82: 123 | L82: 492 | M82: MEDL | N82: MEDICAL | O82: FALSE | P82: SO | R82: Medline Industries, Inc. | S82: 8001 SW 47th St. | U82: OK | V82: 73179 | X82: 0 | Z82: Medline Industries LP | AA82: Oklahoma City | AC82: PCI-01 | AD82: STRUKMYER, LLC
A83: 45761 | B83: 45847 | C83: 46078 | D83: 45919 | E83: 0000064075 | F83: 10 | G83: B27 | H83: 006013 | I83: MEDLINE CURAD MEDI STRIP 1 X 5 NON250501 | J83: 3 | K83: 123 | L83: 369 | M83: MEDL | N83: MEDICAL | O83: FALSE | P83: SO | R83: Medline Industries, Inc. | S83: 92 Southeast 223rd Avenue | U83: OR | V83: 97030 | X83: 0 | Z83: Medline Industries LP | AA83: Gresham | AC83: PCI-01 | AD83: STRUKMYER, LLC
A84: 45761 | B84: 45847 | C84: 46078 | D84: 45919 | E84: 0000064076 | F84: 60 | G84: B06 | H84: 006013 | I84: MEDLINE CURAD MEDI STRIP 1 X 5 NON250501 | J84: 10 | K84: 123 | L84: 1230 | M84: MEDL | N84: MEDICAL | O84: FALSE | P84: SO | R84: Medline Industries, Inc. | S84: 1 Medline Drive, Suite 100 | U84: TX | V84: 75172 | X84: 0 | Z84: Medline Industries LP | AA84: Wilmer | AC84: PCI-01 | AD84: STRUKMYER, LLC
A85: 45761 | B85: 45847 | C85: 46078 | D85: 45919 | E85: 0000064077 | F85: 40 | G85: C54 | H85: 006013 | I85: MEDLINE CURAD MEDI STRIP 1 X 5 NON250501 | J85: 7 | K85: 123 | L85: 861 | M85: MEDL | N85: MEDICAL | O85: FALSE | P85: SO | R85: Medline Industries, Inc. | S85: 494 State Route 416 | T85: 494 State Route 416 | U85: NY | V85: 12549 | X85: 0 | Z85: Medline Industries LP | AA85: Montgomery | AC85: PCI-01 | AD85: STRUKMYER, LLC
A86: 45761 | B86: 45847 | C86: 46078 | D86: 45919 | E86: 0000064080 | F86: 20 | G86: C75 | H86: 006013 | I86: MEDLINE CURAD MEDI STRIP 1 X 5 NON250501 | J86: 19 | K86: 123 | L86: 2337 | M86: MEDL | N86: MEDICAL | O86: FALSE | P86: SO | R86: Medline Industries, Inc. | S86: 3770 Hogum Bay Road Ne | U86: WA | V86: 98516 | X86: 0 | Z86: Medline Industries LP | AA86: Lacey | AC86: PCI-01 | AD86: STRUKMYER, LLC
A87: 45909 | B87: 46025 | C87: 46078 | D87: 46073 | E87: 0000064548 | F87: 1 | G87: IRELAND | H87: 007235 | I87: HARMAC PRTD DRAPE ASSEMBLY P3113231 REV.A (ROW) | J87: 60000 | K87: 0.5211 | L87: 31266 | M87: HARM IRE | N87: Drape&Mask | O87: FALSE | P87: SO | R87: Harmac Medical Products | S87: IDA Business Park | U87: .. | V87: ... | X87: 0 | Z87: Harmac Medical Products | AA87: Castlerea, County Roscommon | AB87: use expeditors***Heat treated Pallets
A88: Must include Shippers letter of instruction" | B88: PCI-01 | C88: STRUKMYER, LLC
A89: 45912 | B89: 46087 | C89: 46078 | D89: 46087 | E89: 0000064559 | F89: 1 | G89: IRELAND | H89: 003958 | I89: Harmac Filter Disc P3113306 Rev E | J89: 202500 | K89: 0.27 | L89: 54675 | M89: HARM IRE | N89: MEDICAL | O89: FALSE | P89: SO | R89: Harmac Medical Products | S89: IDA Business Park | U89: .. | V89: ... | X89: 0 | Z89: Harmac Medical Products | AA89: Castlerea, County Roscommon | AB89: use expeditors***Heat treated Pallets
A90: Must include Shippers letter of instruction" | B90: PCI-01 | C90: STRUKMYER, LLC
A91: 45915 | B91: 46056 | C91: 46078 | D91: 46073 | E91: 0000064562 | F91: 1 | G91: IRELAND | H91: 007235 | I91: HARMAC PRTD DRAPE ASSEMBLY P3113231 REV.A (ROW) | J91: 60000 | K91: 0.5211 | L91: 31266 | M91: HARM IRE | N91: Drape&Mask | O91: FALSE | P91: SO | R91: Harmac Medical Products | S91: IDA Business Park | U91: .. | V91: ... | X91: 0 | Z91: Harmac Medical Products | AA91: Castlerea, County Roscommon | AB91: use expeditors***Heat treated Pallets
A92: Must include Shippers letter of instruction" | B92: PCI-01 | C92: STRUKMYER, LLC
A93: 45925 | B93: 46043 | C93: 46078 | D93: 46043 | E93: 0000064618 | F93: 5 | G93: ATLANTA | H93: 007487 | I93: CARDINAL HEALTH TELFA ADHESIVE DRESSING 2"x3" 6017 | J93: 300 | K93: 269.76 | L93: 80928 | M93: COVIDMA | N93: MEDICAL | O93: FALSE | P93: SO | R93: Patient Recovery | S93: 110 Kendall Park Lane | U93: GA | V93: 30336 | X93: 0 | Z93: Atlanta RC - US | AA93: Atlanta | AB93: **Effective 7/28/18 www.routingguides.com/cardinal%20health
A94: For Small orders and LTL use fedex 3rd party 920710310 | B94: less than or equal to 150lbs | C94: refer to LTL/TL routing guide *requires special cert*" | D94: PCI-01 | E94: STRUKMYER, LLC
A95: 45987 | B95: 46125 | C95: 46078 | D95: 46093 | E95: 0000064787 | F95: 2 | G95: ICS | H95: 007155 | I95: URGO - VASHE 250 ml Instill 00316 | J95: 6000 | K95: 4.34 | L95: 26040 | M95: URGO | N95: Filling OP | O95: FALSE | P95: SO | R95: URGO Medical | S95: 167 International Blvd, Suite 550 | U95: KY | V95: 40109 | X95: 0 | Z95: ICS (Urgo Medical) | AA95: Brooks | AB95: ReceivingBrooks@icsconnect.com
A96: 502-955-3671" | B96: PCI-01 | C96: STRUKMYER, LLC
A97: 45987 | B97: 46125 | C97: 46078 | D97: 46093 | E97: 0000064787 | F97: 3 | G97: ICS | H97: 007159 | I97: URGO - VASHE 250 ml OTC Flip Top 00405 | J97: 5004 | K97: 1.95 | L97: 9757.8 | M97: URGO | N97: Filling OP | O97: FALSE | P97: SO | R97: URGO Medical | S97: 167 International Blvd, Suite 550 | U97: KY | V97: 40109 | X97: 0 | Z97: ICS (Urgo Medical) | AA97: Brooks | AB97: ReceivingBrooks@icsconnect.com
A98: 502-955-3671" | B98: PCI-01 | C98: STRUKMYER, LLC
A99: 46072 | B99: 2 | C99: 46078 | D99: 46079 | E99: 0000065008 | F99: 1 | G99: BILL | H99: F-22004 | I99: 5 SITE SEMI-OCCLUSIVE STRIP | J99: 16000 | K99: 0.41 | L99: 6560 | M99: MONADERM | N99: MEDICAL | O99: FALSE | P99: SO | R99: Monaderm | S99: 5, rue des Violettes | U99: .. | V99: .... | X99: 0 | Z99: Monaderm | AA99: 98000 Monaco | AB99: Please select UPS Expedited or UPS Standard for shipping | AC99: PCI-01 | AD99: STRUKMYER, LLC
A100: 45692 | B100: 45795 | C100: 46079 | D100: 45884 | E100: 0000063804 | F100: 1 | G100: LAREDO | H100: 006008 | I100: MEDLINE CURAD MEDISTRIP 1/4 X 1.5 IN, STERILE NON250114 | J100: 1 | K100: 71.94 | L100: 71.94 | M100: MEDL | N100: MEDICAL | O100: FALSE | P100: SO | R100: Medline Industries, Inc. | S100: 12001 General Milton Dr | U100: TX | V100: 78045 | X100: 1 | Z100: Medline Industries | AA100: Laredo | AB100: This location will be inactive Effective 7/17/17. new location 12001 General Milton Dr. Laredo, TX . If customer request NDA - use Fedex Collect # 326382027 | AC100: PCI-01 | AD100: STRUKMYER, LLC
A101: 45706 | B101: 45790 | C101: 46079 | D101: 45884 | E101: 0000063833 | F101: 10 | G101: C50 | H101: 006008 | I101: MEDLINE CURAD MEDISTRIP 1/4 X 1.5 IN, STERILE NON250114 | J101: 20 | K101: 71.94 | L101: 1438.8 | M101: MEDL | N101: MEDICAL | O101: FALSE | P101: SO | R101: Medline Industries, Inc. | S101: 8787 W BUCKEYE RD | U101: AZ | V101: 853539399 | X101: 1 | Z101: Medline Industries LP | AA101: TOLLESON | AC101: PCI-01 | AD101: STRUKMYER, LLC
A102: 45713 | B102: 45818 | C102: 46079 | D102: 45884 | E102: 0000063874 | F102: 1 | G102: LAREDO | H102: 006008 | I102: MEDLINE CURAD MEDISTRIP 1/4 X 1.5 IN, STERILE NON250114 | J102: 2 | K102: 71.94 | L102: 143.88 | M102: MEDL | N102: MEDICAL | O102: FALSE | P102: SO | R102: Medline Industries, Inc. | S102: 12001 General Milton Dr | U102: TX | V102: 78045 | X102: 1 | Z102: Medline Industries | AA102: Laredo | AB102: This location will be inactive Effective 7/17/17. new location 12001 General Milton Dr. Laredo, TX . If customer request NDA - use Fedex Collect # 326382027 | AC102: PCI-01 | AD102: STRUKMYER, LLC
A103: 45720 | B103: 45805 | C103: 46079 | D103: 45884 | E103: 0000063886 | F103: 10 | G103: C50 | H103: 006008 | I103: MEDLINE CURAD MEDISTRIP 1/4 X 1.5 IN, STERILE NON250114 | J103: 7 | K103: 71.94 | L103: 503.58 | M103: MEDL | N103: MEDICAL | O103: FALSE | P103: SO | R103: Medline Industries, Inc. | S103: 8787 W BUCKEYE RD | U103: AZ | V103: 853539399 | X103: 1 | Z103: Medline Industries LP | AA103: TOLLESON | AC103: PCI-01 | AD103: STRUKMYER, LLC
A104: 45720 | B104: 45805 | C104: 46079 | D104: 45884 | E104: 0000063889 | F104: 20 | G104: C32 | H104: 006008 | I104: MEDLINE CURAD MEDISTRIP 1/4 X 1.5 IN, STERILE NON250114 | J104: 6 | K104: 71.94 | L104: 431.64 | M104: MEDL | N104: MEDICAL | O104: FALSE | P104: SO | R104: Medline Industries, Inc. | S104: 29895 US HWY 90 BUS | U104: TX | V104: 77494 | X104: 1 | Z104: Medline Industries LP | AA104: Katy | AC104: PCI-01 | AD104: STRUKMYER, LLC
...

Sheet Raw data w lookup
L2: =SUBTOTAL(9, L4:L1452) -> 9065728.6
A3: Order date | B3: Requested Ship date | C3: ScheduledShipDate | D3: PromisedShipDate | E3: SONumber | F3: LineNumber | G3: ShipToCode | H3: ItemCode | I3: ItemDescription | J3: OrderQuantity | K3: UnitPrice | L3: ExtendedLineAmount | M3: CustomerCode | N3: ItemSalesClassCode | O3: DropShip | P3: SOTypeCode | Q3: FinalDestination | R3: CustomerName | S3: ShipToAddress1 | T3: ShipToAddress2 | U3: ShipToStateCode | V3: ShipToZip | W3: ParentDocumentNumber | X3: Weight | Y3: OrderMessage | Z3: ShipToName | AA3: ShipToCity | AB3: ShippingInstructions | AC3: WarehouseCode | AD3: WarehouseName | AE3: Profit
A4: 45944 | B4: 46034 | C4: 2 | D4: 46050 | E4: 0000064684 | F4: 1 | G4: MAYNARD | H4: 3843 | I4: DeRoyal Episeal Tan 3 Inch Non-Reinforced Material | J4: 28000 | K4: 0.396 | L4: 11088 | M4: DEROYAL | N4: MEDICAL | O4: FALSE | P4: SO | R4: DeRoyal Accounts Payable Dept | S4: 185 Richardson Way | U4: TN | V4: 37807 | X4: 0 | Z4: DeRoyal Foam/ Convertin | AA4: Maynardville | AC4: PCI-01 | AE4: =J4*VLOOKUP(H4,'Cost sheet'!$C$2:$G$1232,5,FALSE) -> 7710.752
A5: 45974 | B5: 45996 | C5: 2 | D5: 2 | E5: 0000064757 | F5: 2 | G5: LAND | H5: 6370 | I5: TB DRY MOUTH TINGLING RINSE 16 OZ BULK 40101908 | J5: 20000 | K5: 1.7789 | L5: 35578 | M5: ORORA | N5: Filling OP | O5: FALSE | P5: SO | R5: Orora Business Service Center | S5: 13397 Marlay Ave Ste A | U5: CA | V5: 92337-6946 | X5: 0 | Z5: Landsberg-Fullfillment Solutions | AA5: Fontana | AB5: Need special certificate COA before shipped | AC5: PCI-01 | AE5: =J5*VLOOKUP(H5,'Cost sheet'!$C$2:$G$1232,5,FALSE) -> 13112.86
A6: 46020 | B6: 46089 | C6: 2 | D6: 2 | E6: 0000064846 | F6: 1 | G6: lawson | H6: 5121 | I6: IMPLUS CANADA BLISTER PADS 4740700 | J6: 15600 | K6: 2.9 | L6: 45240 | M6: IMPLUS CAN | N6: MEDICAL | O6: FALSE | P6: SO | R6: Implus Canada | S6: 8399 LAWSON ROAD, UNIT 104 | U6: ON | V6: L9T9L1 | X6: 0 | Z6: SPENCO CANADA/IMPLUS CANADA | AA6: MILTON | AB6: For all Collect shipments to Implus Canada email Graham Patterson gpatterson@4implus.com, Shipments@4implus.com, and our Canadian carrier One For Freight support team at Implus@oneforfreight.com. | AE6: =J6*VLOOKUP(H6,'Cost sheet'!$C$2:$G$1232,5,FALSE) -> 19753.25
A7: 46042 | B7: 2 | C7: 2 | D7: 2 | E7: 0000064923 | F7: 1 | H7: N-4001 | I7: 1,000 L Obelix Bulk Wound Wash Solution | J7: 1 | K7: 2912 | L7: 2912 | M7: URGO | N7: MEDICAL | O7: FALSE | P7: SO | R7: URGO Medical | S7: 100 Lexington Street, Suite 400 | U7: TX | V7: 76102 | X7: 0 | Z7: URGO Medical | AA7: Fort Worth | AC7: PCI-01 | AE7: =J7*VLOOKUP(H7,'Cost sheet'!$C$2:$G$1232,5,FALSE) -> #N/A
A8: 46057 | B8: 2 | C8: 2 | D8: 2 | E8: 0000064956 | F8: 1 | G8: BILL | H8: 7217 | I8: DERMACLIP EXT 3 CLIP PAD NS -31005 | J8: 300 | K8: 6.7991 | L8: 2039.73 | M8: Dermaclip | N8: MEDICAL | O8: FALSE | P8: SO | R8: DermaClip US, LLC | S8: 730 N Post Oak Rd., Ste. 202 | U8: TX | V8: 77024 | X8: 0 | Z8: DermaClip US, LLC | AA8: Houston | AC8: PCI-01 | AE8: =J8*VLOOKUP(H8,'Cost sheet'!$C$2:$G$1232,5,FALSE) -> 125.9112
A9: 46064 | B9: 2 | C9: 2 | D9: 2 | E9: 0000064985 | F9: 1 | H9: N-4001 | I9: Cleaning validation for Delight production | J9: 1 | K9: 3000 | L9: 3000 | M9: Bloomi | N9: MEDICAL | O9: FALSE | P9: SO | R9: The Bloomi Inc | S9: 74 Royal Ridge Ct | U9: CA | V9: 94507 | X9: 0 | Z9: The Bloomi Inc | AA9: Alamo | AC9: PCI-01 | AE9: =J9*VLOOKUP(H9,'Cost sheet'!$C$2:$G$1232,5,FALSE) -> #N/A
A10: 46064 | B10: 2 | C10: 2 | D10: 2 | E10: 0000064986 | F10: 1 | H10: 7991 | I10: Bloomi Delight 3oz | J10: 5000 | K10: 3.45 | L10: 17250 | M10: Bloomi | N10: Default | O10: FALSE | P10: SO | R10: The Bloomi Inc | S10: 74 Royal Ridge Ct | U10: CA | V10: 94507 | X10: 0 | Z10: The Bloomi Inc | AA10: Alamo | AB10: Bloomi to arrange freight | AC10: PCI-01 | AE10: =J10*VLOOKUP(H10,'Cost sheet'!$C$2:$G$1232,5,FALSE) -> 17250
A11: 46064 | B11: 46108 | C11: 2 | D11: 2 | E11: 0000064990 | F11: 1 | H11: 7993 | I11: 200 RC Filter | J11: 10000 | K11: 1.675 | L11: 16750 | M11: HARM IRE | N11: MEDICAL | O11: FALSE | P11: SO | R11: Harmac Medical Products | S11: IDA Business Park | U11: .. | V11: ... | X11: 0 | Z11: Harmac Medical Products | AA11: Castlerea, County Roscommon | AC11: PCI-01 | AE11: =J11*VLOOKUP(H11,'Cost sheet'!$C$2:$G$1232,5,FALSE) -> 16750
A12: 46064 | B12: 46108 | C12: 2 | D12: 2 | E12: 0000064990 | F12: 2 | H12: 7992 | I12: Port Drape | J12: 10000 | K12: 0.625 | L12: 6250 | M12: HARM IRE | N12: MEDICAL | O12: FALSE | P12: SO | R12: Harmac Medical Products | S12: IDA Business Park | U12: .. | V12: ... | X12: 0 | Z12: Harmac Medical Products | AA12: Castlerea, County Roscommon | AC12: PCI-01 | AE12: =J12*VLOOKUP(H12,'Cost sheet'!$C$2:$G$1232,5,FALSE) -> 5600
A13: 46066 | B13: 2 | C13: 2 | D13: 2 | E13: 0000064992 | F13: 1 | G13: BILL | H13: 8012 | I13: Bloomi Delight 3oz (1K Use Only) | J13: 1 | K13: 1000 | L13: 1000 | M13: Bloomi | N13: Filling OP | O13: FALSE | P13: SO | R13: The Bloomi Inc | S13: 74 Royal Ridge Ct | U13: CA | V13: 94507 | X13: 0 | Z13: The Bloomi Inc | AA13: Alamo | AC13: PCI-01 | AE13: =J13*VLOOKUP(H13,'Cost sheet'!$C$2:$G$1232,5,FALSE) -> 999.26485
A14: 46071 | B14: 2 | C14: 2 | D14: 2 | E14: 0000065007 | F14: 1 | H14: N-4001 | I14: 1 of 3 Bulk Validations | J14: 1 | K14: 1910 | L14: 1910 | M14: TURN | N14: MEDICAL | O14: FALSE | P14: SO | R14: Turn Therapeutics | S14: 250 N. Westlake Blvd, Suite 210 | U14: CA | V14: 91362 | X14: 0 | Z14: Turn Therapeutics | AA14: Westlake Village | AC14: PCI-01 | AE14: =J14*VLOOKUP(H14,'Cost sheet'!$C$2:$G$1232,5,FALSE) -> #N/A
A15: 46071 | B15: 2 | C15: 2 | D15: 2 | E15: 0000065007 | F15: 2 | H15: 7997 | I15: Turn Therapeutics Hexagen Bulk - 55 Gallon Drum | J15: 8 | K15: 1910 | L15: 15280 | M15: TURN | N15: Filling OP | O15: FALSE | P15: SO | R15: Turn Therapeutics | S15: 250 N. Westlake Blvd, Suite 210 | U15: CA | V15: 91362 | X15: 0 | Z15: Turn Therapeutics | AA15: Westlake Village | AC15: PCI-01 | AE15: =J15*VLOOKUP(H15,'Cost sheet'!$C$2:$G$1232,5,FALSE) -> 15280
A16: 46071 | B16: 2 | C16: 2 | D16: 2 | E16: 0000065007 | F16: 3 | H16: N-4001 | I16: Cleaning Validation | J16: 1 | K16: 10000 | L16: 10000 | M16: TURN | N16: MEDICAL | O16: FALSE | P16: SO | R16: Turn Therapeutics | S16: 250 N. Westlake Blvd, Suite 210 | U16: CA | V16: 91362 | X16: 0 | Z16: Turn Therapeutics | AA16: Westlake Village | AC16: PCI-01 | AE16: =J16*VLOOKUP(H16,'Cost sheet'!$C$2:$G$1232,5,FALSE) -> #N/A
A17: 46076 | B17: 46191 | C17: 2 | D17: 2 | E17: 0000065010 | F17: 1 | G17: ATLANTA | H17: 7488 | I17: CARDINAL HEALTH TELFA NON-ADHERENT DRESSING 3"x4" 2132 | J17: 1080 | K17: 170.4 | L17: 184032 | M17: COVIDMA | N17: MEDICAL | O17: FALSE | P17: SO | R17: Patient Recovery | S17: 110 Kendall Park Lane | U17: GA | V17: 30336 | X17: 0 | Z17: Atlanta RC - US | AA17: Atlanta | AB17: **Effective 7/28/18 www.routingguides.com/cardinal%20health | AE17: =J17*VLOOKUP(H17,'Cost sheet'!$C$2:$G$1232,5,FALSE) -> 21385.04
A18: 46077 | B18: 46225 | C18: 2 | D18: 2 | E18: 0000065011 | F18: 1 | G18: G-Global | H18: 609 | I18: MEDISTRIP 1/4 IN X 3 IN BULK | J18: 17 | K18: 119 | L18: 2023 | M18: CENTURION | N18: MEDICAL | O18: FALSE | P18: SO | R18: Centurion Medical Products Corp | S18: C/O G-Global Logistics Inc | T18: 1776 Pan American St. Building B Suite 100 | U18: CA | V18: 92231 | X18: 1 | Z18: Centurion Medical | AA18: Calexico | AC18: PCI-01 | AE18: =J18*VLOOKUP(H18,'Cost sheet'!$C$2:$G$1232,5,FALSE) -> 844.04779
A19: 46077 | B19: 46225 | C19: 2 | D19: 2 | E19: 0000065011 | F19: 2 | G19: G-Global | H19: 610 | I19: MEDISTRIP 1 IN X 4 IN BULK | J19: 55 | K19: 196.5 | L19: 10807.5 | M19: CENTURION | N19: MEDICAL | O19: FALSE | P19: SO | R19: Centurion Medical Products Corp | S19: C/O G-Global Logistics Inc | T19: 1776 Pan American St. Building B Suite 100 | U19: CA | V19: 92231 | X19: 4 | Z19: Centurion Medical | AA19: Calexico | AC19: PCI-01 | AE19: =J19*VLOOKUP(H19,'Cost sheet'!$C$2:$G$1232,5,FALSE) -> 4062.229
A20: 46077 | B20: 46176 | C20: 2 | D20: 2 | E20: 0000065012 | F20: 1 | G20: G-Global | H20: 2977 | I20: MEDLINE DRSG SURESITE 4.75 X 4 FRAME/LABL (MSC52281) | J20: 63 | K20: 340 | L20: 21420 | M20: CENTURION | N20: MEDICAL | O20: FALSE | P20: SO | R20: Centurion Medical Products Corp | S20: C/O G-Global Logistics Inc | T20: 1776 Pan American St. Building B Suite 100 | U20: CA | V20: 92231 | X20: 26 | Z20: Centurion Medical | AA20: Calexico | AC20: PCI-01 | AE20: =J20*VLOOKUP(H20,'Cost sheet'!$C$2:$G$1232,5,FALSE) -> 5391.365
A21: 46077 | B21: 46105 | C21: 2 | D21: 2 | E21: 0000065013 | F21: 1 | H21: 7861 | I21: ViaCLYR Flip Top 8oz | J21: 5000 | K21: 2.7 | L21: 13500 | M21: CLYRA | N21: Filling OP | O21: FALSE | P21: SO | R21: Clyra Medical Technologies, Inc. | S21: 10770 N 46th Street, Unit C-300 | U21: FL | V21: 33617 | X21: 0 | Z21: Clyra Medical Technologies, Inc. | AA21: Tampa | AC21: PCI-01 | AE21: =J21*VLOOKUP(H21,'Cost sheet'!$C$2:$G$1232,5,FALSE) -> 9291.675
A22: 46077 | B22: 46105 | C22: 2 | D22: 2 | E22: 0000065013 | F22: 2 | H22: 7862 | I22: ViaCLYR Flip Top 16oz | J22: 5000 | K22: 3.5 | L22: 17500 | M22: CLYRA | N22: Filling OP | O22: FALSE | P22: SO | R22: Clyra Medical Technologies, Inc. | S22: 10770 N 46th Street, Unit C-300 | U22: FL | V22: 33617 | X22: 0 | Z22: Clyra Medical Technologies, Inc. | AA22: Tampa | AC22: PCI-01 | AE22: =J22*VLOOKUP(H22,'Cost sheet'!$C$2:$G$1232,5,FALSE) -> 11076.47
A23: 46077 | B23: 46105 | C23: 2 | D23: 2 | E23: 0000065013 | F23: 3 | H23: 7863 | I23: ViaCLYR Flip Top 32oz | J23: 1000 | K23: 7.52 | L23: 7520 | M23: CLYRA | N23: Filling OP | O23: FALSE | P23: SO | R23: Clyra Medical Technologies, Inc. | S23: 10770 N 46th Street, Unit C-300 | U23: FL | V23: 33617 | X23: 0 | Z23: Clyra Medical Technologies, Inc. | AA23: Tampa | AC23: PCI-01 | AE23: =J23*VLOOKUP(H23,'Cost sheet'!$C$2:$G$1232,5,FALSE) -> 5463.174
A24: 46077 | B24: 46237 | C24: 2 | D24: 2 | E24: 0000065014 | F24: 1 | G24: 3440 | H24: 5045 | I24: FREUDENBERG 30cm X 47cm Nonwoven Sheets 122P0463 | J24: 25000 | K24: 1.63 | L24: 40750 | M24: FREUD | N24: MEDICAL | O24: FALSE | P24: SO | R24: Freudenberg Performance Materials LP | S24: 3440 Industrial Drive | U24: NC | V24: 27704 | X24: 0 | Z24: Freudenberg Performance Materials LP | AA24: Durham | AB24: **DO NOT DOUBLE STACK LABEL - TAKE PHOTO** | AE24: =J24*VLOOKUP(H24,'Cost sheet'!$C$2:$G$1232,5,FALSE) -> 14910
A25: 45903 | B25: 2 | C25: 46063 | D25: 46021 | E25: 0000064540 | F25: 1 | H25: 7898 | I25: MPM DryMax/DrySAP Extra Super Absorbent Drsg, Sterile, 8X8; | J25: 10000 | K25: 0.99 | L25: 9900 | M25: MPM | N25: MEDICAL | O25: FALSE | P25: SO | R25: MPM Medical, Inc. | S25: 1801 Big Town Blvd, Suite 300 | U25: TX | V25: 75149 | X25: 0 | Z25: MPM Medical, Inc. | AA25: Mesquite | AC25: PCI-01 | AE25: =J25*VLOOKUP(H25,'Cost sheet'!$C$2:$G$1232,5,FALSE) -> 9900
A26: 45987 | B26: 46104 | C26: 46073 | D26: 46086 | E26: 0000064784 | F26: 2 | G26: ICS | H26: 7153 | I26: URGO - VASHE 250 ml Flip Top 00313 | J26: 50004 | K26: 1.88 | L26: 94007.52 | M26: URGO | N26: Filling OP | O26: FALSE | P26: SO | R26: URGO Medical | S26: 167 International Blvd, Suite 550 | U26: KY | V26: 40109 | X26: 0 | Z26: ICS (Urgo Medical) | AA26: Brooks | AB26: ReceivingBrooks@icsconnect.com | AE26: =J26*VLOOKUP(H26,'Cost sheet'!$C$2:$G$1232,5,FALSE) -> 38025.842
A27: 45987 | B27: 46118 | C27: 46073 | D27: 46086 | E27: 0000064786 | F27: 1 | G27: ICS | H27: 7153 | I27: URGO - VASHE 250 ml Flip Top 00313 | J27: 45000 | K27: 1.88 | L27: 84600 | M27: URGO | N27: Filling OP | O27: FALSE | P27: SO | R27: URGO Medical | S27: 167 International Blvd, Suite 550 | U27: KY | V27: 40109 | X27: 0 | Z27: ICS (Urgo Medical) | AA27: Brooks | AB27: ReceivingBrooks@icsconnect.com | AE27: =J27*VLOOKUP(H27,'Cost sheet'!$C$2:$G$1232,5,FALSE) -> 34220.52
A28: 45987 | B28: 46125 | C28: 46073 | D28: 46086 | E28: 0000064787 | F28: 1 | G28: ICS | H28: 7153 | I28: URGO - VASHE 250 ml Flip Top 00313 | J28: 50004 | K28: 1.88 | L28: 94007.52 | M28: URGO | N28: Filling OP | O28: FALSE | P28: SO | R28: URGO Medical | S28: 167 International Blvd, Suite 550 | U28: KY | V28: 40109 | X28: 0 | Z28: ICS (Urgo Medical) | AA28: Brooks | AB28: ReceivingBrooks@icsconnect.com | AE28: =J28*VLOOKUP(H28,'Cost sheet'!$C$2:$G$1232,5,FALSE) -> 38025.842
A29: 45974 | B29: 45996 | C29: 46076 | D29: 46064 | E29: 0000064757 | F29: 1 | G29: LAND | H29: 6370 | I29: TB DRY MOUTH TINGLING RINSE 16 OZ BULK 40101908 | J29: 17475 | K29: 1.7789 | L29: 31086.28 | M29: ORORA | N29: Filling OP | O29: FALSE | P29: SO | R29: Orora Business Service Center | S29: 13397 Marlay Ave Ste A | U29: CA | V29: 92337-6946 | X29: 0 | Z29: Landsberg-Fullfillment Solutions | AA29: Fontana | AB29: Need special certificate COA before shipped | AC29: PCI-01 | AE29: =J29*VLOOKUP(H29,'Cost sheet'!$C$2:$G$1232,5,FALSE) -> 11457.361
A30: 45987 | B30: 46097 | C30: 46077 | D30: 46090 | E30: 0000064788 | F30: 1 | G30: ICS | H30: 7154 | I30: URGO - VASHE 475 ml Flip Top 00314 | J30: 30000 | K30: 2.59 | L30: 77700 | M30: URGO | N30: Filling OP | O30: FALSE | P30: SO | R30: URGO Medical | S30: 167 International Blvd, Suite 550 | U30: KY | V30: 40109 | X30: 0 | Z30: ICS (Urgo Medical) | AA30: Brooks | AB30: ReceivingBrooks@icsconnect.com | AE30: =J30*VLOOKUP(H30,'Cost sheet'!$C$2:$G$1232,5,FALSE) -> 36058.83
A31: 45594 | B31: 45685 | C31: 46078 | D31: 45709 | E31: 0000063455 | F31: 30 | G31: C02 | H31: 6011 | I31: MEDLINE CURAD MEDISTRIP 1/4 X 4 IN STERILE NON250414 | J31: 182 | K31: 127.14 | L31: 23139.48 | M31: MEDL | N31: MEDICAL | O31: FALSE | P31: SO | R31: Medline Industries, Inc. | S31: 2200 Cornerstone Pkwy, Ste 100 | U31: IL | V31: 60030 | X31: 0 | Z31: Medline Industries LP | AA31: Grayslake | AC31: PCI-01 | AE31: =J31*VLOOKUP(H31,'Cost sheet'!$C$2:$G$1232,5,FALSE) -> 10556.159
A32: 45618 | B32: 45709 | C32: 46078 | D32: 45709 | E32: 0000063558 | F32: 10 | G32: B25 | H32: 6011 | I32: MEDLINE CURAD MEDISTRIP 1/4 X 4 IN STERILE NON250414 | J32: 26 | K32: 127.14 | L32: 3305.64 | M32: MEDL | N32: MEDICAL | O32: FALSE | P32: SO | R32: Medline Industries, Inc. | S32: 1401 N. Universal Ave. | U32: MO | V32: 641202139 | X32: 0 | Z32: Medline Industries LP | AA32: KANSAS CITY | AC32: PCI-01 | AE32: =J32*VLOOKUP(H32,'Cost sheet'!$C$2:$G$1232,5,FALSE) -> 1508.0226
A33: 45618 | B33: 45709 | C33: 46078 | D33: 45709 | E33: 0000063559 | F33: 30 | G33: C57 | H33: 6011 | I33: MEDLINE CURAD MEDISTRIP 1/4 X 4 IN STERILE NON250414 | J33: 8 | K33: 127.14 | L33: 1017.12 | M33: MEDL | N33: MEDICAL | O33: FALSE | P33: SO | R33: Medline Industries, Inc. | S33: 5511 West Ten Rd | U33: NC | V33: 27302 | X33: 0 | Z33: Medline Industries LP | AA33: Mebane | AC33: PCI-01 | AE33: =J33*VLOOKUP(H33,'Cost sheet'!$C$2:$G$1232,5,FALSE) -> 464.00697
A34: 45636 | B34: 45726 | C34: 46078 | D34: 45761 | E34: 0000063612 | F34: 60 | G34: C09 | H34: 6011 | I34: MEDLINE CURAD MEDISTRIP 1/4 X 4 IN STERILE NON250414 | J34: 104 | K34: 127.14 | L34: 13222.56 | M34: MEDL | N34: MEDICAL | O34: FALSE | P34: SO | R34: Medline Industries, Inc. | S34: 1960 W Miro Way | U34: CA | V34: 92376 | X34: 0 | Z34: Medline Industries LP | AA34: Rialto | AC34: PCI-01 | AE34: =J34*VLOOKUP(H34,'Cost sheet'!$C$2:$G$1232,5,FALSE) -> 6032.0906
A35: 45706 | B35: 45790 | C35: 46078 | D35: 45919 | E35: 0000063836 | F35: 10 | G35: C47 | H35: 6013 | I35: MEDLINE CURAD MEDI STRIP 1 X 5 NON250501 | J35: 3 | K35: 123 | L35: 369 | M35: MEDL | N35: MEDICAL | O35: FALSE | P35: SO | R35: Medline Industries, Inc. | S35: 239 Belvidere Rd | U35: MD | V35: 21903 | X35: 0 | Z35: Medline Industries LP | AA35: Perryville | AC35: PCI-01 | AE35: =J35*VLOOKUP(H35,'Cost sheet'!$C$2:$G$1232,5,FALSE) -> 180.1643
A36: 45706 | B36: 45790 | C36: 46078 | D36: 45919 | E36: 0000063843 | F36: 20 | G36: B11 | H36: 6013 | I36: MEDLINE CURAD MEDI STRIP 1 X 5 NON250501 | J36: 1 | K36: 123 | L36: 123 | M36: MEDL | N36: MEDICAL | O36: FALSE | P36: SO | R36: Medline Industries, Inc. | S36: 21111 E. 36th Drive | U36: CO | V36: 80011 | X36: 0 | Z36: Medline Industries LP | AA36: Aurora | AC36: PCI-01 | AE36: =J36*VLOOKUP(H36,'Cost sheet'!$C$2:$G$1232,5,FALSE) -> 60.054767
A37: 45706 | B37: 45790 | C37: 46078 | D37: 45919 | E37: 0000063854 | F37: 20 | G37: C02 | H37: 6013 | I37: MEDLINE CURAD MEDI STRIP 1 X 5 NON250501 | J37: 5 | K37: 123 | L37: 615 | M37: MEDL | N37: MEDICAL | O37: FALSE | P37: SO | R37: Medline Industries, Inc. | S37: 2200 Cornerstone Pkwy, Ste 100 | U37: IL | V37: 60030 | X37: 0 | Z37: Medline Industries LP | AA37: Grayslake | AC37: PCI-01 | AE37: =J37*VLOOKUP(H37,'Cost sheet'!$C$2:$G$1232,5,FALSE) -> 300.27383
A38: 45706 | B38: 45790 | C38: 46078 | D38: 45919 | E38: 0000063855 | F38: 10 | G38: B01 | H38: 6013 | I38: MEDLINE CURAD MEDI STRIP 1 X 5 NON250501 | J38: 37 | K38: 123 | L38: 4551 | M38: MEDL | N38: MEDICAL | O38: FALSE | P38: SO | R38: Medline Industries, Inc. | S38: 1200 Townline Rd. | U38: IL | V38: 60060 | X38: 0 | Z38: Medline Industries LP | AA38: Mundelein | AC38: PCI-01 | AE38: =J38*VLOOKUP(H38,'Cost sheet'!$C$2:$G$1232,5,FALSE) -> 2222.0264
A39: 45720 | B39: 45805 | C39: 46078 | D39: 45919 | E39: 0000063882 | F39: 20 | G39: C40 | H39: 6013 | I39: MEDLINE CURAD MEDI STRIP 1 X 5 NON250501 | J39: 5 | K39: 123 | L39: 615 | M39: MEDL | N39: MEDICAL | O39: FALSE | P39: SO | R39: Medline Industries, Inc. | S39: 81 Campanelli Drive | U39: MA | V39: 01569 | X39: 0 | Z39: Medline Industries LP | AA39: UXBRIDGE | AC39: PCI-01 | AE39: =J39*VLOOKUP(H39,'Cost sheet'!$C$2:$G$1232,5,FALSE) -> 300.27383
A40: 45720 | B40: 45805 | C40: 46078 | D40: 45919 | E40: 0000063883 | F40: 30 | G40: B06 | H40: 6013 | I40: MEDLINE CURAD MEDI STRIP 1 X 5 NON250501 | J40: 9 | K40: 123 | L40: 1107 | M40: MEDL | N40: MEDICAL | O40: FALSE | P40: SO | R40: Medline Industries, Inc. | S40: 1 Medline Drive, Suite 100 | U40: TX | V40: 75172 | X40: 0 | Z40: Medline Industries LP | AA40: Wilmer | AC40: PCI-01 | AE40: =J40*VLOOKUP(H40,'Cost sheet'!$C$2:$G$1232,5,FALSE) -> 540.4929
A41: 45720 | B41: 45805 | C41: 46078 | D41: 45919 | E41: 0000063885 | F41: 10 | G41: B11 | H41: 6013 | I41: MEDLINE CURAD MEDI STRIP 1 X 5 NON250501 | J41: 3 | K41: 123 | L41: 369 | M41: MEDL | N41: MEDICAL | O41: FALSE | P41: SO | R41: Medline Industries, Inc. | S41: 21111 E. 36th Drive | U41: CO | V41: 80011 | X41: 0 | Z41: Medline Industries LP | AA41: Aurora | AC41: PCI-01 | AE41: =J41*VLOOKUP(H41,'Cost sheet'!$C$2:$G$1232,5,FALSE) -> 180.1643
A42: 45720 | B42: 45805 | C42: 46078 | D42: 45919 | E42: 0000063886 | F42: 30 | G42: C50 | H42: 6013 | I42: MEDLINE CURAD MEDI STRIP 1 X 5 NON250501 | J42: 2 | K42: 123 | L42: 246 | M42: MEDL | N42: MEDICAL | O42: FALSE | P42: SO | R42: Medline Industries, Inc. | S42: 8787 W BUCKEYE RD | U42: AZ | V42: 853539399 | X42: 0 | Z42: Medline Industries LP | AA42: TOLLESON | AC42: PCI-01 | AE42: =J42*VLOOKUP(H42,'Cost sheet'!$C$2:$G$1232,5,FALSE) -> 120.10953
... A46: 45720 | B46: 45805 | C46: 46078 | D46: 45919 | E46: 0000063891 | F46: 30 | G46: B24 | H46: 6013 | I46: MEDLINE CURAD MEDI STRIP 1 X 5 NON250501 | J46: 8 | K46: 123 | L46: 984 | M46: MEDL | N46: MEDICAL | O46: FALSE | P46: SO | R46: Medline Industries, Inc. | S46: 8001 SW 47th St. | U46: OK | V46: 73179 | X46: 0 | Z46: Medline Industries LP | AA46: Oklahoma City | AC46: PCI-01 | AE46: =J46*VLOOKUP(H46,'Cost sheet'!$C$2:$G$1232,5,FALSE) -> 480.43814
A47: 45720 | B47: 45805 | C47: 46078 | D47: 45919 | E47: 0000063892 | F47: 20 | G47: C54 | H47: 6013 | I47: MEDLINE CURAD MEDI STRIP 1 X 5 NON250501 | J47: 4 | K47: 123 | L47: 492 | M47: MEDL | N47: MEDICAL | O47: FALSE | P47: SO | R47: Medline Industries, Inc. | S47: 494 State Route 416 | T47: 494 State Route 416 | U47: NY | V47: 12549 | X47: 0 | Z47: Medline Industries LP | AA47: Montgomery | AC47: PCI-01 | AE47: =J47*VLOOKUP(H47,'Cost sheet'!$C$2:$G$1232,5,FALSE) -> 240.21907
A48: 45720 | B48: 45805 | C48: 46078 | D48: 45919 | E48: 0000063897 | F48: 20 | G48: C59 | H48: 6013 | I48: MEDLINE CURAD MEDI STRIP 1 X 5 NON250501 | J48: 2 | K48: 123 | L48: 246 | M48: MEDL | N48: MEDICAL | O48: FALSE | P48: SO | R48: Medline Industries, Inc. | S48: 2100 Industrial Park Rd | U48: LA | V48: 70401 | X48: 0 | Z48: Medline Industries, LP | AA48: Hammond | AC48: PCI-01 | AE48: =J48*VLOOKUP(H48,'Cost sheet'!$C$2:$G$1232,5,FALSE) -> 120.10953
A49: 45720 | B49: 45805 | C49: 46078 | D49: 45919 | E49: 0000063899 | F49: 10 | G49: C02 | H49: 6013 | I49: MEDLINE CURAD MEDI STRIP 1 X 5 NON250501 | J49: 6 | K49: 123 | L49: 738 | M49: MEDL | N49: MEDICAL | O49: FALSE | P49: SO | R49: Medline Industries, Inc. | S49: 2200 Cornerstone Pkwy, Ste 100 | U49: IL | V49: 60030 | X49: 0 | Z49: Medline Industries LP | AA49: Grayslake | AC49: PCI-01 | AE49: =J49*VLOOKUP(H49,'Cost sheet'!$C$2:$G$1232,5,FALSE) -> 360.3286
A50: 45720 | B50: 45805 | C50: 46078 | D50: 45919 | E50: 0000063901 | F50: 20 | G50: B25 | H50: 6013 | I50: MEDLINE CURAD MEDI STRIP 1 X 5 NON250501 | J50: 8 | K50: 123 | L50: 984 | M50: MEDL | N50: MEDICAL | O50: FALSE | P50: SO | R50: Medline Industries, Inc. | S50: 1401 N. Universal Ave. | U50: MO | V50: 641202139 | X50: 0 | Z50: Medline Industries LP | AA50: KANSAS CITY | AC50: PCI-01 | AE50: =J50*VLOOKUP(H50,'Cost sheet'!$C$2:$G$1232,5,FALSE) -> 480.43814
A51: 45720 | B51: 45805 | C51: 46078 | D51: 45919 | E51: 0000063902 | F51: 20 | G51: K46 | H51: 6013 | I51: MEDLINE CURAD MEDI STRIP 1 X 5 NON250501 | J51: 1 | K51: 123 | L51: 123 | M51: MEDL | N51: MEDICAL | O51: FALSE | P51: SO | R51: Medline Industries, Inc. | S51: 18601 Christopher Way, STE 100 | T51: 18601 Christopher Way, STE 100 | U51: CA | V51: 95330 | X51: 0 | Z51: Medline Industries, Inc. | AA51: Lathrop | AC51: PCI-01 | AE51: =J51*VLOOKUP(H51,'Cost sheet'!$C$2:$G$1232,5,FALSE) -> 60.054767
A52: 45726 | B52: 46006 | C52: 46078 | D52: 46006 | E52: 0000063917 | F52: 1 | H52: 5342 | I52: ISI LARGE ALUMI-HAND 760 | J52: 6900 | K52: 7.7 | L52: 53130 | M52: ISI | N52: MEDICAL | O52: FALSE | P52: SO | R52: Instrument Specialists Inc | S52: 32390 IH 10 West | U52: TX | V52: 78006 | X52: 0 | Z52: Instrument Specialists Inc | AA52: Boerne | AC52: PCI-01 | AE52: =J52*VLOOKUP(H52,'Cost sheet'!$C$2:$G$1232,5,FALSE) -> 21331.598
A53: 45734 | B53: 45819 | C53: 46078 | D53: 45919 | E53: 0000063941 | F53: 30 | G53: B06 | H53: 6013 | I53: MEDLINE CURAD MEDI STRIP 1 X 5 NON250501 | J53: 4 | K53: 123 | L53: 492 | M53: MEDL | N53: MEDICAL | O53: FALSE | P53: SO | R53: Medline Industries, Inc. | S53: 1 Medline Drive, Suite 100 | U53: TX | V53: 75172 | X53: 0 | Z53: Medline Industries LP | AA53: Wilmer | AC53: PCI-01 | AE53: =J53*VLOOKUP(H53,'Cost sheet'!$C$2:$G$1232,5,FALSE) -> 240.21907
A54: 45734 | B54: 45819 | C54: 46078 | D54: 45919 | E54: 0000063942 | F54: 10 | G54: K46 | H54: 6013 | I54: MEDLINE CURAD MEDI STRIP 1 X 5 NON250501 | J54: 1 | K54: 123 | L54: 123 | M54: MEDL | N54: MEDICAL | O54: FALSE | P54: SO | R54: Medline Industries, Inc. | S54: 18601 Christopher Way, STE 100 | T54: 18601 Christopher Way, STE 100 | U54: CA | V54: 95330 | X54: 0 | Z54: Medline Industries, Inc. | AA54: Lathrop | AC54: PCI-01 | AE54: =J54*VLOOKUP(H54,'Cost sheet'!$C$2:$G$1232,5,FALSE) -> 60.054767
A55: 45734 | B55: 45819 | C55: 46078 | D55: 45919 | E55: 0000063943 | F55: 30 | G55: C32 | H55: 6013 | I55: MEDLINE CURAD MEDI STRIP 1 X 5 NON250501 | J55: 3 | K55: 123 | L55: 369 | M55: MEDL | N55: MEDICAL | O55: FALSE | P55: SO | R55: Medline Industries, Inc. | S55: 29895 US HWY 90 BUS | U55: TX | V55: 77494 | X55: 0 | Z55: Medline Industries LP | AA55: Katy | AC55: PCI-01 | AE55: =J55*VLOOKUP(H55,'Cost sheet'!$C$2:$G$1232,5,FALSE) -> 180.1643
A56: 45734 | B56: 45819 | C56: 46078 | D56: 45919 | E56: 0000063945 | F56: 10 | G56: C37 | H56: 6013 | I56: MEDLINE CURAD MEDI STRIP 1 X 5 NON250501 | J56: 3 | K56: 123 | L56: 369 | M56: MEDL | N56: MEDICAL | O56: FALSE | P56: SO | R56: Medline Industries, Inc. | S56: 5000 Premier Pkwy Ste 100 | U56: MO | V56: 63376 | X56: 0 | Z56: Medline Industries LP | AA56: Saint Peters | AC56: PCI-01 | AE56: =J56*VLOOKUP(H56,'Cost sheet'!$C$2:$G$1232,5,FALSE) -> 180.1643
A57: 45734 | B57: 45819 | C57: 46078 | D57: 45919 | E57: 0000063947 | F57: 40 | G57: C02 | H57: 6013 | I57: MEDLINE CURAD MEDI STRIP 1 X 5 NON250501 | J57: 4 | K57: 123 | L57: 492 | M57: MEDL | N57: MEDICAL | O57: FALSE | P57: SO | R57: Medline Industries, Inc. | S57: 2200 Cornerstone Pkwy, Ste 100 | U57: IL | V57: 60030 | X57: 0 | Z57: Medline Industries LP | AA57: Grayslake | AC57: PCI-01 | AE57: =J57*VLOOKUP(H57,'Cost sheet'!$C$2:$G$1232,5,FALSE) -> 240.21907
A58: 45734 | B58: 45819 | C58: 46078 | D58: 45919 | E58: 0000063948 | F58: 10 | G58: B25 | H58: 6013 | I58: MEDLINE CURAD MEDI STRIP 1 X 5 NON250501 | J58: 4 | K58: 123 | L58: 492 | M58: MEDL | N58: MEDICAL | O58: FALSE | P58: SO | R58: Medline Industries, Inc. | S58: 1401 N. Universal Ave. | U58: MO | V58: 641202139 | X58: 0 | Z58: Medline Industries LP | AA58: KANSAS CITY | AC58: PCI-01 | AE58: =J58*VLOOKUP(H58,'Cost sheet'!$C$2:$G$1232,5,FALSE) -> 240.21907
A59: 45734 | B59: 45819 | C59: 46078 | D59: 45919 | E59: 0000063949 | F59: 10 | G59: C40 | H59: 6013 | I59: MEDLINE CURAD MEDI STRIP 1 X 5 NON250501 | J59: 2 | K59: 123 | L59: 246 | M59: MEDL | N59: MEDICAL | O59: FALSE | P59: SO | R59: Medline Industries, Inc. | S59: 81 Campanelli Drive | U59: MA | V59: 01569 | X59: 0 | Z59: Medline Industries LP | AA59: UXBRIDGE | AC59: PCI-01 | AE59: =J59*VLOOKUP(H59,'Cost sheet'!$C$2:$G$1232,5,FALSE) -> 120.10953
A60: 45734 | B60: 45819 | C60: 46078 | D60: 45919 | E60: 0000063951 | F60: 10 | G60: C57 | H60: 6013 | I60: MEDLINE CURAD MEDI STRIP 1 X 5 NON250501 | J60: 4 | K60: 123 | L60: 492 | M60: MEDL | N60: MEDICAL | O60: FALSE | P60: SO | R60: Medline Industries, Inc. | S60: 5511 West Ten Rd | U60: NC | V60: 27302 | X60: 0 | Z60: Medline Industries LP | AA60: Mebane | AC60: PCI-01 | AE60: =J60*VLOOKUP(H60,'Cost sheet'!$C$2:$G$1232,5,FALSE) -> 240.21907
A61: 45734 | B61: 45819 | C61: 46078 | D61: 45919 | E61: 0000063955 | F61: 10 | G61: B01 | H61: 6013 | I61: MEDLINE CURAD MEDI STRIP 1 X 5 NON250501 | J61: 6 | K61: 123 | L61: 738 | M61: MEDL | N61: MEDICAL | O61: FALSE | P61: SO | R61: Medline Industries, Inc. | S61: 1200 Townline Rd. | U61: IL | V61: 60060 | X61: 0 | Z61: Medline Industries LP | AA61: Mundelein | AC61: PCI-01 | AE61: =J61*VLOOKUP(H61,'Cost sheet'!$C$2:$G$1232,5,FALSE) -> 360.3286
A62: 45734 | B62: 45819 | C62: 46078 | D62: 45919 | E62: 0000063957 | F62: 10 | G62: C71 | H62: 6013 | I62: MEDLINE CURAD MEDI STRIP 1 X 5 NON250501 | J62: 1 | K62: 123 | L62: 123 | M62: MEDL | N62: MEDICAL | O62: FALSE | P62: SO | R62: Medline Industries, Inc. | S62: 264 South 5750 West | U62: UT | V62: 84104 | X62: 0 | Z62: MEDLINE INDUSTRIES, Inc. | AA62: Salt Lake City | AC62: PCI-01 | AE62: =J62*VLOOKUP(H62,'Cost sheet'!$C$2:$G$1232,5,FALSE) -> 60.054767
A63: 45734 | B63: 45819 | C63: 46078 | D63: 45919 | E63: 0000063960 | F63: 10 | G63: B11 | H63: 6013 | I63: MEDLINE CURAD MEDI STRIP 1 X 5 NON250501 | J63: 1 | K63: 123 | L63: 123 | M63: MEDL | N63: MEDICAL | O63: FALSE | P63: SO | R63: Medline Industries, Inc. | S63: 21111 E. 36th Drive | U63: CO | V63: 80011 | X63: 0 | Z63: Medline Industries LP | AA63: Aurora | AC63: PCI-01 | AE63: =J63*VLOOKUP(H63,'Cost sheet'!$C$2:$G$1232,5,FALSE) -> 60.054767
A64: 45734 | B64: 45819 | C64: 46078 | D64: 45919 | E64: 0000063961 | F64: 20 | G64: C54 | H64: 6013 | I64: MEDLINE CURAD MEDI STRIP 1 X 5 NON250501 | J64: 4 | K64: 123 | L64: 492 | M64: MEDL | N64: MEDICAL | O64: FALSE | P64: SO | R64: Medline Industries, Inc. | S64: 494 State Route 416 | T64: 494 State Route 416 | U64: NY | V64: 12549 | X64: 0 | Z64: Medline Industries LP | AA64: Montgomery | AC64: PCI-01 | AE64: =J64*VLOOKUP(H64,'Cost sheet'!$C$2:$G$1232,5,FALSE) -> 240.21907
A65: 45734 | B65: 45819 | C65: 46078 | D65: 45919 | E65: 0000063962 | F65: 30 | G65: C09 | H65: 6013 | I65: MEDLINE CURAD MEDI STRIP 1 X 5 NON250501 | J65: 4 | K65: 123 | L65: 492 | M65: MEDL | N65: MEDICAL | O65: FALSE | P65: SO | R65: Medline Industries, Inc. | S65: 1960 W Miro Way | U65: CA | V65: 92376 | X65: 0 | Z65: Medline Industries LP | AA65: Rialto | AC65: PCI-01 | AE65: =J65*VLOOKUP(H65,'Cost sheet'!$C$2:$G$1232,5,FALSE) -> 240.21907
A66: 45734 | B66: 45819 | C66: 46078 | D66: 45919 | E66: 0000063963 | F66: 30 | G66: C41 | H66: 6013 | I66: MEDLINE CURAD MEDI STRIP 1 X 5 NON250501 | J66: 2 | K66: 123 | L66: 246 | M66: MEDL | N66: MEDICAL | O66: FALSE | P66: SO | R66: Medline Industries, Inc. | S66: 1040 Enterprise Parkway | U66: OH | V66: 43162 | X66: 0 | Z66: Medline Industries LP | AA66: West Jefferson | AC66: PCI-01 | AE66: =J66*VLOOKUP(H66,'Cost sheet'!$C$2:$G$1232,5,FALSE) -> 120.10953
A67: 45734 | B67: 45819 | C67: 46078 | D67: 45919 | E67: 0000063964 | F67: 30 | G67: C50 | H67: 6013 | I67: MEDLINE CURAD MEDI STRIP 1 X 5 NON250501 | J67: 6 | K67: 123 | L67: 738 | M67: MEDL | N67: MEDICAL | O67: FALSE | P67: SO | R67: Medline Industries, Inc. | S67: 8787 W BUCKEYE RD | U67: AZ | V67: 853539399 | X67: 0 | Z67: Medline Industries LP | AA67: TOLLESON | AC67: PCI-01 | AE67: =J67*VLOOKUP(H67,'Cost sheet'!$C$2:$G$1232,5,FALSE) -> 360.3286
A68: 45757 | B68: 45961 | C68: 46078 | D68: 45961 | E68: 0000064057 | F68: 1 | G68: 3440 | H68: 5045 | I68: FREUDENBERG 30cm X 47cm Nonwoven Sheets 122P0463 | J68: 25000 | K68: 1.63 | L68: 40750 | M68: FREUD | N68: MEDICAL | O68: FALSE | P68: SO | R68: Freudenberg Performance Materials LP | S68: 3440 Industrial Drive | U68: NC | V68: 27704 | X68: 0 | Z68: Freudenberg Performance Materials LP | AA68: Durham | AB68: **DO NOT DOUBLE STACK LABEL - TAKE PHOTO** | AE68: =J68*VLOOKUP(H68,'Cost sheet'!$C$2:$G$1232,5,FALSE) -> 14910
A69: 45761 | B69: 45847 | C69: 46078 | D69: 45919 | E69: 0000064069 | F69: 10 | G69: K46 | H69: 6013 | I69: MEDLINE CURAD MEDI STRIP 1 X 5 NON250501 | J69: 13 | K69: 123 | L69: 1599 | M69: MEDL | N69: MEDICAL | O69: FALSE | P69: SO | R69: Medline Industries, Inc. | S69: 18601 Christopher Way, STE 100 | T69: 18601 Christopher Way, STE 100 | U69: CA | V69: 95330 | X69: 0 | Z69: Medline Industries, Inc. | AA69: Lathrop | AC69: PCI-01 | AE69: =J69*VLOOKUP(H69,'Cost sheet'!$C$2:$G$1232,5,FALSE) -> 780.71197
A70: 45761 | B70: 45847 | C70: 46078 | D70: 45919 | E70: 0000064070 | F70: 30 | G70: B24 | H70: 6013 | I70: MEDLINE CURAD MEDI STRIP 1 X 5 NON250501 | J70: 4 | K70: 123 | L70: 492 | M70: MEDL | N70: MEDICAL | O70: FALSE | P70: SO | R70: Medline Industries, Inc. | S70: 8001 SW 47th St. | U70: OK | V70: 73179 | X70: 0 | Z70: Medline Industries LP | AA70: Oklahoma City | AC70: PCI-01 | AE70: =J70*VLOOKUP(H70,'Cost sheet'!$C$2:$G$1232,5,FALSE) -> 240.21907
A71: 45761 | B71: 45847 | C71: 46078 | D71: 45919 | E71: 0000064075 | F71: 10 | G71: B27 | H71: 6013 | I71: MEDLINE CURAD MEDI STRIP 1 X 5 NON250501 | J71: 3 | K71: 123 | L71: 369 | M71: MEDL | N71: MEDICAL | O71: FALSE | P71: SO | R71: Medline Industries, Inc. | S71: 92 Southeast 223rd Avenue | U71: OR | V71: 97030 | X71: 0 | Z71: Medline Industries LP | AA71: Gresham | AC71: PCI-01 | AE71: =J71*VLOOKUP(H71,'Cost sheet'!$C$2:$G$1232,5,FALSE) -> 180.1643
A72: 45761 | B72: 45847 | C72: 46078 | D72: 45919 | E72: 0000064076 | F72: 60 | G72: B06 | H72: 6013 | I72: MEDLINE CURAD MEDI STRIP 1 X 5 NON250501 | J72: 10 | K72: 123 | L72: 1230 | M72: MEDL | N72: MEDICAL | O72: FALSE | P72: SO | R72: Medline Industries, Inc. | S72: 1 Medline Drive, Suite 100 | U72: TX | V72: 75172 | X72: 0 | Z72: Medline Industries LP | AA72: Wilmer | AC72: PCI-01 | AE72: =J72*VLOOKUP(H72,'Cost sheet'!$C$2:$G$1232,5,FALSE) -> 600.54767
A73: 45761 | B73: 45847 | C73: 46078 | D73: 45919 | E73: 0000064077 | F73: 40 | G73: C54 | H73: 6013 | I73: MEDLINE CURAD MEDI STRIP 1 X 5 NON250501 | J73: 7 | K73: 123 | L73: 861 | M73: MEDL | N73: MEDICAL | O73: FALSE | P73: SO | R73: Medline Industries, Inc. | S73: 494 State Route 416 | T73: 494 State Route 416 | U73: NY | V73: 12549 | X73: 0 | Z73: Medline Industries LP | AA73: Montgomery | AC73: PCI-01 | AE73: =J73*VLOOKUP(H73,'Cost sheet'!$C$2:$G$1232,5,FALSE) -> 420.38337
A74: 45761 | B74: 45847 | C74: 46078 | D74: 45919 | E74: 0000064080 | F74: 20 | G74: C75 | H74: 6013 | I74: MEDLINE CURAD MEDI STRIP 1 X 5 NON250501 | J74: 19 | K74: 123 | L74: 2337 | M74: MEDL | N74: MEDICAL | O74: FALSE | P74: SO | R74: Medline Industries, Inc. | S74: 3770 Hogum Bay Road Ne | U74: WA | V74: 98516 | X74: 0 | Z74: Medline Industries LP | AA74: Lacey | AC74: PCI-01 | AE74: =J74*VLOOKUP(H74,'Cost sheet'!$C$2:$G$1232,5,FALSE) -> 1141.0406
A75: 45909 | B75: 46025 | C75: 46078 | D75: 46073 | E75: 0000064548 | F75: 1 | G75: IRELAND | H75: 7235 | I75: HARMAC PRTD DRAPE ASSEMBLY P3113231 REV.A (ROW) | J75: 60000 | K75: 0.5211 | L75: 31266 | M75: HARM IRE | N75: Drape&Mask | O75: FALSE | P75: SO | R75: Harmac Medical Products | S75: IDA Business Park | U75: .. | V75: ... | X75: 0 | Z75: Harmac Medical Products | AA75: Castlerea, County Roscommon | AB75: use expeditors***Heat treated Pallets | AE75: =J75*VLOOKUP(H75,'Cost sheet'!$C$2:$G$1232,5,FALSE) -> 19164.96
A76: 45912 | B76: 46087 | C76: 46078 | D76: 46087 | E76: 0000064559 | F76: 1 | G76: IRELAND | H76: 3958 | I76: Harmac Filter Disc P3113306 Rev E | J76: 202500 | K76: 0.27 | L76: 54675 | M76: HARM IRE | N76: MEDICAL | O76: FALSE | P76: SO | R76: Harmac Medical Products | S76: IDA Business Park | U76: .. | V76: ... | X76: 0 | Z76: Harmac Medical Products | AA76: Castlerea, County Roscommon | AB76: use expeditors***Heat treated Pallets | AE76: =J76*VLOOKUP(H76,'Cost sheet'!$C$2:$G$1232,5,FALSE) -> 28557.158
A77: 45915 | B77: 46056 | C77: 46078 | D77: 46073 | E77: 0000064562 | F77: 1 | G77: IRELAND | H77: 7235 | I77: HARMAC PRTD DRAPE ASSEMBLY P3113231 REV.A (ROW) | J77: 60000 | K77: 0.5211 | L77: 31266 | M77: HARM IRE | N77: Drape&Mask | O77: FALSE | P77: SO | R77: Harmac Medical Products | S77: IDA Business Park | U77: .. | V77: ... | X77: 0 | Z77: Harmac Medical Products | AA77: Castlerea, County Roscommon | AB77: use expeditors***Heat treated Pallets | AE77: =J77*VLOOKUP(H77,'Cost sheet'!$C$2:$G$1232,5,FALSE) -> 19164.96
A78: 45925 | B78: 46043 | C78: 46078 | D78: 46043 | E78: 0000064618 | F78: 5 | G78: ATLANTA | H78: 7487 | I78: CARDINAL HEALTH TELFA ADHESIVE DRESSING 2"x3" 6017 | J78: 300 | K78: 269.76 | L78: 80928 | M78: COVIDMA | N78: MEDICAL | O78: FALSE | P78: SO | R78: Patient Recovery | S78: 110 Kendall Park Lane | U78: GA | V78: 30336 | X78: 0 | Z78: Atlanta RC - US | AA78: Atlanta | AB78: **Effective 7/28/18 www.routingguides.com/cardinal%20health | AE78: =J78*VLOOKUP(H78,'Cost sheet'!$C$2:$G$1232,5,FALSE) -> 41660.933
A79: 45987 | B79: 46125 | C79: 46078 | D79: 46093 | E79: 0000064787 | F79: 2 | G79: ICS | H79: 7155 | I79: URGO - VASHE 250 ml Instill 00316 | J79: 6000 | K79: 4.34 | L79: 26040 | M79: URGO | N79: Filling OP | O79: FALSE | P79: SO | R79: URGO Medical | S79: 167 International Blvd, Suite 550 | U79: KY | V79: 40109 | X79: 0 | Z79: ICS (Urgo Medical) | AA79: Brooks | AB79: ReceivingBrooks@icsconnect.com | AE79: =J79*VLOOKUP(H79,'Cost sheet'!$C$2:$G$1232,5,FALSE) -> 17492.802
A80: 45987 | B80: 46125 | C80: 46078 | D80: 46093 | E80: 0000064787 | F80: 3 | G80: ICS | H80: 7159 | I80: URGO - VASHE 250 ml OTC Flip Top 00405 | J80: 5004 | K80: 1.95 | L80: 9757.8 | M80: URGO | N80: Filling OP | O80: FALSE | P80: SO | R80: URGO Medical | S80: 167 International Blvd, Suite 550 | U80: KY | V80: 40109 | X80: 0 | Z80: ICS (Urgo Medical) | AA80: Brooks | AB80: ReceivingBrooks@icsconnect.com | AE80: =J80*VLOOKUP(H80,'Cost sheet'!$C$2:$G$1232,5,FALSE) -> 4113.4181
A81: 46072 | B81: 2 | C81: 46078 | D81: 46079 | E81: 0000065008 | F81: 1 | G81: BILL | H81: F-22004 | I81: 5 SITE SEMI-OCCLUSIVE STRIP | J81: 16000 | K81: 0.41 | L81: 6560 | M81: MONADERM | N81: MEDICAL | O81: FALSE | P81: SO | R81: Monaderm | S81: 5, rue des Violettes | U81: .. | V81: .... | X81: 0 | Z81: Monaderm | AA81: 98000 Monaco | AB81: Please select UPS Expedited or UPS Standard for shipping | AC81: PCI-01 | AE81: =J81*VLOOKUP(H81,'Cost sheet'!$C$2:$G$1232,5,FALSE) -> 2378.112
A82: 45692 | B82: 45795 | C82: 46079 | D82: 45884 | E82: 0000063804 | F82: 1 | G82: LAREDO | H82: 6008 | I82: MEDLINE CURAD MEDISTRIP 1/4 X 1.5 IN, STERILE NON250114 | J82: 1 | K82: 71.94 | L82: 71.94 | M82: MEDL | N82: MEDICAL | O82: FALSE | P82: SO | R82: Medline Industries, Inc. | S82: 12001 General Milton Dr | U82: TX | V82: 78045 | X82: 1 | Z82: Medline Industries | AA82: Laredo | AB82: This location will be inactive Effective 7/17/17. new location 12001 General Milton Dr. Laredo, TX . If customer request NDA - use Fedex Collect # 326382027 | AC82: PCI-01 | AE82: =J82*VLOOKUP(H82,'Cost sheet'!$C$2:$G$1232,5,FALSE) -> 36.229519
A83: 45706 | B83: 45790 | C83: 46079 | D83: 45884 | E83: 0000063833 | F83: 10 | G83: C50 | H83: 6008 | I83: MEDLINE CURAD MEDISTRIP 1/4 X 1.5 IN, STERILE NON250114 | J83: 20 | K83: 71.94 | L83: 1438.8 | M83: MEDL | N83: MEDICAL | O83: FALSE | P83: SO | R83: Medline Industries, Inc. | S83: 8787 W BUCKEYE RD | U83: AZ | V83: 853539399 | X83: 1 | Z83: Medline Industries LP | AA83: TOLLESON | AC83: PCI-01 | AE83: =J83*VLOOKUP(H83,'Cost sheet'!$C$2:$G$1232,5,FALSE) -> 724.59038
A84: 45713 | B84: 45818 | C84: 46079 | D84: 45884 | E84: 0000063874 | F84: 1 | G84: LAREDO | H84: 6008 | I84: MEDLINE CURAD MEDISTRIP 1/4 X 1.5 IN, STERILE NON250114 | J84: 2 | K84: 71.94 | L84: 143.88 | M84: MEDL | N84: MEDICAL | O84: FALSE | P84: SO | R84: Medline Industries, Inc. | S84: 12001 General Milton Dr | U84: TX | V84: 78045 | X84: 1 | Z84: Medline Industries | AA84: Laredo | AB84: This location will be inactive Effective 7/17/17. new location 12001 General Milton Dr. Laredo, TX . If customer request NDA - use Fedex Collect # 326382027 | AC84: PCI-01 | AE84: =J84*VLOOKUP(H84,'Cost sheet'!$C$2:$G$1232,5,FALSE) -> 72.459038
A85: 45720 | B85: 45805 | C85: 46079 | D85: 45884 | E85: 0000063886 | F85: 10 | G85: C50 | H85: 6008 | I85: MEDLINE CURAD MEDISTRIP 1/4 X 1.5 IN, STERILE NON250114 | J85: 7 | K85: 71.94 | L85: 503.58 | M85: MEDL | N85: MEDICAL | O85: FALSE | P85: SO | R85: Medline Industries, Inc. | S85: 8787 W BUCKEYE RD | U85: AZ | V85: 853539399 | X85: 1 | Z85: Medline Industries LP | AA85: TOLLESON | AC85: PCI-01 | AE85: =J85*VLOOKUP(H85,'Cost sheet'!$C$2:$G$1232,5,FALSE) -> 253.60663
A86: 45720 | B86: 45805 | C86: 46079 | D86: 45884 | E86: 0000063889 | F86: 20 | G86: C32 | H86: 6008 | I86: MEDLINE CURAD MEDISTRIP 1/4 X 1.5 IN, STERILE NON250114 | J86: 6 | K86: 71.94 | L86: 431.64 | M86: MEDL | N86: MEDICAL | O86: FALSE | P86: SO | R86: Medline Industries, Inc. | S86: 29895 US HWY 90 BUS | U86: TX | V86: 77494 | X86: 1 | Z86: Medline Industries LP | AA86: Katy | AC86: PCI-01 | AE86: =J86*VLOOKUP(H86,'Cost sheet'!$C$2:$G$1232,5,FALSE) -> 217.37711
A87: 45720 | B87: 45805 | C87: 46079 | D87: 45884 | E87: 0000063891 | F87: 10 | G87: B24 | H87: 6008 | I87: MEDLINE CURAD MEDISTRIP 1/4 X 1.5 IN, STERILE NON250114 | J87: 3 | K87: 71.94 | L87: 215.82 | M87: MEDL | N87: MEDICAL | O87: FALSE | P87: SO | R87: Medline Industries, Inc. | S87: 8001 SW 47th St. | U87: OK | V87: 73179 | X87: 1 | Z87: Medline Industries LP | AA87: Oklahoma City | AC87: PCI-01 | AE87: =J87*VLOOKUP(H87,'Cost sheet'!$C$2:$G$1232,5,FALSE) -> 108.68856
A88: 45720 | B88: 45805 | C88: 46079 | D88: 45884 | E88: 0000063900 | F88: 10 | G88: C46 | H88: 6008 | I88: MEDLINE CURAD MEDISTRIP 1/4 X 1.5 IN, STERILE NON250114 | J88: 30 | K88: 71.94 | L88: 2158.2 | M88: MEDL | N88: MEDICAL | O88: FALSE | P88: SO | R88: Medline Industries, Inc. | S88: 5701 PROMONTORY PKWY | U88: CA | V88: 953779201 | X88: 1 | Z88: Medline Industries LP | AA88: TRACY | AC88: PCI-01 | AE88: =J88*VLOOKUP(H88,'Cost sheet'!$C$2:$G$1232,5,FALSE) -> 1086.8856
A89: 45720 | B89: 45805 | C89: 46079 | D89: 45884 | E89: 0000063903 | F89: 10 | G89: B49 | H89: 6008 | I89: MEDLINE CURAD MEDISTRIP 1/4 X 1.5 IN, STERILE NON250114 | J89: 4 | K89: 71.94 | L89: 287.76 | M89: MEDL | N89: MEDICAL | O89: FALSE | P89: SO | R89: Medline Industries, Inc. | S89: 42500 Winchester Rd | U89: CA | V89: 925902570 | X89: 1 | Z89: Medline Industries LP | AA89: Temecula | AC89: PCI-01 | AE89: =J89*VLOOKUP(H89,'Cost sheet'!$C$2:$G$1232,5,FALSE) -> 144.91808
A90: 45721 | B90: 45825 | C90: 46079 | D90: 45884 | E90: 0000063908 | F90: 1 | G90: LAREDO | H90: 6008 | I90: MEDLINE CURAD MEDISTRIP 1/4 X 1.5 IN, STERILE NON250114 | J90: 4 | K90: 71.94 | L90: 287.76 | M90: MEDL | N90: MEDICAL | O90: FALSE | P90: SO | R90: Medline Industries, Inc. | S90: 12001 General Milton Dr | U90: TX | V90: 78045 | X90: 1 | Z90: Medline Industries | AA90: Laredo | AB90: This location will be inactive Effective 7/17/17. new location 12001 General Milton Dr. Laredo, TX . If customer request NDA - use Fedex Collect # 326382027 | AC90: PCI-01 | AE90: =J90*VLOOKUP(H90,'Cost sheet'!$C$2:$G$1232,5,FALSE) -> 144.91808
A91: 45721 | B91: 45791 | C91: 46079 | D91: 45884 | E91: 0000063910 | F91: 1 | G91: LAREDO | H91: 6008 | I91: MEDLINE CURAD MEDISTRIP 1/4 X 1.5 IN, STERILE NON250114 | J91: 4 | K91: 71.94 | L91: 287.76 | M91: MEDL | N91: MEDICAL | O91: FALSE | P91: SO | R91: Medline Industries, Inc. | S91: 12001 General Milton Dr | U91: TX | V91: 78045 | X91: 1 | Z91: Medline Industries | AA91: Laredo | AB91: This location will be inactive Effective 7/17/17. new location 12001 General Milton Dr. Laredo, TX . If customer request NDA - use Fedex Collect # 326382027 | AC91: PCI-01 | AE91: =J91*VLOOKUP(H91,'Cost sheet'!$C$2:$G$1232,5,FALSE) -> 144.91808
A92: 45734 | B92: 45819 | C92: 46079 | D92: 45884 | E92: 0000063941 | F92: 20 | G92: B06 | H92: 6008 | I92: MEDLINE CURAD MEDISTRIP 1/4 X 1.5 IN, STERILE NON250114 | J92: 6 | K92: 71.94 | L92: 431.64 | M92: MEDL | N92: MEDICAL | O92: FALSE | P92: SO | R92: Medline Industries, Inc. | S92: 1 Medline Drive, Suite 100 | U92: TX | V92: 75172 | X92: 1 | Z92: Medline Industries LP | AA92: Wilmer | AC92: PCI-01 | AE92: =J92*VLOOKUP(H92,'Cost sheet'!$C$2:$G$1232,5,FALSE) -> 217.37711
A93: 45734 | B93: 45819 | C93: 46079 | D93: 45884 | E93: 0000063943 | F93: 20 | G93: C32 | H93: 6008 | I93: MEDLINE CURAD MEDISTRIP 1/4 X 1.5 IN, STERILE NON250114 | J93: 2 | K93: 71.94 | L93: 143.88 | M93: MEDL | N93: MEDICAL | O93: FALSE | P93: SO | R93: Medline Industries, Inc. | S93: 29895 US HWY 90 BUS | U93: TX | V93: 77494 | X93: 1 | Z93: Medline Industries LP | AA93: Katy | AC93: PCI-01 | AE93: =J93*VLOOKUP(H93,'Cost sheet'!$C$2:$G$1232,5,FALSE) -> 72.459038
A94: 45734 | B94: 45819 | C94: 46079 | D94: 45884 | E94: 0000063950 | F94: 30 | G94: B24 | H94: 6008 | I94: MEDLINE CURAD MEDISTRIP 1/4 X 1.5 IN, STERILE NON250114 | J94: 3 | K94: 71.94 | L94: 215.82 | M94: MEDL | N94: MEDICAL | O94: FALSE | P94: SO | R94: Medline Industries, Inc. | S94: 8001 SW 47th St. | U94: OK | V94: 73179 | X94: 1 | Z94: Medline Industries LP | AA94: Oklahoma City | AC94: PCI-01 | AE94: =J94*VLOOKUP(H94,'Cost sheet'!$C$2:$G$1232,5,FALSE) -> 108.68856
A95: 45734 | B95: 45819 | C95: 46079 | D95: 45884 | E95: 0000063956 | F95: 10 | G95: B49 | H95: 6008 | I95: MEDLINE CURAD MEDISTRIP 1/4 X 1.5 IN, STERILE NON250114 | J95: 1 | K95: 71.94 | L95: 71.94 | M95: MEDL | N95: MEDICAL | O95: FALSE | P95: SO | R95: Medline Industries, Inc. | S95: 42500 Winchester Rd | U95: CA | V95: 925902570 | X95: 1 | Z95: Medline Industries LP | AA95: Temecula | AC95: PCI-01 | AE95: =J95*VLOOKUP(H95,'Cost sheet'!$C$2:$G$1232,5,FALSE) -> 36.229519
A96: 45734 | B96: 45819 | C96: 46079 | D96: 45884 | E96: 0000063958 | F96: 10 | G96: B28 | H96: 6008 | I96: MEDLINE CURAD MEDISTRIP 1/4 X 1.5 IN, STERILE NON250114 | J96: 1 | K96: 71.94 | L96: 71.94 | M96: MEDL | N96: MEDICAL | O96: FALSE | P96: SO | R96: Medline Industries, Inc. | S96: 735 County Rd. 4 EAST | U96: AL | V96: 36067 | X96: 1 | Z96: Medline Industries LP | AA96: Prattville | AC96: PCI-01 | AE96: =J96*VLOOKUP(H96,'Cost sheet'!$C$2:$G$1232,5,FALSE) -> 36.229519
A97: 45734 | B97: 45819 | C97: 46079 | D97: 45884 | E97: 0000063964 | F97: 10 | G97: C50 | H97: 6008 | I97: MEDLINE CURAD MEDISTRIP 1/4 X 1.5 IN, STERILE NON250114 | J97: 4 | K97: 71.94 | L97: 287.76 | M97: MEDL | N97: MEDICAL | O97: FALSE | P97: SO | R97: Medline Industries, Inc. | S97: 8787 W BUCKEYE RD | U97: AZ | V97: 853539399 | X97: 1 | Z97: Medline Industries LP | AA97: TOLLESON | AC97: PCI-01 | AE97: =J97*VLOOKUP(H97,'Cost sheet'!$C$2:$G$1232,5,FALSE) -> 144.91808
A98: 45734 | B98: 45838 | C98: 46079 | D98: 45884 | E98: 0000063967 | F98: 1 | G98: LAREDO | H98: 6008 | I98: MEDLINE CURAD MEDISTRIP 1/4 X 1.5 IN, STERILE NON250114 | J98: 3 | K98: 71.94 | L98: 215.82 | M98: MEDL | N98: MEDICAL | O98: FALSE | P98: SO | R98: Medline Industries, Inc. | S98: 12001 General Milton Dr | U98: TX | V98: 78045 | X98: 1 | Z98: Medline Industries | AA98: Laredo | AB98: This location will be inactive Effective 7/17/17. new location 12001 General Milton Dr. Laredo, TX . If customer request NDA - use Fedex Collect # 326382027 | AC98: PCI-01 | AE98: =J98*VLOOKUP(H98,'Cost sheet'!$C$2:$G$1232,5,FALSE) -> 108.68856
A99: 45749 | B99: 45852 | C99: 46079 | D99: 45884 | E99: 0000064035 | F99: 1 | G99: LAREDO | H99: 6008 | I99: MEDLINE CURAD MEDISTRIP 1/4 X 1.5 IN, STERILE NON250114 | J99: 2 | K99: 71.94 | L99: 143.88 | M99: MEDL | N99: MEDICAL | O99: FALSE | P99: SO | R99: Medline Industries, Inc. | S99: 12001 General Milton Dr | U99: TX | V99: 78045 | X99: 1 | Z99: Medline Industries | AA99: Laredo | AB99: This location will be inactive Effective 7/17/17. new location 12001 General Milton Dr. Laredo, TX . If customer request NDA - use Fedex Collect # 326382027 | AC99: PCI-01 | AE99: =J99*VLOOKUP(H99,'Cost sheet'!$C$2:$G$1232,5,FALSE) -> 72.459038
A100: 45761 | B100: 45847 | C100: 46079 | D100: 45884 | E100: 0000064070 | F100: 10 | G100: B24 | H100: 6008 | I100: MEDLINE CURAD MEDISTRIP 1/4 X 1.5 IN, STERILE NON250114 | J100: 2 | K100: 71.94 | L100: 143.88 | M100: MEDL | N100: MEDICAL | O100: FALSE | P100: SO | R100: Medline Industries, Inc. | S100: 8001 SW 47th St. | U100: OK | V100: 73179 | X100: 1 | Z100: Medline Industries LP | AA100: Oklahoma City | AC100: PCI-01 | AE100: =J100*VLOOKUP(H100,'Cost sheet'!$C$2:$G$1232,5,FALSE) -> 72.459038
A101: 45761 | B101: 45847 | C101: 46079 | D101: 45884 | E101: 0000064071 | F101: 10 | G101: C05 | H101: 6008 | I101: MEDLINE CURAD MEDISTRIP 1/4 X 1.5 IN, STERILE NON250114 | J101: 9 | K101: 71.94 | L101: 647.46 | M101: MEDL | N101: MEDICAL | O101: FALSE | P101: SO | R101: Medline Industries, Inc. | S101: 1062 Old Dixie Hwy | U101: FL | V101: 33823 | X101: 1 | Z101: Medline Industries LP | AA101: Auburndale | AC101: PCI-01 | AE101: =J101*VLOOKUP(H101,'Cost sheet'!$C$2:$G$1232,5,FALSE) -> 326.06567
A102: 45761 | B102: 45847 | C102: 46079 | D102: 45884 | E102: 0000064073 | F102: 10 | G102: C50 | H102: 6008 | I102: MEDLINE CURAD MEDISTRIP 1/4 X 1.5 IN, STERILE NON250114 | J102: 1 | K102: 71.94 | L102: 71.94 | M102: MEDL | N102: MEDICAL | O102: FALSE | P102: SO | R102: Medline Industries, Inc. | S102: 8787 W BUCKEYE RD | U102: AZ | V102: 853539399 | X102: 1 | Z102: Medline Industries LP | AA102: TOLLESON | AC102: PCI-01 | AE102: =J102*VLOOKUP(H102,'Cost sheet'!$C$2:$G$1232,5,FALSE) -> 36.229519
A103: 45761 | B103: 45847 | C103: 46079 | D103: 45884 | E103: 0000064076 | F103: 20 | G103: B06 | H103: 6008 | I103: MEDLINE CURAD MEDISTRIP 1/4 X 1.5 IN, STERILE NON250114 | J103: 6 | K103: 71.94 | L103: 431.64 | M103: MEDL | N103: MEDICAL | O103: FALSE | P103: SO | R103: Medline Industries, Inc. | S103: 1 Medline Drive, Suite 100 | U103: TX | V103: 75172 | X103: 1 | Z103: Medline Industries LP | AA103: Wilmer | AC103: PCI-01 | AE103: =J103*VLOOKUP(H103,'Cost sheet'!$C$2:$G$1232,5,FALSE) -> 217.37711
A104: 45761 | B104: 45847 | C104: 46079 | D104: 45884 | E104: 0000064079 | F104: 20 | G104: C32 | H104: 6008 | I104: MEDLINE CURAD MEDISTRIP 1/4 X 1.5 IN, STERILE NON250114 | J104: 7 | K104: 71.94 | L104: 503.58 | M104: MEDL | N104: MEDICAL | O104: FALSE | P104: SO | R104: Medline Industries, Inc. | S104: 29895 US HWY 90 BUS | U104: TX | V104: 77494 | X104: 1 | Z104: Medline Industries LP | AA104: Katy | AC104: PCI-01 | AE104: =J104*VLOOKUP(H104,'Cost sheet'!$C$2:$G$1232,5,FALSE) -> 253.60663
...

Sheet Detail3
A1: Details for Sum of ExtendedLineAmount - Months (ScheduledShipDate): Dec, Years (ScheduledShipDate): 2026, ItemSalesClassCode: Filling OP, ItemCode: N-4001 (+)
A3: ScheduledShipDate | B3: PromisedShipDate | C3: SONumber | D3: LineNumber | E3: ShipToCode | F3: ItemCode | G3: ItemDescription | H3: OrderQuantity | I3: UnitPrice | J3: ExtendedLineAmount | K3: CustomerCode | L3: ItemSalesClassCode | M3: DropShip | N3: SOTypeCode | O3: FinalDestination | P3: CustomerName | Q3: ShipToAddress1 | R3: ShipToAddress2 | S3: ShipToStateCode | T3: ShipToZip | U3: ParentDocumentNumber | V3: Weight | W3: OrderMessage | X3: ShipToName | Y3: ShipToCity | Z3: ShippingInstructions | AA3: WarehouseCode | AB3: WarehouseName
A4: 46387 | B4: 46031 | C4: 0000064678 | D4: 10 | E4: C54 | F4: 4357 | G4: CURAD MEDIPLAST WART REMOVER CUR01496 | H4: 112 | I4: 57.96 | J4: 6491.52 | K4: MEDL | L4: MEDICAL | M4: FALSE | N4: SO | P4: Medline Industries, Inc. | Q4: 494 State Route 416 | R4: 494 State Route 416 | S4: NY | T4: 12549 | V4: 0 | X4: Medline Industries LP | Y4: Montgomery | AA4: PCI-01 | AB4: STRUKMYER, LLC
A5: 46387 | B5: 46031 | C5: 0000064676 | D5: 10 | E5: K46 | F5: 4357 | G5: CURAD MEDIPLAST WART REMOVER CUR01496 | H5: 14 | I5: 57.96 | J5: 811.44 | K5: MEDL | L5: MEDICAL | M5: FALSE | N5: SO | P5: Medline Industries, Inc. | Q5: 18601 Christopher Way, STE 100 | R5: 18601 Christopher Way, STE 100 | S5: CA | T5: 95330 | V5: 0 | X5: Medline Industries, Inc. | Y5: Lathrop | AA5: PCI-01 | AB5: STRUKMYER, LLC
A6: 46387 | B6: 46031 | C6: 0000064675 | D6: 10 | E6: C42 | F6: 4357 | G6: CURAD MEDIPLAST WART REMOVER CUR01496 | H6: 70 | I6: 57.96 | J6: 4057.2 | K6: MEDL | L6: MEDICAL | M6: FALSE | N6: SO | P6: Medline Industries, Inc. | Q6: 3446 Highway 51 N, Suite 100 | S6: MS | T6: 38672 | V6: 0 | X6: Medline Industries LP | Y6: Southaven | AA6: PCI-01 | AB6: STRUKMYER, LLC
A7: 46387 | B7: 46031 | C7: 0000064674 | D7: 10 | E7: C09 | F7: 4357 | G7: CURAD MEDIPLAST WART REMOVER CUR01496 | H7: 56 | I7: 57.96 | J7: 3245.76 | K7: MEDL | L7: MEDICAL | M7: FALSE | N7: SO | P7: Medline Industries, Inc. | Q7: 1960 W Miro Way | S7: CA | T7: 92376 | V7: 0 | X7: Medline Industries LP | Y7: Rialto | AA7: PCI-01 | AB7: STRUKMYER, LLC
A8: 46387 | B8: 46031 | C8: 0000064673 | D8: 10 | E8: B06 | F8: 4357 | G8: CURAD MEDIPLAST WART REMOVER CUR01496 | H8: 84 | I8: 57.96 | J8: 4868.64 | K8: MEDL | L8: MEDICAL | M8: FALSE | N8: SO | P8: Medline Industries, Inc. | Q8: 1 Medline Drive, Suite 100 | S8: TX | T8: 75172 | V8: 0 | X8: Medline Industries LP | Y8: Wilmer | AA8: PCI-01 | AB8: STRUKMYER, LLC
A9: 46387 | B9: 46031 | C9: 0000064672 | D9: 10 | E9: K56 | F9: 4357 | G9: CURAD MEDIPLAST WART REMOVER CUR01496 | H9: 14 | I9: 57.96 | J9: 811.44 | K9: MEDL | L9: MEDICAL | M9: FALSE | N9: SO | P9: Medline Industries, Inc. | Q9: 190 Medline Drive Suite 200 | S9: GA | T9: 31324 | V9: 0 | X9: Medline Industries LP | Y9: Richmond Hill | AA9: PCI-01 | AB9: STRUKMYER, LLC
A10: 46387 | B10: 46031 | C10: 0000064670 | D10: 10 | E10: C05 | F10: 4357 | G10: CURAD MEDIPLAST WART REMOVER CUR01496 | H10: 28 | I10: 57.96 | J10: 1622.88 | K10: MEDL | L10: MEDICAL | M10: FALSE | N10: SO | P10: Medline Industries, Inc. | Q10: 1062 Old Dixie Hwy | S10: FL | T10: 33823 | V10: 0 | X10: Medline Industries LP | Y10: Auburndale | AA10: PCI-01 | AB10: STRUKMYER, LLC
A11: 46387 | B11: 46031 | C11: 0000064669 | D11: 10 | E11: C03 | F11: 4357 | G11: CURAD MEDIPLAST WART REMOVER CUR01496 | H11: 140 | I11: 57.96 | J11: 8114.4 | K11: MEDL | L11: MEDICAL | M11: FALSE | N11: SO | P11: Medline Industries, Inc. | Q11: 1500 Medline Place | S11: GA | T11: 30253 | V11: 0 | X11: Medline Industries LP | Y11: McDonough | AA11: PCI-01 | AB11: STRUKMYER, LLC
A12: 46387 | B12: 46031 | C12: 0000064667 | D12: 10 | E12: C47 | F12: 4357 | G12: CURAD MEDIPLAST WART REMOVER CUR01496 | H12: 28 | I12: 57.96 | J12: 1622.88 | K12: MEDL | L12: MEDICAL | M12: FALSE | N12: SO | P12: Medline Industries, Inc. | Q12: 239 Belvidere Rd | S12: MD | T12: 21903 | V12: 0 | X12: Medline Industries LP | Y12: Perryville | AA12: PCI-01 | AB12: STRUKMYER, LLC
A13: 46387 | B13: 46017 | C13: 0000064643 | D13: 10 | E13: B24 | F13: 4357 | G13: CURAD MEDIPLAST WART REMOVER CUR01496 | H13: 28 | I13: 57.96 | J13: 1622.88 | K13: MEDL | L13: MEDICAL | M13: FALSE | N13: SO | P13: Medline Industries, Inc. | Q13: 8001 SW 47th St. | S13: OK | T13: 73179 | V13: 0 | X13: Medline Industries LP | Y13: Oklahoma City | AA13: PCI-01 | AB13: STRUKMYER, LLC
A14: 46387 | B14: 46017 | C14: 0000064642 | D14: 10 | E14: C05 | F14: 4357 | G14: CURAD MEDIPLAST WART REMOVER CUR01496 | H14: 14 | I14: 57.96 | J14: 811.44 | K14: MEDL | L14: MEDICAL | M14: FALSE | N14: SO | P14: Medline Industries, Inc. | Q14: 1062 Old Dixie Hwy | S14: FL | T14: 33823 | V14: 0 | X14: Medline Industries LP | Y14: Auburndale | AA14: PCI-01 | AB14: STRUKMYER, LLC
A15: 46387 | B15: 46017 | C15: 0000064641 | D15: 10 | E15: C02 | F15: 4357 | G15: CURAD MEDIPLAST WART REMOVER CUR01496 | H15: 182 | I15: 57.96 | J15: 10548.72 | K15: MEDL | L15: MEDICAL | M15: FALSE | N15: SO | P15: Medline Industries, Inc. | Q15: 2200 Cornerstone Pkwy, Ste 100 | S15: IL | T15: 60030 | V15: 0 | X15: Medline Industries LP | Y15: Grayslake | AA15: PCI-01 | AB15: STRUKMYER, LLC
A16: 46387 | B16: 46020 | C16: 0000064639 | D16: 10 | E16: C03 | F16: 4357 | G16: CURAD MEDIPLAST WART REMOVER CUR01496 | H16: 14 | I16: 57.96 | J16: 811.44 | K16: MEDL | L16: MEDICAL | M16: FALSE | N16: SO | P16: Medline Industries, Inc. | Q16: 1500 Medline Place | S16: GA | T16: 30253 | V16: 0 | X16: Medline Industries LP | Y16: McDonough | AA16: PCI-01 | AB16: STRUKMYER, LLC
A17: 46387 | B17: 46017 | C17: 0000064636 | D17: 10 | E17: C47 | F17: 4357 | G17: CURAD MEDIPLAST WART REMOVER CUR01496 | H17: 14 | I17: 57.96 | J17: 811.44 | K17: MEDL | L17: MEDICAL | M17: FALSE | N17: SO | P17: Medline Industries, Inc. | Q17: 239 Belvidere Rd | S17: MD | T17: 21903 | V17: 0 | X17: Medline Industries LP | Y17: Perryville | AA17: PCI-01 | AB17: STRUKMYER, LLC
A18: 46387 | B18: 46017 | C18: 0000064635 | D18: 10 | E18: C54 | F18: 4357 | G18: CURAD MEDIPLAST WART REMOVER CUR01496 | H18: 28 | I18: 57.96 | J18: 1622.88 | K18: MEDL | L18: MEDICAL | M18: FALSE | N18: SO | P18: Medline Industries, Inc. | Q18: 494 State Route 416 | R18: 494 State Route 416 | S18: NY | T18: 12549 | V18: 0 | X18: Medline Industries LP | Y18: Montgomery | AA18: PCI-01 | AB18: STRUKMYER, LLC
A19: 46387 | B19: 46020 | C19: 0000064633 | D19: 10 | E19: C42 | F19: 4357 | G19: CURAD MEDIPLAST WART REMOVER CUR01496 | H19: 28 | I19: 57.96 | J19: 1622.88 | K19: MEDL | L19: MEDICAL | M19: FALSE | N19: SO | P19: Medline Industries, Inc. | Q19: 3446 Highway 51 N, Suite 100 | S19: MS | T19: 38672 | V19: 0 | X19: Medline Industries LP | Y19: Southaven | AA19: PCI-01 | AB19: STRUKMYER, LLC
A20: 46387 | B20: 46020 | C20: 0000064632 | D20: 10 | E20: C02 | F20: 4357 | G20: CURAD MEDIPLAST WART REMOVER CUR01496 | H20: 182 | I20: 57.96 | J20: 10548.72 | K20: MEDL | L20: MEDICAL | M20: FALSE | N20: SO | P20: Medline Industries, Inc. | Q20: 2200 Cornerstone Pkwy, Ste 100 | S20: IL | T20: 60030 | V20: 0 | X20: Medline Industries LP | Y20: Grayslake | AA20: PCI-01 | AB20: STRUKMYER, LLC
A21: 46387 | B21: 46020 | C21: 0000064631 | D21: 10 | E21: K46 | F21: 4357 | G21: CURAD MEDIPLAST WART REMOVER CUR01496 | H21: 14 | I21: 57.96 | J21: 811.44 | K21: MEDL | L21: MEDICAL | M21: FALSE | N21: SO | P21: Medline Industries, Inc. | Q21: 18601 Christopher Way, STE 100 | R21: 18601 Christopher Way, STE 100 | S21: CA | T21: 95330 | V21: 0 | X21: Medline Industries, Inc. | Y21: Lathrop | AA21: PCI-01 | AB21: STRUKMYER, LLC
A22: 46387 | B22: 46017 | C22: 0000064630 | D22: 10 | E22: C41 | F22: 4357 | G22: CURAD MEDIPLAST WART REMOVER CUR01496 | H22: 14 | I22: 57.96 | J22: 811.44 | K22: MEDL | L22: MEDICAL | M22: FALSE | N22: SO | P22: Medline Industries, Inc. | Q22: 1040 Enterprise Parkway | S22: OH | T22: 43162 | V22: 0 | X22: Medline Industries LP | Y22: West Jefferson | AA22: PCI-01 | AB22: STRUKMYER, LLC
A23: 46387 | B23: 46020 | C23: 0000064629 | D23: 10 | E23: C09 | F23: 4357 | G23: CURAD MEDIPLAST WART REMOVER CUR01496 | H23: 28 | I23: 57.96 | J23: 1622.88 | K23: MEDL | L23: MEDICAL | M23: FALSE | N23: SO | P23: Medline Industries, Inc. | Q23: 1960 W Miro Way | S23: CA | T23: 92376 | V23: 0 | X23: Medline Industries LP | Y23: Rialto | AA23: PCI-01 | AB23: STRUKMYER, LLC
A24: 46387 | B24: 46020 | C24: 0000064628 | D24: 10 | E24: C05 | F24: 4357 | G24: CURAD MEDIPLAST WART REMOVER CUR01496 | H24: 42 | I24: 57.96 | J24: 2434.32 | K24: MEDL | L24: MEDICAL | M24: FALSE | N24: SO | P24: Medline Industries, Inc. | Q24: 1062 Old Dixie Hwy | S24: FL | T24: 33823 | V24: 0 | X24: Medline Industries LP | Y24: Auburndale | AA24: PCI-01 | AB24: STRUKMYER, LLC
A25: 46387 | B25: 46017 | C25: 0000064627 | D25: 10 | E25: C89 | F25: 4357 | G25: CURAD MEDIPLAST WART REMOVER CUR01496 | H25: 182 | I25: 57.96 | J25: 10548.72 | K25: MEDL | L25: MEDICAL | M25: FALSE | N25: SO | P25: Medline Industries, Inc. | Q25: 251 Hilton Dr | S25: IN | T25: 47130 | V25: 0 | X25: Medline Industries LP | Y25: Jeffersonville | AA25: PCI-01 | AB25: STRUKMYER, LLC
A26: 46387 | B26: 46020 | C26: 0000064626 | D26: 10 | E26: B29 | F26: 4357 | G26: CURAD MEDIPLAST WART REMOVER CUR01496 | H26: 28 | I26: 57.96 | J26: 1622.88 | K26: MEDL | L26: MEDICAL | M26: FALSE | N26: SO | P26: Medline Industries, Inc. | Q26: 13115 Brockton Lane N | S26: MN | T26: 55374 | V26: 0 | X26: Medline Industries LP | Y26: Rogers | AA26: PCI-01 | AB26: STRUKMYER, LLC
A27: 46387 | B27: 46017 | C27: 0000064625 | D27: 10 | E27: C09 | F27: 4357 | G27: CURAD MEDIPLAST WART REMOVER CUR01496 | H27: 56 | I27: 57.96 | J27: 3245.76 | K27: MEDL | L27: MEDICAL | M27: FALSE | N27: SO | P27: Medline Industries, Inc. | Q27: 1960 W Miro Way | S27: CA | T27: 92376 | V27: 0 | X27: Medline Industries LP | Y27: Rialto | AA27: PCI-01 | AB27: STRUKMYER, LLC
A28: 46387 | B28: 46002 | C28: 0000064573 | D28: 10 | E28: C02 | F28: 4357 | G28: CURAD MEDIPLAST WART REMOVER CUR01496 | H28: 98 | I28: 57.96 | J28: 5680.08 | K28: MEDL | L28: MEDICAL | M28: FALSE | N28: SO | P28: Medline Industries, Inc. | Q28: 2200 Cornerstone Pkwy, Ste 100 | S28: IL | T28: 60030 | V28: 0 | X28: Medline Industries LP | Y28: Grayslake | AA28: PCI-01 | AB28: STRUKMYER, LLC
A29: 46387 | B29: 46002 | C29: 0000064572 | D29: 10 | E29: C03 | F29: 4357 | G29: CURAD MEDIPLAST WART REMOVER CUR01496 | H29: 28 | I29: 57.96 | J29: 1622.88 | K29: MEDL | L29: MEDICAL | M29: FALSE | N29: SO | P29: Medline Industries, Inc. | Q29: 1500 Medline Place | S29: GA | T29: 30253 | V29: 0 | X29: Medline Industries LP | Y29: McDonough | AA29: PCI-01 | AB29: STRUKMYER, LLC
A30: 46387 | B30: 46002 | C30: 0000064570 | D30: 10 | E30: K56 | F30: 4357 | G30: CURAD MEDIPLAST WART REMOVER CUR01496 | H30: 14 | I30: 57.96 | J30: 811.44 | K30: MEDL | L30: MEDICAL | M30: FALSE | N30: SO | P30: Medline Industries, Inc. | Q30: 190 Medline Drive Suite 200 | S30: GA | T30: 31324 | V30: 0 | X30: Medline Industries LP | Y30: Richmond Hill | AA30: PCI-01 | AB30: STRUKMYER, LLC
A31: 46387 | B31: 46002 | C31: 0000064567 | D31: 10 | E31: C42 | F31: 4357 | G31: CURAD MEDIPLAST WART REMOVER CUR01496 | H31: 126 | I31: 57.96 | J31: 7302.96 | K31: MEDL | L31: MEDICAL | M31: FALSE | N31: SO | P31: Medline Industries, Inc. | Q31: 3446 Highway 51 N, Suite 100 | S31: MS | T31: 38672 | V31: 0 | X31: Medline Industries LP | Y31: Southaven | AA31: PCI-01 | AB31: STRUKMYER, LLC
A32: 46387 | B32: 46002 | C32: 0000064565 | D32: 10 | E32: C54 | F32: 4357 | G32: CURAD MEDIPLAST WART REMOVER CUR01496 | H32: 112 | I32: 57.96 | J32: 6491.52 | K32: MEDL | L32: MEDICAL | M32: FALSE | N32: SO | P32: Medline Industries, Inc. | Q32: 494 State Route 416 | R32: 494 State Route 416 | S32: NY | T32: 12549 | V32: 0 | X32: Medline Industries LP | Y32: Montgomery | AA32: PCI-01 | AB32: STRUKMYER, LLC
A33: 46387 | B33: 45989 | C33: 0000064539 | D33: 10 | E33: C47 | F33: 4357 | G33: CURAD MEDIPLAST WART REMOVER CUR01496 | H33: 42 | I33: 57.96 | J33: 2434.32 | K33: MEDL | L33: MEDICAL | M33: FALSE | N33: SO | P33: Medline Industries, Inc. | Q33: 239 Belvidere Rd | S33: MD | T33: 21903 | V33: 0 | X33: Medline Industries LP | Y33: Perryville | AA33: PCI-01 | AB33: STRUKMYER, LLC
A34: 46387 | B34: 45989 | C34: 0000064538 | D34: 10 | E34: C75 | F34: 4357 | G34: CURAD MEDIPLAST WART REMOVER CUR01496 | H34: 14 | I34: 57.96 | J34: 811.44 | K34: MEDL | L34: MEDICAL | M34: FALSE | N34: SO | P34: Medline Industries, Inc. | Q34: 3770 Hogum Bay Road Ne | S34: WA | T34: 98516 | V34: 0 | X34: Medline Industries LP | Y34: Lacey | AA34: PCI-01 | AB34: STRUKMYER, LLC
A35: 46387 | B35: 45989 | C35: 0000064536 | D35: 10 | E35: C42 | F35: 4357 | G35: CURAD MEDIPLAST WART REMOVER CUR01496 | H35: 28 | I35: 57.96 | J35: 1622.88 | K35: MEDL | L35: MEDICAL | M35: FALSE | N35: SO | P35: Medline Industries, Inc. | Q35: 3446 Highway 51 N, Suite 100 | S35: MS | T35: 38672 | V35: 0 | X35: Medline Industries LP | Y35: Southaven | AA35: PCI-01 | AB35: STRUKMYER, LLC
A36: 46387 | B36: 45989 | C36: 0000064535 | D36: 10 | E36: C41 | F36: 4357 | G36: CURAD MEDIPLAST WART REMOVER CUR01496 | H36: 14 | I36: 57.96 | J36: 811.44 | K36: MEDL | L36: MEDICAL | M36: FALSE | N36: SO | P36: Medline Industries, Inc. | Q36: 1040 Enterprise Parkway | S36: OH | T36: 43162 | V36: 0 | X36: Medline Industries LP | Y36: West Jefferson | AA36: PCI-01 | AB36: STRUKMYER, LLC
A37: 46387 | B37: 45989 | C37: 0000064534 | D37: 10 | E37: K46 | F37: 4357 | G37: CURAD MEDIPLAST WART REMOVER CUR01496 | H37: 14 | I37: 57.96 | J37: 811.44 | K37: MEDL | L37: MEDICAL | M37: FALSE | N37: SO | P37: Medline Industries, Inc. | Q37: 18601 Christopher Way, STE 100 | R37: 18601 Christopher Way, STE 100 | S37: CA | T37: 95330 | V37: 0 | X37: Medline Industries, Inc. | Y37: Lathrop | AA37: PCI-01 | AB37: STRUKMYER, LLC
A38: 46387 | B38: 45989 | C38: 0000064533 | D38: 10 | E38: C54 | F38: 4357 | G38: CURAD MEDIPLAST WART REMOVER CUR01496 | H38: 210 | I38: 57.96 | J38: 12171.6 | K38: MEDL | L38: MEDICAL | M38: FALSE | N38: SO | P38: Medline Industries, Inc. | Q38: 494 State Route 416 | R38: 494 State Route 416 | S38: NY | T38: 12549 | V38: 0 | X38: Medline Industries LP | Y38: Montgomery | AA38: PCI-01 | AB38: STRUKMYER, LLC
A39: 46387 | B39: 45989 | C39: 0000064532 | D39: 10 | E39: C40 | F39: 4357 | G39: CURAD MEDIPLAST WART REMOVER CUR01496 | H39: 28 | I39: 57.96 | J39: 1622.88 | K39: MEDL | L39: MEDICAL | M39: FALSE | N39: SO | P39: Medline Industries, Inc. | Q39: 81 Campanelli Drive | S39: MA | T39: 01569 | V39: 0 | X39: Medline Industries LP | Y39: UXBRIDGE | AA39: PCI-01 | AB39: STRUKMYER, LLC
A40: 46387 | B40: 45989 | C40: 0000064531 | D40: 10 | E40: B30 | F40: 4357 | G40: CURAD MEDIPLAST WART REMOVER CUR01496 | H40: 14 | I40: 57.96 | J40: 811.44 | K40: MEDL | L40: MEDICAL | M40: FALSE | N40: SO | P40: Medline Industries, Inc. | Q40: 1900 Meadowville Technology Parkway | S40: VA | T40: 23836 | V40: 0 | X40: Medline Industries LP | Y40: Chester | AA40: PCI-01 | AB40: STRUKMYER, LLC
A41: 46387 | B41: 45989 | C41: 0000064527 | D41: 10 | E41: C09 | F41: 4357 | G41: CURAD MEDIPLAST WART REMOVER CUR01496 | H41: 294 | I41: 57.96 | J41: 17040.24 | K41: MEDL | L41: MEDICAL | M41: FALSE | N41: SO | P41: Medline Industries, Inc. | Q41: 1960 W Miro Way | S41: CA | T41: 92376 | V41: 0 | X41: Medline Industries LP | Y41: Rialto | AA41: PCI-01 | AB41: STRUKMYER, LLC
A42: 46387 | B42: 45985 | C42: 0000064526 | D42: 10 | E42: B29 | F42: 4357 | G42: CURAD MEDIPLAST WART REMOVER CUR01496 | H42: 28 | I42: 57.96 | J42: 1622.88 | K42: MEDL | L42: MEDICAL | M42: FALSE | N42: SO | P42: Medline Industries, Inc. | Q42: 13115 Brockton Lane N | S42: MN | T42: 55374 | V42: 0 | X42: Medline Industries LP | Y42: Rogers | AA42: PCI-01 | AB42: STRUKMYER, LLC
A43: 46387 | B43: 45989 | C43: 0000064524 | D43: 10 | E43: B24 | F43: 4357 | G43: CURAD MEDIPLAST WART REMOVER CUR01496 | H43: 14 | I43: 57.96 | J43: 811.44 | K43: MEDL | L43: MEDICAL | M43: FALSE | N43: SO | P43: Medline Industries, Inc. | Q43: 8001 SW 47th St. | S43: OK | T43: 73179 | V43: 0 | X43: Medline Industries LP | Y43: Oklahoma City | AA43: PCI-01 | AB43: STRUKMYER, LLC
A44: 46387 | B44: 45989 | C44: 0000064523 | D44: 10 | E44: C02 | F44: 4357 | G44: CURAD MEDIPLAST WART REMOVER CUR01496 | H44: 70 | I44: 57.96 | J44: 4057.2 | K44: MEDL | L44: MEDICAL | M44: FALSE | N44: SO | P44: Medline Industries, Inc. | Q44: 2200 Cornerstone Pkwy, Ste 100 | S44: IL | T44: 60030 | V44: 0 | X44: Medline Industries LP | Y44: Grayslake | AA44: PCI-01 | AB44: STRUKMYER, LLC
A45: 46387 | B45: 45989 | C45: 0000064522 | D45: 10 | E45: B49 | F45: 4357 | G45: CURAD MEDIPLAST WART REMOVER CUR01496 | H45: 182 | I45: 57.96 | J45: 10548.72 | K45: MEDL | L45: MEDICAL | M45: FALSE | N45: SO | P45: Medline Industries, Inc. | Q45: 42500 Winchester Rd | S45: CA | T45: 925902570 | V45: 0 | X45: Medline Industries LP | Y45: Temecula | AA45: PCI-01 | AB45: STRUKMYER, LLC
A46: 46387 | B46: 45985 | C46: 0000064486 | D46: 10 | E46: C59 | F46: 4357 | G46: CURAD MEDIPLAST WART REMOVER CUR01496 | H46: 56 | I46: 57.96 | J46: 3245.76 | K46: MEDL | L46: MEDICAL | M46: FALSE | N46: SO | P46: Medline Industries, Inc. | Q46: 2100 Industrial Park Rd | S46: LA | T46: 70401 | V46: 0 | X46: Medline Industries, LP | Y46: Hammond | AA46: PCI-01 | AB46: STRUKMYER, LLC
A47: 46387 | B47: 45985 | C47: 0000064485 | D47: 10 | E47: C54 | F47: 4357 | G47: CURAD MEDIPLAST WART REMOVER CUR01496 | H47: 140 | I47: 57.96 | J47: 8114.4 | K47: MEDL | L47: MEDICAL | M47: FALSE | N47: SO | P47: Medline Industries, Inc. | Q47: 494 State Route 416 | R47: 494 State Route 416 | S47: NY | T47: 12549 | V47: 0 | X47: Medline Industries LP | Y47: Montgomery | AA47: PCI-01 | AB47: STRUKMYER, LLC
A48: 46387 | B48: 45985 | C48: 0000064484 | D48: 10 | E48: C42 | F48: 4357 | G48: CURAD MEDIPLAST WART REMOVER CUR01496 | H48: 56 | I48: 57.96 | J48: 3245.76 | K48: MEDL | L48: MEDICAL | M48: FALSE | N48: SO | P48: Medline Industries, Inc. | Q48: 3446 Highway 51 N, Suite 100 | S48: MS | T48: 38672 | V48: 0 | X48: Medline Industries LP | Y48: Southaven | AA48: PCI-01 | AB48: STRUKMYER, LLC
A49: 46387 | B49: 46387 | C49: 0000063869 | D49: 5 | E49: ATLANTA | F49: 7486 | G49: CARDINAL HEALTH TELFA ADHESIVE DRESSING 3"x4" 7643 | H49: 900 | I49: 259.272 | J49: 233344.8 | K49: COVIDMA | L49: MEDICAL | M49: FALSE | N49: SO | P49: Patient Recovery | Q49: 110 Kendall Park Lane | S49: GA | T49: 30336 | V49: 0 | W49: Cardinal Blanket 18 Month PO
A50: 46387 | B50: 46387 | C50: 0000063869 | D50: 4 | E50: ATLANTA | F50: 7482 | G50: CARDINAL HEALTH TELFA MINI ISLAND DRESSING 2"x3.75" 7539LF | H50: 7500 | I50: 32.88 | J50: 246600 | K50: COVIDMA | L50: MEDICAL | M50: FALSE | N50: SO | P50: Patient Recovery | Q50: 110 Kendall Park Lane | S50: GA | T50: 30336 | V50: 0 | W50: Cardinal Blanket 18 Month PO
A51: 46387 | B51: 46387 | C51: 0000063869 | D51: 3 | E51: ATLANTA | F51: 7487 | G51: CARDINAL HEALTH TELFA ADHESIVE DRESSING 2"x3" 6017 | H51: 900 | I51: 269.76 | J51: 242784 | K51: COVIDMA | L51: MEDICAL | M51: FALSE | N51: SO | P51: Patient Recovery | Q51: 110 Kendall Park Lane | S51: GA | T51: 30336 | V51: 0 | W51: Cardinal Blanket 18 Month PO
A52: 46387 | B52: 46387 | C52: 0000063869 | D52: 1 | E52: ATLANTA | F52: 7489 | G52: CARDINAL HEALTH TELFA NON-ADHERENT DRESSING 2"x3" 1961 | H52: 900 | I52: 108 | J52: 97200 | K52: COVIDMA | L52: MEDICAL | M52: FALSE | N52: SO | P52: Patient Recovery | Q52: 110 Kendall Park Lane | S52: GA | T52: 30336 | V52: 0 | W52: Cardinal Blanket 18 Month PO
A53: 46387 | B53: 45992 | C53: 0000063862 | D53: 1 | E53: York | F53: 6339 | G53: THERBR PLUS PMINT RINSE 12/16OZ EXP CLM1557439 | H53: 2500 | I53: 23.17 | J53: 57925 | K53: ORORA | L53: Filling OP | M53: FALSE | N53: SO | P53: Orora Business Service Center | Q53: 5197 Commerce Dr | S53: PA | T53: 17408 | V53: 0 | X53: YK - C&D York | Y53: York | Z53: Need special certificate COA before shipped | AA53: PCI-01 | AB53: STRUKMYER, LLC
A54: 46387 | B54: 44972 | C54: 0000059978 | D54: 4 | E54: Langhorne | F54: 6929 | G54: NEXGEL SILVER SEAL 2X3 HYDROGEL DRESSING | H54: 150 | I54: 44.364 | J54: 6654.6 | K54: Nexgel | L54: MEDICAL | M54: FALSE | N54: SO | P54: Nexgel | Q54: 2150 Cabot Blvd West | R54: STE B | S54: PA | T54: 19047 | V54: 0 | X54: Nexgel, Inc | Y54: Langhorne | AA54: PCI-01 | AB54: STRUKMYER, LLC
A55: 46387 | B55: 44972 | C55: 0000059978 | D55: 3 | E55: Langhorne | F55: 6930 | G55: NEXGEL TURF GUARD 2X3 HYDROGEL DRESSING | H55: 118 | I55: 44.364 | J55: 5234.95 | K55: Nexgel | L55: MEDICAL | M55: FALSE | N55: SO | P55: Nexgel | Q55: 2150 Cabot Blvd West | R55: STE B | S55: PA | T55: 19047 | V55: 0 | X55: Nexgel, Inc | Y55: Langhorne | AA55: PCI-01 | AB55: STRUKMYER, LLC
A56: 46387 | B56: 44972 | C56: 0000059978 | D56: 2 | E56: Langhorne | F56: 6929 | G56: NEXGEL SILVER SEAL 2X3 HYDROGEL DRESSING | H56: 31 | I56: 44.364 | J56: 1375.28 | K56: Nexgel | L56: MEDICAL | M56: FALSE | N56: SO | P56: Nexgel | Q56: 2150 Cabot Blvd West | R56: STE B | S56: PA | T56: 19047 | V56: 0 | X56: Nexgel, Inc | Y56: Langhorne | AA56: PCI-01 | AB56: STRUKMYER, LLC
A57: 46385 | B57: 2 | C57: 0000065006 | D57: 1 | E57: LAREDO | F57: 6039 | G57: MEDLINE SURESITE 4 X 4.75 MSC2304 | H57: 140 | I57: 20.61 | J57: 2885.4 | K57: MEDL | L57: MEDICAL | M57: FALSE | N57: SO | P57: Medline Industries, Inc. | Q57: 12001 General Milton Dr | S57: TX | T57: 78045 | V57: 4 | X57: Medline Industries | Y57: Laredo | Z57: This location will be inactive Effective 7/17/17. new location 12001 General Milton Dr. Laredo, TX . If customer request NDA - use Fedex Collect # 326382027 | AA57: PCI-01 | AB57: STRUKMYER, LLC
A58: 46385 | B58: 2 | C58: 0000065005 | D58: 1 | E58: MORENO | F58: 6039 | G58: MEDLINE SURESITE 4 X 4.75 MSC2304 | H58: 144 | I58: 20.61 | J58: 2967.84 | K58: MEDL | L58: MEDICAL | M58: FALSE | N58: SO | P58: Medline Industries, Inc. | Q58: 16415 Cosmos Street | S58: CA | T58: 92551 | V58: 4 | X58: Medline - SPT Division | Y58: Moreno Valley | Z58: call for dock appointment 951-296-2639 x 4237 or email yduran@medline.com | AA58: PCI-01 | AB58: STRUKMYER, LLC
A59: 46385 | B59: 2 | C59: 0000065004 | D59: 1 | E59: NORTHPT | F59: 4785 | G59: MEDLINE 119883 10"x16" Instrument Drape | H59: 1 | I59: 160 | J59: 160 | K59: MEDL | L59: MEDICAL | M59: FALSE | N59: SO | P59: Medline Industries, Inc. | Q59: 1170 South Northpoint Blvd. | S59: IL | T59: 60085 | V59: 14 | X59: Medline - SPT Division | Y59: Waukegan | AA59: PCI-01 | AB59: STRUKMYER, LLC
A60: 46385 | B60: 2 | C60: 0000064982 | D60: 1 | E60: LAREDO | F60: 606 | G60: MEDISTRIP 1/8 IN X 3 IN BULK | H60: 1 | I60: 193.8 | J60: 193.8 | K60: MEDL | L60: MEDICAL | M60: FALSE | N60: SO | P60: Medline Industries, Inc. | Q60: 12001 General Milton Dr | S60: TX | T60: 78045 | V60: 0 | X60: Medline Industries | Y60: Laredo | Z60: This location will be inactive Effective 7/17/17. new location 12001 General Milton Dr. Laredo, TX . If customer request NDA - use Fedex Collect # 326382027 | AA60: PCI-01 | AB60: STRUKMYER, LLC
A61: 46385 | B61: 2 | C61: 0000064981 | D61: 1 | E61: LAREDO | F61: 4785 | G61: MEDLINE 119883 10"x16" Instrument Drape | H61: 2 | I61: 160 | J61: 320 | K61: MEDL | L61: MEDICAL | M61: FALSE | N61: SO | P61: Medline Industries, Inc. | Q61: 12001 General Milton Dr | S61: TX | T61: 78045 | V61: 14 | X61: Medline Industries | Y61: Laredo | Z61: This location will be inactive Effective 7/17/17. new location 12001 General Milton Dr. Laredo, TX . If customer request NDA - use Fedex Collect # 326382027 | AA61: PCI-01 | AB61: STRUKMYER, LLC
A62: 46385 | B62: 2 | C62: 0000064974 | D62: 5 | E62: FRANCE | F62: 3853 | G62: MEDISTRIP 1 IN X 4 IN BULK NON-STERILE | H62: 2 | I62: 196.5 | J62: 393 | K62: MEDL EURO | L62: MEDICAL | M62: FALSE | N62: SO | P62: Medline Assembly France SAS | Q62: Rue du President Kennedy | S62: .. | T62: 44110 | V62: 0 | X62: Medline Assembly France SAS | Y62: Chateaubriant | Z62: DHL EXPRESS WORLDWIDE 956478111.. ****Warehouse is opened from 5am to 1pm | AA62: PCI-01 | AB62: STRUKMYER, LLC
A63: 46385 | B63: 2 | C63: 0000064974 | D63: 4 | E63: FRANCE | F63: 3852 | G63: MEDISTRIP 1/4 IN X 3 IN BULK NON-STERILE | H63: 1 | I63: 119 | J63: 119 | K63: MEDL EURO | L63: MEDICAL | M63: FALSE | N63: SO | P63: Medline Assembly France SAS | Q63: Rue du President Kennedy | S63: .. | T63: 44110 | V63: 0 | X63: Medline Assembly France SAS | Y63: Chateaubriant | Z63: DHL EXPRESS WORLDWIDE 956478111.. ****Warehouse is opened from 5am to 1pm | AA63: PCI-01 | AB63: STRUKMYER, LLC
A64: 46385 | B64: 2 | C64: 0000064974 | D64: 3 | E64: FRANCE | F64: 3851 | G64: MEDISTRIP 1/4 IN X 4 IN BULK NON-STERILE 5/CD | H64: 5 | I64: 195 | J64: 975 | K64: MEDL EURO | L64: MEDICAL | M64: FALSE | N64: SO | P64: Medline Assembly France SAS | Q64: Rue du President Kennedy | S64: .. | T64: 44110 | V64: 0 | X64: Medline Assembly France SAS | Y64: Chateaubriant | Z64: DHL EXPRESS WORLDWIDE 956478111.. ****Warehouse is opened from 5am to 1pm | AA64: PCI-01 | AB64: STRUKMYER, LLC
A65: 46385 | B65: 2 | C65: 0000064974 | D65: 2 | E65: FRANCE | F65: 3850 | G65: MEDISTRIP 1/2 IN X 4 IN BULK NONSTERILE 3/CD | H65: 4 | I65: 1943 | J65: 7772 | K65: MEDL EURO | L65: MEDICAL | M65: FALSE | N65: SO | P65: Medline Assembly France SAS | Q65: Rue du President Kennedy | S65: .. | T65: 44110 | V65: 0 | X65: Medline Assembly France SAS | Y65: Chateaubriant | Z65: DHL EXPRESS WORLDWIDE 956478111.. ****Warehouse is opened from 5am to 1pm | AA65: PCI-01 | AB65: STRUKMYER, LLC
A66: 46385 | B66: 2 | C66: 0000064974 | D66: 1 | E66: FRANCE | F66: 3849 | G66: MEDISTRIP 1/4 IN X 1.5 IN BULK NON-STERILE | H66: 1 | I66: 165 | J66: 165 | K66: MEDL EURO | L66: MEDICAL | M66: FALSE | N66: SO | P66: Medline Assembly France SAS | Q66: Rue du President Kennedy | S66: .. | T66: 44110 | V66: 0 | X66: Medline Assembly France SAS | Y66: Chateaubriant | Z66: DHL EXPRESS WORLDWIDE 956478111.. ****Warehouse is opened from 5am to 1pm | AA66: PCI-01 | AB66: STRUKMYER, LLC
A67: 46385 | B67: 2 | C67: 0000064971 | D67: 5 | E67: BILL | F67: 3853 | G67: MEDISTRIP 1 IN X 4 IN BULK NON-STERILE | H67: 5 | I67: 196.5 | J67: 982.5 | K67: MEDL SLOV | L67: MEDICAL | M67: FALSE | N67: SO | P67: Medline Assembly Slovakia S.R.O | Q67: Malobielicka 284/8 | S67: .. | T67: 95804 | V67: 0 | X67: Medline Assembly Slovakia S.R.O | Y67: Partizanske | Z67: DHL EXPRESS Worldwide 954238829 | AA67: PCI-01 | AB67: STRUKMYER, LLC
A68: 46385 | B68: 2 | C68: 0000064971 | D68: 4 | E68: BILL | F68: 3852 | G68: MEDISTRIP 1/4 IN X 3 IN BULK NON-STERILE | H68: 3 | I68: 119 | J68: 357 | K68: MEDL SLOV | L68: MEDICAL | M68: FALSE | N68: SO | P68: Medline Assembly Slovakia S.R.O | Q68: Malobielicka 284/8 | S68: .. | T68: 95804 | V68: 0 | X68: Medline Assembly Slovakia S.R.O | Y68: Partizanske | Z68: DHL EXPRESS Worldwide 954238829 | AA68: PCI-01 | AB68: STRUKMYER, LLC
A69: 46385 | B69: 2 | C69: 0000064971 | D69: 3 | E69: BILL | F69: 3851 | G69: MEDISTRIP 1/4 IN X 4 IN BULK NON-STERILE 5/CD | H69: 1 | I69: 195 | J69: 195 | K69: MEDL SLOV | L69: MEDICAL | M69: FALSE | N69: SO | P69: Medline Assembly Slovakia S.R.O | Q69: Malobielicka 284/8 | S69: .. | T69: 95804 | V69: 0 | X69: Medline Assembly Slovakia S.R.O | Y69: Partizanske | Z69: DHL EXPRESS Worldwide 954238829 | AA69: PCI-01 | AB69: STRUKMYER, LLC
A70: 46385 | B70: 2 | C70: 0000064971 | D70: 2 | E70: BILL | F70: 3850 | G70: MEDISTRIP 1/2 IN X 4 IN BULK NONSTERILE 3/CD | H70: 3 | I70: 1943 | J70: 5829 | K70: MEDL SLOV | L70: MEDICAL | M70: FALSE | N70: SO | P70: Medline Assembly Slovakia S.R.O | Q70: Malobielicka 284/8 | S70: .. | T70: 95804 | V70: 0 | X70: Medline Assembly Slovakia S.R.O | Y70: Partizanske | Z70: DHL EXPRESS Worldwide 954238829 | AA70: PCI-01 | AB70: STRUKMYER, LLC
A71: 46385 | B71: 2 | C71: 0000064971 | D71: 1 | E71: BILL | F71: 3849 | G71: MEDISTRIP 1/4 IN X 1.5 IN BULK NON-STERILE | H71: 1 | I71: 165 | J71: 165 | K71: MEDL SLOV | L71: MEDICAL | M71: FALSE | N71: SO | P71: Medline Assembly Slovakia S.R.O | Q71: Malobielicka 284/8 | S71: .. | T71: 95804 | V71: 0 | X71: Medline Assembly Slovakia S.R.O | Y71: Partizanske | Z71: DHL EXPRESS Worldwide 954238829 | AA71: PCI-01 | AB71: STRUKMYER, LLC
A72: 46385 | B72: 2 | C72: 0000064964 | D72: 1 | E72: NORTHPT | F72: 6010 | G72: MEDLINE CURAD MEDISTRIP 1/2 X 4 IN STERILE NON250412 | H72: 20 | I72: 102 | J72: 2040 | K72: MEDL | L72: MEDICAL | M72: FALSE | N72: SO | P72: Medline Industries, Inc. | Q72: 1170 South Northpoint Blvd. | S72: IL | T72: 60085 | V72: 2 | X72: Medline - SPT Division | Y72: Waukegan | AA72: PCI-01 | AB72: STRUKMYER, LLC
A73: 46385 | B73: 2 | C73: 0000064960 | D73: 1 | E73: LAREDO | F73: 610 | G73: MEDISTRIP 1 IN X 4 IN BULK | H73: 3 | I73: 196.5 | J73: 589.5 | K73: MEDL | L73: MEDICAL | M73: FALSE | N73: SO | P73: Medline Industries, Inc. | Q73: 12001 General Milton Dr | S73: TX | T73: 78045 | V73: 4 | X73: Medline Industries | Y73: Laredo | Z73: This location will be inactive Effective 7/17/17. new location 12001 General Milton Dr. Laredo, TX . If customer request NDA - use Fedex Collect # 326382027 | AA73: PCI-01 | AB73: STRUKMYER, LLC
A74: 46385 | B74: 2 | C74: 0000064957 | D74: 1 | E74: LAREDO | F74: 4785 | G74: MEDLINE 119883 10"x16" Instrument Drape | H74: 9 | I74: 160 | J74: 1440 | K74: MEDL | L74: MEDICAL | M74: FALSE | N74: SO | P74: Medline Industries, Inc. | Q74: 12001 General Milton Dr | S74: TX | T74: 78045 | V74: 14 | X74: Medline Industries | Y74: Laredo | Z74: This location will be inactive Effective 7/17/17. new location 12001 General Milton Dr. Laredo, TX . If customer request NDA - use Fedex Collect # 326382027 | AA74: PCI-01 | AB74: STRUKMYER, LLC
A75: 46385 | B75: 2 | C75: 0000064953 | D75: 20 | E75: C89 | F75: 5116 | G75: MEDLINE OPTIFOAM THIN 2X3 MSC1523EP | H75: 4 | I75: 63.42 | J75: 253.68 | K75: MEDL | L75: MEDICAL | M75: FALSE | N75: SO | P75: Medline Industries, Inc. | Q75: 251 Hilton Dr | S75: IN | T75: 47130 | V75: 0 | X75: Medline Industries LP | Y75: Jeffersonville | AA75: PCI-01 | AB75: STRUKMYER, LLC
A76: 46385 | B76: 2 | C76: 0000064951 | D76: 30 | E76: C09 | F76: 5117 | G76: MEDLINE OPTIFOAM THIN 4x4 MSC1544EP | H76: 11 | I76: 94.6 | J76: 1040.6 | K76: MEDL | L76: MEDICAL | M76: FALSE | N76: SO | P76: Medline Industries, Inc. | Q76: 1960 W Miro Way | S76: CA | T76: 92376 | V76: 0 | X76: Medline Industries LP | Y76: Rialto | AA76: PCI-01 | AB76: STRUKMYER, LLC
A77: 46385 | B77: 2 | C77: 0000064951 | D77: 20 | E77: C09 | F77: 5116 | G77: MEDLINE OPTIFOAM THIN 2X3 MSC1523EP | H77: 10 | I77: 63.42 | J77: 634.2 | K77: MEDL | L77: MEDICAL | M77: FALSE | N77: SO | P77: Medline Industries, Inc. | Q77: 1960 W Miro Way | S77: CA | T77: 92376 | V77: 0 | X77: Medline Industries LP | Y77: Rialto | AA77: PCI-01 | AB77: STRUKMYER, LLC
A78: 46385 | B78: 2 | C78: 0000064950 | D78: 10 | E78: C03 | F78: 5116 | G78: MEDLINE OPTIFOAM THIN 2X3 MSC1523EP | H78: 10 | I78: 63.42 | J78: 634.2 | K78: MEDL | L78: MEDICAL | M78: FALSE | N78: SO | P78: Medline Industries, Inc. | Q78: 1500 Medline Place | S78: GA | T78: 30253 | V78: 0 | X78: Medline Industries LP | Y78: McDonough | AA78: PCI-01 | AB78: STRUKMYER, LLC
A79: 46385 | B79: 2 | C79: 0000064949 | D79: 20 | E79: C46 | F79: 5117 | G79: MEDLINE OPTIFOAM THIN 4x4 MSC1544EP | H79: 18 | I79: 94.6 | J79: 1702.8 | K79: MEDL | L79: MEDICAL | M79: FALSE | N79: SO | P79: Medline Industries, Inc. | Q79: 5701 PROMONTORY PKWY | S79: CA | T79: 953779201 | V79: 0 | X79: Medline Industries LP | Y79: TRACY | AA79: PCI-01 | AB79: STRUKMYER, LLC
A80: 46385 | B80: 2 | C80: 0000064949 | D80: 10 | E80: C46 | F80: 5116 | G80: MEDLINE OPTIFOAM THIN 2X3 MSC1523EP | H80: 4 | I80: 63.42 | J80: 253.68 | K80: MEDL | L80: MEDICAL | M80: FALSE | N80: SO | P80: Medline Industries, Inc. | Q80: 5701 PROMONTORY PKWY | S80: CA | T80: 953779201 | V80: 0 | X80: Medline Industries LP | Y80: TRACY | AA80: PCI-01 | AB80: STRUKMYER, LLC
A81: 46385 | B81: 2 | C81: 0000064948 | D81: 10 | E81: B36 | F81: 5117 | G81: MEDLINE OPTIFOAM THIN 4x4 MSC1544EP | H81: 1 | I81: 94.6 | J81: 94.6 | K81: MEDL | L81: MEDICAL | M81: FALSE | N81: SO | P81: Medline Industries, Inc. | Q81: 1989 TRANSIT WAY | S81: NY | T81: 144203007 | V81: 0 | X81: Medline Industries LP | Y81: BROCKPORT | AA81: PCI-01 | AB81: STRUKMYER, LLC
A82: 46385 | B82: 2 | C82: 0000064946 | D82: 20 | E82: C41 | F82: 5116 | G82: MEDLINE OPTIFOAM THIN 2X3 MSC1523EP | H82: 15 | I82: 63.42 | J82: 951.3 | K82: MEDL | L82: MEDICAL | M82: FALSE | N82: SO | P82: Medline Industries, Inc. | Q82: 1040 Enterprise Parkway | S82: OH | T82: 43162 | V82: 0 | X82: Medline Industries LP | Y82: West Jefferson | AA82: PCI-01 | AB82: STRUKMYER, LLC
A83: 46385 | B83: 2 | C83: 0000064943 | D83: 10 | E83: C02 | F83: 5117 | G83: MEDLINE OPTIFOAM THIN 4x4 MSC1544EP | H83: 3 | I83: 94.6 | J83: 283.8 | K83: MEDL | L83: MEDICAL | M83: FALSE | N83: SO | P83: Medline Industries, Inc. | Q83: 2200 Cornerstone Pkwy, Ste 100 | S83: IL | T83: 60030 | V83: 0 | X83: Medline Industries LP | Y83: Grayslake | AA83: PCI-01 | AB83: STRUKMYER, LLC
A84: 46385 | B84: 2 | C84: 0000064941 | D84: 10 | E84: B51 | F84: 5116 | G84: MEDLINE OPTIFOAM THIN 2X3 MSC1523EP | H84: 24 | I84: 63.42 | J84: 1522.08 | K84: MEDL | L84: MEDICAL | M84: FALSE | N84: SO | P84: Medline Industries, Inc. | Q84: 60 Athletes Way N STE 100 | S84: TN | T84: 37122 | V84: 0 | X84: Medline Industries LP | Y84: Mount Juliet | AA84: PCI-01 | AB84: STRUKMYER, LLC
A85: 46385 | B85: 2 | C85: 0000064930 | D85: 2 | E85: MORENO | F85: 6008 | G85: MEDLINE CURAD MEDISTRIP 1/4 X 1.5 IN, STERILE NON250114 | H85: 1 | I85: 71.94 | J85: 71.94 | K85: MEDL | L85: MEDICAL | M85: FALSE | N85: SO | P85: Medline Industries, Inc. | Q85: 16415 Cosmos Street | S85: CA | T85: 92551 | V85: 1 | X85: Medline - SPT Division | Y85: Moreno Valley | Z85: call for dock appointment 951-296-2639 x 4237 or email yduran@medline.com | AA85: PCI-01 | AB85: STRUKMYER, LLC
A86: 46385 | B86: 2 | C86: 0000064930 | D86: 1 | E86: MORENO | F86: 609 | G86: MEDISTRIP 1/4 IN X 3 IN BULK | H86: 74 | I86: 119 | J86: 8806 | K86: MEDL | L86: MEDICAL | M86: FALSE | N86: SO | P86: Medline Industries, Inc. | Q86: 16415 Cosmos Street | S86: CA | T86: 92551 | V86: 1 | X86: Medline - SPT Division | Y86: Moreno Valley | Z86: call for dock appointment 951-296-2639 x 4237 or email yduran@medline.com | AA86: PCI-01 | AB86: STRUKMYER, LLC
A87: 46385 | B87: 2 | C87: 0000064929 | D87: 1 | E87: LAREDO | F87: 609 | G87: MEDISTRIP 1/4 IN X 3 IN BULK | H87: 8 | I87: 119 | J87: 952 | K87: MEDL | L87: MEDICAL | M87: FALSE | N87: SO | P87: Medline Industries, Inc. | Q87: 12001 General Milton Dr | S87: TX | T87: 78045 | V87: 1 | X87: Medline Industries | Y87: Laredo | Z87: This location will be inactive Effective 7/17/17. new location 12001 General Milton Dr. Laredo, TX . If customer request NDA - use Fedex Collect # 326382027 | AA87: PCI-01 | AB87: STRUKMYER, LLC
A88: 46385 | B88: 2 | C88: 0000064922 | D88: 1 | E88: MORENO | F88: 609 | G88: MEDISTRIP 1/4 IN X 3 IN BULK | H88: 13 | I88: 119 | J88: 1547 | K88: MEDL | L88: MEDICAL | M88: FALSE | N88: SO | P88: Medline Industries, Inc. | Q88: 16415 Cosmos Street | S88: CA | T88: 92551 | V88: 1 | X88: Medline - SPT Division | Y88: Moreno Valley | Z88: call for dock appointment 951-296-2639 x 4237 or email yduran@medline.com | AA88: PCI-01 | AB88: STRUKMYER, LLC
A89: 46385 | B89: 2 | C89: 0000064916 | D89: 1 | E89: LAREDO | F89: 609 | G89: MEDISTRIP 1/4 IN X 3 IN BULK | H89: 10 | I89: 119 | J89: 1190 | K89: MEDL | L89: MEDICAL | M89: FALSE | N89: SO | P89: Medline Industries, Inc. | Q89: 12001 General Milton Dr | S89: TX | T89: 78045 | V89: 1 | X89: Medline Industries | Y89: Laredo | Z89: This location will be inactive Effective 7/17/17. new location 12001 General Milton Dr. Laredo, TX . If customer request NDA - use Fedex Collect # 326382027 | AA89: PCI-01 | AB89: STRUKMYER, LLC
A90: 46385 | B90: 2 | C90: 0000064914 | D90: 10 | E90: C89 | F90: 5117 | G90: MEDLINE OPTIFOAM THIN 4x4 MSC1544EP | H90: 1 | I90: 94.6 | J90: 94.6 | K90: MEDL | L90: MEDICAL | M90: FALSE | N90: SO | P90: Medline Industries, Inc. | Q90: 251 Hilton Dr | S90: IN | T90: 47130 | V90: 0 | X90: Medline Industries LP | Y90: Jeffersonville | AA90: PCI-01 | AB90: STRUKMYER, LLC
A91: 46385 | B91: 2 | C91: 0000064911 | D91: 10 | E91: B06 | F91: 5116 | G91: MEDLINE OPTIFOAM THIN 2X3 MSC1523EP | H91: 27 | I91: 63.42 | J91: 1712.34 | K91: MEDL | L91: MEDICAL | M91: FALSE | N91: SO | P91: Medline Industries, Inc. | Q91: 1 Medline Drive, Suite 100 | S91: TX | T91: 75172 | V91: 0 | X91: Medline Industries LP | Y91: Wilmer | AA91: PCI-01 | AB91: STRUKMYER, LLC
A92: 46385 | B92: 2 | C92: 0000064910 | D92: 10 | E92: B48 | F92: 5116 | G92: MEDLINE OPTIFOAM THIN 2X3 MSC1523EP | H92: 4 | I92: 63.42 | J92: 253.68 | K92: MEDL | L92: MEDICAL | M92: FALSE | N92: SO | P92: Medline Industries, Inc. | Q92: 36445 Van Born Road STE 200 | S92: MI | T92: 48174 | V92: 0 | X92: Medline Industries LP | Y92: Romulus | AA92: PCI-01 | AB92: STRUKMYER, LLC
A93: 46385 | B93: 2 | C93: 0000064908 | D93: 20 | E93: C02 | F93: 5117 | G93: MEDLINE OPTIFOAM THIN 4x4 MSC1544EP | H93: 3 | I93: 94.6 | J93: 283.8 | K93: MEDL | L93: MEDICAL | M93: FALSE | N93: SO | P93: Medline Industries, Inc. | Q93: 2200 Cornerstone Pkwy, Ste 100 | S93: IL | T93: 60030 | V93: 0 | X93: Medline Industries LP | Y93: Grayslake | AA93: PCI-01 | AB93: STRUKMYER, LLC
A94: 46385 | B94: 2 | C94: 0000064908 | D94: 10 | E94: C02 | F94: 5116 | G94: MEDLINE OPTIFOAM THIN 2X3 MSC1523EP | H94: 38 | I94: 63.42 | J94: 2409.96 | K94: MEDL | L94: MEDICAL | M94: FALSE | N94: SO | P94: Medline Industries, Inc. | Q94: 2200 Cornerstone Pkwy, Ste 100 | S94: IL | T94: 60030 | V94: 0 | X94: Medline Industries LP | Y94: Grayslake | AA94: PCI-01 | AB94: STRUKMYER, LLC
A95: 46385 | B95: 2 | C95: 0000064907 | D95: 20 | E95: C05 | F95: 5117 | G95: MEDLINE OPTIFOAM THIN 4x4 MSC1544EP | H95: 2 | I95: 94.6 | J95: 189.2 | K95: MEDL | L95: MEDICAL | M95: FALSE | N95: SO | P95: Medline Industries, Inc. | Q95: 1062 Old Dixie Hwy | S95: FL | T95: 33823 | V95: 0 | X95: Medline Industries LP | Y95: Auburndale | AA95: PCI-01 | AB95: STRUKMYER, LLC
A96: 46385 | B96: 2 | C96: 0000064906 | D96: 20 | E96: C32 | F96: 5117 | G96: MEDLINE OPTIFOAM THIN 4x4 MSC1544EP | H96: 12 | I96: 94.6 | J96: 1135.2 | K96: MEDL | L96: MEDICAL | M96: FALSE | N96: SO | P96: Medline Industries, Inc. | Q96: 29895 US HWY 90 BUS | S96: TX | T96: 77494 | V96: 0 | X96: Medline Industries LP | Y96: Katy | AA96: PCI-01 | AB96: STRUKMYER, LLC
A97: 46385 | B97: 2 | C97: 0000064905 | D97: 30 | E97: C09 | F97: 5117 | G97: MEDLINE OPTIFOAM THIN 4x4 MSC1544EP | H97: 6 | I97: 94.6 | J97: 567.6 | K97: MEDL | L97: MEDICAL | M97: FALSE | N97: SO | P97: Medline Industries, Inc. | Q97: 1960 W Miro Way | S97: CA | T97: 92376 | V97: 0 | X97: Medline Industries LP | Y97: Rialto | AA97: PCI-01 | AB97: STRUKMYER, LLC
A98: 46385 | B98: 2 | C98: 0000064905 | D98: 20 | E98: C09 | F98: 5116 | G98: MEDLINE OPTIFOAM THIN 2X3 MSC1523EP | H98: 3 | I98: 63.42 | J98: 190.26 | K98: MEDL | L98: MEDICAL | M98: FALSE | N98: SO | P98: Medline Industries, Inc. | Q98: 1960 W Miro Way | S98: CA | T98: 92376 | V98: 0 | X98: Medline Industries LP | Y98: Rialto | AA98: PCI-01 | AB98: STRUKMYER, LLC
A99: 46385 | B99: 2 | C99: 0000064903 | D99: 10 | E99: C46 | F99: 5117 | G99: MEDLINE OPTIFOAM THIN 4x4 MSC1544EP | H99: 2 | I99: 94.6 | J99: 189.2 | K99: MEDL | L99: MEDICAL | M99: FALSE | N99: SO | P99: Medline Industries, Inc. | Q99: 5701 PROMONTORY PKWY | S99: CA | T99: 953779201 | V99: 0 | X99: Medline Industries LP | Y99: TRACY | AA99: PCI-01 | AB99: STRUKMYER, LLC
A100: 46385 | B100: 2 | C100: 0000064902 | D100: 5 | E100: BILL | F100: 3853 | G100: MEDISTRIP 1 IN X 4 IN BULK NON-STERILE | H100: 6 | I100: 196.5 | J100: 1179 | K100: MEDL SLOV | L100: MEDICAL | M100: FALSE | N100: SO | P100: Medline Assembly Slovakia S.R.O | Q100: Malobielicka 284/8 | S100: .. | T100: 95804 | V100: 0 | X100: Medline Assembly Slovakia S.R.O | Y100: Partizanske | Z100: DHL EXPRESS Worldwide 954238829 | AA100: PCI-01 | AB100: STRUKMYER, LLC
A101: 46385 | B101: 2 | C101: 0000064902 | D101: 4 | E101: BILL | F101: 3852 | G101: MEDISTRIP 1/4 IN X 3 IN BULK NON-STERILE | H101: 4 | I101: 119 | J101: 476 | K101: MEDL SLOV | L101: MEDICAL | M101: FALSE | N101: SO | P101: Medline Assembly Slovakia S.R.O | Q101: Malobielicka 284/8 | S101: .. | T101: 95804 | V101: 0 | X101: Medline Assembly Slovakia S.R.O | Y101: Partizanske | Z101: DHL EXPRESS Worldwide 954238829 | AA101: PCI-01 | AB101: STRUKMYER, LLC
...

Sheet Sales Map per month
C1: TOTAL SALES
C2: =D23 -> 9065728.6 | H2: N Codes
A3: ItemSalesClassCode | B3: (All) | G3: ItemCode | H3: (Multiple Items)
A4: ItemCode | B4: (All) | G4: ItemSalesClassCode | H4: (All)
A6: Sum of ExtendedLineAmount | G6: N Code Sales
A7: Years (ScheduledShipDate) | B7: Months (ScheduledShipDate) | C7: ScheduledShipDate | D7: Total | G7: ScheduledShipDate | H7: Total
A8: 1900 | B8: Jan | D8: 465850.23 | G8: 2 | H8: 17822
A9: 1900 Total | D9: 465850.23 | G9: 46296 | H9: 13339.02
A10: 2026 | B10: Feb | D10: 1189209.4 | G10: 46080 | H10: 4755.79
B11: Mar | D11: 2106445.2 | G11: 46113 | H11: 54691
B12: Apr | D12: 1598583.1 | G12: 46142 | H12: 250
B13: May | D13: 1038408.3 | G13: 46094 | H13: 6700
B14: Jun | D14: 230497 | G14: Grand Total | H14: 97557.81
B15: Jul | D15: 376891
B16: Aug | D16: 253135.5
B17: Sep | D17: 129838
B18: Oct | D18: 225388.52
B19: Nov | D19: 300112.02
B20: Dec | D20: 1092927.4
A21: 2026 Total | D21: 8541435.4
A22: 2027 | D22: 58443
A23: Grand Total | D23: 9065728.6

Sheet Sales by Product
A1: ItemSalesClassCode | B1: (All) | C1: =GETPIVOTDATA("Sum of ExtendedLineAmount",$A$6) -> 1189209.4
A2: ScheduledShipDate | B2: (All)
A3: Months (ScheduledShipDate) | B3: Feb | C3: =C8 -> 272615.04 | D3: Items at risk
A4: Years (ScheduledShipDate) | B4: 2026
C6: Data
A7: ItemCode | B7: ItemDescription | C7: Sum of ExtendedLineAmount | D7: Sum of OrderQuantity
A8: 7153 | B8: URGO - VASHE 250 ml Flip Top 00313 | C8: 272615.04 | D8: 145008
A9: 7156 | B9: URGO - VASHE 475 ml Instill 00317 | C9: 154960.32 | D9: 30504
A10: 1674 | B10: BI OVERLAY #2 - ITALY | C10: 118500 | D10: 500000
A11: 7487 | B11: CARDINAL HEALTH TELFA ADHESIVE DRESSING 2"x3" 6017 | C11: 80928 | D11: 300
A12: 7154 | B12: URGO - VASHE 475 ml Flip Top 00314 | C12: 77700 | D12: 30000
A13: 7235 | B13: HARMAC PRTD DRAPE ASSEMBLY P3113231 REV.A (ROW) | C13: 62532 | D13: 120000
A14: 3958 | B14: Harmac Filter Disc P3113306 Rev E | C14: 54675 | D14: 202500
A15: 5342 | B15: ISI LARGE ALUMI-HAND 760 | C15: 53130 | D15: 6900
A16: 6011 | B16: MEDLINE CURAD MEDISTRIP 1/4 X 4 IN STERILE NON250414 | C16: 43227.6 | D16: 340
A17: 5045 | B17: FREUDENBERG 30cm X 47cm Nonwoven Sheets 122P0463 | C17: 40750 | D17: 25000
A18: 6370 | B18: TB DRY MOUTH TINGLING RINSE 16 OZ BULK 40101908 | C18: 31086.28 | D18: 17475
A19: 6013 | B19: MEDLINE CURAD MEDI STRIP 1 X 5 NON250501 | C19: 26199 | D19: 213
... A27: 5660 | B27: MPM Antiseptic Wound & Skin Cleanser 8 fl.oz. MP00032 | C27: 8758.2 | D27: 3981
A28: F-22007 | B28: ADVANCED 2" × 200' ROLL SEMI-OCCLUSIVE | C28: 8599.2 | D28: 40
A29: 5520 | B29: D* Tetrapotassium Pyrophosphate CAS#7320-34-5 1614086 | C29: 8331.11 | D29: 7446
A30: 6328 | B30: CARBOX WAX SENTRY POLYETHYLENE GLYCOL 600 NF CAS#25322-68-3 | C30: 6977.1 | D30: 716188
A31: F-22004 | B31: 5 SITE SEMI-OCCLUSIVE STRIP | C31: 6560 | D31: 16000
A32: 6323 | B32: MINERALIZ GU/Zn CAS# 4468-02-4 KOSHER | C32: 4961.39 | D32: 66959
A33: F-22008 | B33: ADVANCED 2" × 200' ROLL OCCLUSIVE | C33: 4134.4 | D33: 40
A34: 5521 | B34: D* Tetrasodium Pyrophosphate CAS#7722-88-5 KOSHER | C34: 3825.84 | D34: 13337
A35: N-4008 | B35: Expedite Fee for 15ml Bottles | C35: 2556.79 | D35: 1
A36: 5515 | B36: D* Dentsil DS 60 HYDRATED SILICA - CAS#112926-00-8 KOSHER | C36: 2414.7 | D36: 467602
A37: 5590 | B37: BAG, AP2390.11 Arena "Air-Evac" Vertex, 3Ply Liquid Liner Bag | C37: 1863.13 | D37: 14
A38: 5703 | B38: D* Glycerin 99.7% CAS# 56-81-5 KOSHER | C38: 1661.22 | D38: 2013600
A39: 5639 | B39: D* Sorbitol Crystalline Powder NF, CAS# 50-70-4 KOSHER | C39: 1215.81 | D39: 214127.05
A40: N-4009 | B40: Artwork Prep/Plate Fee(s) | C40: 1200 | D40: 1
A41: 5525 | B41: D* AmmoniumGlycyrrhizate Magnasweet 110-2X CAS#53956-04-0 KOSHER | C41: 1033.12 | D41: 81438
A42: N-4001 | B42: Art & Print Plate Charges | C42: 549 | D42: 1
B43: Set Up Charges | C43: 450 | D43: 1
A44: 5518 | B44: D* Mint Flavor WONF OS, Natural 113.19228 CAS# 68917-18-0 KOSHER | C44: 963.58 | D44: 16562
A45: 5713 | B45: Polysorbate 20 CAS# 9005-64-5 | C45: 919.01 | D45: 112638
A46: 6330 | B46: MENTHOL CAS#2216-51-5 KOSHER | C46: 867.7 | D46: 9524
A47: 7224 | B47: GREEN TEA PHYTOBASIC IN PG (3345L) KOSHER | C47: 853.65 | D47: 15375
A48: 5517 | B48: D* Cooling Type Flavor Natural 113.90468 KOSHER | C48: 790.04 | D48: 48563.98
A49: 5528 | B49: D* Mentha Viridis (Spearmint) Leaf Oil CAS# 8008-79-5 KOSHER | C49: 367.09 | D49: 890.55
A50: 7525 | B50: D* BLANOSE™ CMC 7MF CAS#9004-32-4 KOSHER | C50: 278.53 | D50: 37639
A51: 6327 | B51: ALOE VERA LEAF GEL DECOLORIZED 10X # AG014 CAS#94349-62-9 | C51: 277.54 | D51: 21783.07
A52: 5522 | B52: D* Aloe Barbadensis Leaf JuiceCAS#85507-69-3 KOSHER | C52: 257.89 | D52: 45978.01
A53: 5527 | B53: D* Mentha Arvensis (Cornmint) Leaf Oil CAS# 68917-18-0 KOSHER | C53: 135.48 | D53: 671.63
A54: 5530 | B54: D* Sodium Fluoride CAS#7681-49-4 KOSHER | C54: 124.13 | D54: 22656
A55: 5686 | B55: D* Citric Acid CAS# 77-92-9 | C55: 85.64 | D55: 25563.08
... A57: 7573 | B57: AUSTRALIAN TEA TREE OIL #50-6270-01 | C57: 66.99 | D57: 571.53
A58: Grand Total | C58: 1189209.4 | D58: 5101309.4

Sheet Sales by Customer
A1: ItemCode | B1: (All) | E1: ScheduledShipDate | F1: (All)
G2: =GETPIVOTDATA("ExtendedLineAmount",$E$2) -> 9065728.6
A3: Department | B3: Total | H3: Data
A4: URGO Medical | B4: 1973775.4 | E4: CustomerName | F4: ItemCode | G4: ItemDescription | H4: Site Total Sales Revenue | I4: Sum of Profit | K4: UOM | L4: MOQ on Cost sheet | M4: Lots/yr | N4: Comment(MOQ on sales sheet) | O4: Actual MOQ required | P4: 44927 | Q4: 44958 | R4: 44986 | S4: 45017 | T4: 45047 | U4: 45078 | V4: 45108 | W4: 45139 | X4: 45170 | Y4: 45200 | Z4: 45231 | AA4: 45261
A5: Patient Recovery | B5: 1848764.4 | E5: MPM Medical, Inc. | F5: 5671 | G5: MPM OraMagic Rx 12oz MP00213 | H5: 6408 | I5: 2833.7004 | K5: EA | L5: 5000 | M5: =J5/L5 -> 0
A6: Medline Industries, Inc. | B6: 610273.92 | F6: 5674 | G6: MPM OraMagic Plus 8oz MP00224 | H6: 4900 | I6: 1261.37 | K6: EA | L6: 75000 | M6: =J6/L6 -> 0
A7: Harmac Medical Products | B7: 568917 | F7: 5668 | G7: MPM Regenecare HA Gel 3oz. MP00107 | H7: 23400 | I7: 7417.69 | K7: EA | L7: 7000 | M7: =J7/L7 -> 0
A8: Instrument Specialists Inc | B8: 471827 | F8: 5660 | H8: 41758.2 | I8: 15439.677 | K8: EA | L8: 7500 | M8: =J8/L8 -> 0
A9: PerioSciences | B9: 454986.79 | F9: 7898 | G9: MPM DryMax/DrySAP Extra Super Absorbent Drsg, Sterile, 8X8; | H9: 9900 | I9: 9900 | K9: EA | L9: 24000 | M9: =J9/L9 -> 0
A10: MPM Medical, Inc. | B10: 381833.3 | F10: 5662 | G10: MPM Regenecare Wound Gel 0.5 oz, MP00101 | H10: 4900 | I10: 1159.305 | K10: EA | L10: 9600 | M10: =J10/L10 -> 0
A11: OSARTIS GmbH | B11: 327097 | F11: 5440 | G11: MPM Regenecare HA Gel 0.5oz. MP00112 | H11: 7700 | I11: 4408.87 | K11: EA | L11: 50000 | M11: =J11/L11 -> 0
A12: EMED Technologies Corp | B12: 244132 | F12: 5666 | G12: MPM RadiaPlex Rx Gel 6oz. MP00106 | H12: 9364.4 | I12: 3877.9602 | K12: EA | L12: 30000 | M12: =J12/L12 -> 0
A13: Harmac Medical Products, Inc | B13: 233946 | F13: 5859 | G13: MPM MP00990 DRY VEIL CONTACT LAYER 36"X36" (48ea/CS) | H13: 20000 | I13: 8474.79 | K13: EA | L13: 11250 | M13: =J13/L13 -> 0
A14: The Pause Life Supplements, LLC | B14: 213500 | F14: 3424 | G14: MPM Cool Magic Gel Sheet 6.0"x8.0" OL MP00208 | H14: 126000 | I14: 28533.94 | K14: EA | L14: 11250 | M14: =J14/L14 -> 0
A15: Lavipharm SA | B15: 213049 | F15: 5670 | G15: MPM Regenecare HA Spray 4 fl.oz. MP00117 | H15: 17912.7 | I15: 6002.2855 | K15: EA | L15: 14000 | M15: =J15/L15 -> 0
A16: KCII-IRE-IRM | B16: 168138 | F16: 3752 | G16: MPM 4 x 5 THIN FILM DRESSING STERILE MP00470 | H16: 59660 | I16: 13688.842 | K16: EA | L16: 7500 | M16: =J16/L16 -> 0
A17: Freudenberg Performance Materials LP | B17: 163000 | F17: N-4009 | G17: Artwork Prep/Plate Fee(s) | H17: 250 | I17: #N/A | K17: EA | L17: 6250 | M17: =J17/L17 -> 0
A18: Iotech International | B18: 159900 | F18: 3423 | G18: MPM Cool Magic Gel Sheet 3.75"x3.75" OL MP00206 | H18: 49680 | I18: 13616.376 | K18: EA | L18: 22500 | M18: =J18/L18 -> 0
A19: Argentum Medical, LLC | B19: 154517.22 | E19: Harmac Medical Products, Inc | F19: 3958 | G19: Harmac Filter Disc P3113306 Rev E | H19: 58320 | I19: 30460.968 | K19: EA | L19: 76000 | M19: =J19/L19 -> 0 | N19: 76000 | O19: 75000 | P19: 45000 | Q19: 60000
A20: Orora Business Service Center | B20: 105010.99 | F20: 7236 | G20: HARMAC PRTD DRAPE ASSEMBLY W/LABEL - P3113251 Rev C. | H20: 127728 | I20: 70513.68 | K20: CS | L20: 1307 | M20: =J20/L20 -> 0 | N20: 6330 | O20: 6250 | Q20: 6250 | R20: 3750
A21: McKesson Medical Surgical | B21: 104484 | G21: HARMAC PRTD DRAPE ASSEMBLY W/LABEL - P3113251 Rev B. | H21: 47898 | I21: 26442.63 | K21: EA | L21: 60000 | M21: =J21/L21 -> 0 | O21: 60000 | Q21: 60000
A22: O&M Halyard, Inc | B22: 87300 | E22: Iotech International | F22: 7558 | G22: ioTech ioRinse AC 1 liter | H22: 25500 | I22: 19670.865 | K22: CS | N22: 6330 | Q22: 200
A23: Eurofins CRL Cosmetics, Inc | B23: 70050 | F23: 7559 | G23: ioTech ioRinse AC 16oz | H23: 23550 | I23: 17667.93 | K23: EA | L23: 86400 | M23: =J23/L23 -> 0 | N23: 28800 | O23: 90000 | Q23: 30000 | S23: 30000
A24: Centurion Medical Products Corp | B24: 58663.5 | F24: 7560 | G24: ioTech ioRinse Ultra 1 liter | H24: 38250 | I24: 30483.112 | K24: EA | L24: 75000 | M24: =J24/L24 -> 0
A25: Mingguang Glory Sun Precision Technology Co., Ltd. | B25: 46800 | F25: 7561 | G25: ioTech ioRinse Ultra 16 oz | H25: 23550 | I25: 18308.985 | K25: EA | L25: 11874 | M25: =J25/L25 -> 0
A26: Implus LLC | B26: 46800 | F26: 7905 | G26: Iotech MR-HA- US 1L | H26: 25500 | I26: 3520.155 | K26: EA | L26: 10000 | M26: =J26/L26 -> 0 | Q26: 10000
A27: Implus Canada | B27: 45240 | F27: 7906 | G27: Iotech STR-HA 16oz | H27: 23550 | I27: 8342.355 | K27: EA | L27: 864 | M27: =J27/L27 -> 0
A28: Remedium Healthcare Products, LLC | B28: 43800 | E28: Patient Recovery | F28: 7486 | G28: CARDINAL HEALTH TELFA ADHESIVE DRESSING 3"x4" 7643 | H28: 466689.6 | I28: 244230.07 | K28: EA | L28: 1212 | M28: =J28/L28 -> 0
A29: Clyra Medical Technologies, Inc. | B29: 38520 | F29: 7482 | G29: CARDINAL HEALTH TELFA MINI ISLAND DRESSING 2"x3.75" 7539LF | H29: 311866.8 | I29: 39209.463 | K29: EA | L29: 852 | M29: =J29/L29 -> 0
A30: KOB Medical Devices (Deutschland)GmbH | B30: 38500 | F30: 7487 | G30: CARDINAL HEALTH TELFA ADHESIVE DRESSING 2"x3" 6017 | H30: 323712 | I30: 166643.73 | K30: EA | N30: 25000 | Q30: 9000
A31: Medline Assembly Slovakia S.R.O | B31: 37223 | F31: 7488 | G31: CARDINAL HEALTH TELFA NON-ADHERENT DRESSING 3"x4" 2132 | H31: 552096 | I31: 64155.12 | K31: EA | L31: 37500 | M31: =J31/L31 -> 0 | O31: 37500 | R31: 45000
A32: Medline Assembly France SAS | B32: 31554 | F32: 7489 | G32: CARDINAL HEALTH TELFA NON-ADHERENT DRESSING 2"x3" 1961 | H32: 194400 | I32: 42425.865 | K32: EA | L32: 76000 | M32: =J32/L32 -> 0 | N32: 76000 | O32: 75000 | R32: 90000
A33: NAWA, Inc | B33: 30000 | E33: URGO Medical | F33: N-4001 | H33: 58053 | I33: #N/A | K33: EA | L33: 9270 | M33: =J33/L33 -> 0
A34: Turn Therapeutics | B34: 27190 | F34: 7153 | G34: URGO - VASHE 250 ml Flip Top 00313 | H34: 876095.04 | I34: 354378.58 | K34: EA | L34: 6624 | M34: =J34/L34 -> 0
A35: The Bloomi Inc | B35: 21250 | F35: 7154 | G35: URGO - VASHE 475 ml Flip Top 00314 | H35: 77700 | I35: 36058.83 | K35: EA | L35: 4800 | M35: =J35/L35 -> 0
A36: Nexgel | B36: 13264.83 | F36: 7159 | G36: URGO - VASHE 250 ml OTC Flip Top 00405 | H36: 9757.8 | I36: 4113.4181 | K36: EA
A37: Advanced Science Laboratories Inc | B37: 12733.6 | F37: 7152 | G37: URGO - VASHE 118 ml Flip Top 00312 | H37: 504422.64 | I37: 205928.04 | K37: EA | L37: 4128 | M37: =J37/L37 -> 0
A38: DeRoyal Accounts Payable Dept | B38: 11088 | F38: 7155 | G38: URGO - VASHE 250 ml Instill 00316 | H38: 43382.64 | I38: 29143.008 | K38: EA | L38: 60000 | M38: =J38/L38 -> 0 | R38: 60000
A39: Monaderm | B39: 6560 | F39: 7156 | G39: URGO - VASHE 475 ml Instill 00317 | H39: 281940 | I39: 178209.61 | K39: CS | L39: 7500 | M39: =J39/L39 -> 0 | N39: 8000 | O39: 7500 | R39: 6250 | U39: 3750
A40: DermaClip US, LLC | B40: 2039.73 | F40: N-4009 | G40: Artwork Prep/Plate Fee(s) | H40: 1200 | I40: #N/A | K40: EA | L40: 45000 | M40: =J40/L40 -> 0 | O40: 60000 | T40: 50000
A41: Grand Total | B41: 9065728.6 | F41: 7158 | G41: URGO - VASHE 1 L Flip Top 00322 | H41: 52810.56 | I41: 27105.9 | K41: GM | L41: 750000 | M41: =J41/L41 -> 0
F42: 7157 | G42: URGO - VASHE 1 L Instill 00323 | H42: 68413.68 | I42: 37737.166 | K42: EA | L42: 2076 | M42: =J42/L42 -> 0
E43: Harmac Medical Products | F43: N-4001 | H43: 6700 | I43: #N/A | K43: EA | L43: 71631 | M43: =J43/L43 -> 0
F44: 3958 | G44: Harmac Filter Disc P3113306 Rev E | H44: 164025 | I44: 85671.473 | K44: EA | L44: 35000 | M44: =J44/L44 -> 0 | N44: 35000
F45: 7235 | G45: HARMAC PRTD DRAPE ASSEMBLY P3113231 REV.C (ROW) | H45: 250128 | I45: 153319.68
G46: HARMAC PRTD DRAPE ASSEMBLY P3113231 REV.A (ROW) | H46: 125064 | I46: 76659.84
F47: 7993 | G47: 200 RC Filter | H47: 16750 | I47: 16750
F48: 7992 | G48: Port Drape | H48: 6250 | I48: 5600
E49: Medline Assembly Slovakia S.R.O | F49: 3850 | G49: MEDISTRIP 1/2 IN X 4 IN BULK NONSTERILE 3/CD | H49: 27202 | I49: 10566.111
F50: 3853 | G50: MEDISTRIP 1 IN X 4 IN BULK NON-STERILE | H50: 5109 | I50: 1625.2474
F51: 3849 | G51: MEDISTRIP 1/4 IN X 1.5 IN BULK NON-STERILE | H51: 1815 | I51: 44.0935
F52: 3851 | G52: MEDISTRIP 1/4 IN X 4 IN BULK NON-STERILE 5/CD | H52: 2145 | I52: -63.813728
F53: 3852 | G53: MEDISTRIP 1/4 IN X 3 IN BULK NON-STERILE | H53: 952 | I53: 405.068
E54: Medline Assembly France SAS | F54: 3850 | G54: MEDISTRIP 1/2 IN X 4 IN BULK NONSTERILE 3/CD | H54: 27202 | I54: 10566.111
F55: 3853 | G55: MEDISTRIP 1 IN X 4 IN BULK NON-STERILE | H55: 786 | I55: 250.03806
F56: 3849 | G56: MEDISTRIP 1/4 IN X 1.5 IN BULK NON-STERILE | H56: 165 | I56: 4.0085
F57: 3851 | G57: MEDISTRIP 1/4 IN X 4 IN BULK NON-STERILE 5/CD | H57: 2925 | I57: -87.01872
F58: 3852 | G58: MEDISTRIP 1/4 IN X 3 IN BULK NON-STERILE | H58: 476 | I58: 202.534
E59: Medline Industries, Inc. | F59: 609 | G59: MEDISTRIP 1/4 IN X 3 IN BULK | H59: 20825 | I59: 8688.7273
F60: 6008 | G60: MEDLINE CURAD MEDISTRIP 1/4 X 1.5 IN, STERILE NON250114 | H60: 11366.52 | I60: 5724.264
F61: 6011 | G61: MEDLINE CURAD MEDISTRIP 1/4 X 4 IN STERILE NON250414 | H61: 52890.24 | I61: 24128.362
F62: 6013 | G62: MEDLINE CURAD MEDI STRIP 1 X 5 NON250501 | H62: 61992 | I62: 30267.603
F63: 6039 | G63: MEDLINE SURESITE 4 X 4.75 MSC2304 | H63: 44410.6 | I63: 21305.308
F64: 610 | G64: MEDISTRIP 1 IN X 4 IN BULK | H64: 6877.5 | I64: 2585.0548
F65: 5117 | G65: MEDLINE OPTIFOAM THIN 4x4 MSC1544EP | H65: 17028 | I65: 3303.3355
F66: 3132 | G66: MEDLINE CURAD NASAL TUBE HOLDER CURNASTUB50 | H66: 13585 | I66: 3295.0492
F67: 5116 | G67: MEDLINE OPTIFOAM THIN 2X3 MSC1523EP | H67: 20865.18 | I67: 7255.4064
F68: 5979 | G68: MEDLINE SUREFILM 4" X 11 YARDS MSC2404 | H68: 32121.6 | I68: 15156.725
F69: 6010 | G69: MEDLINE CURAD MEDISTRIP 1/2 X 4 IN STERILE NON250412 | H69: 114342 | I69: 37213.088
F70: 6012 | G70: MEDLINE CURAD MEDISTRIP 1/4 X 3 IN STERILE NON250314 | H70: 26440.92 | I70: 18846.976
F71: 6009 | G71: MEDLINE CURAD MEDISTRIP 1/8 X 3 IN STERILE NON250318 | H71: 444.08 | I71: 20.396551
... F75: 5975 | G75: MEDLINE SUREFILM 2" X 11 YARDS MSC2402 | H75: 319.56 | I75: 173.61257
E76: EMED Technologies Corp | F76: 4978 | G76: EMED SOFT-SITE TEGADERM DRESSING 112X51MM MS-0010201 | H76: 114532 | I76: 30995.84
F77: 1917 | G77: EMED 2.375 X 2.75 PRTD DRESS | H77: 129600 | I77: 55678.32
E78: Centurion Medical Products Corp | F78: 609 | G78: MEDISTRIP 1/4 IN X 3 IN BULK | H78: 2499 | I78: 1042.6473
F79: 610 | G79: MEDISTRIP 1 IN X 4 IN BULK | H79: 14344.5 | I79: 5391.6858
F80: 2977 | G80: MEDLINE DRSG SURESITE 4.75 X 4 FRAME/LABL (MSC52281) | H80: 36720 | I80: 9242.3401
F81: 6010 | G81: MEDLINE CURAD MEDISTRIP 1/2 X 4 IN STERILE NON250412 | H81: 5100 | I81: 1659.8166
E82: Freudenberg Performance Materials LP | F82: 5045 | G82: FREUDENBERG 30cm X 47cm Nonwoven Sheets 122P0463 | H82: 163000 | I82: 59640
E83: Orora Business Service Center | F83: 6370 | G83: TB DRY MOUTH TINGLING RINSE 16 OZ BULK 40101908 | H83: 66664.28 | I83: 24570.221
F84: 5639 | G84: D* Sorbitol Crystalline Powder NF, CAS# 50-70-4 KOSHER | H84: 1215.81 | I84: #N/A
F85: 5515 | G85: D* Dentsil DS 60 HYDRATED SILICA - CAS#112926-00-8 KOSHER | H85: 2414.7 | I85: #N/A
F86: 5703 | G86: D* Glycerin 99.7% CAS# 56-81-5 KOSHER | H86: 1661.22 | I86: -310.0944
F87: 5517 | G87: D* Cooling Type Flavor Natural 113.90468 KOSHER | H87: 790.04 | I87: #N/A
F88: 5518 | G88: D* Mint Flavor WONF OS, Natural 113.19228 CAS# 68917-18-0 KOSHER | H88: 963.58 | I88: #N/A
F89: 7525 | G89: D* BLANOSE™ CMC 7MF CAS#9004-32-4 KOSHER | H89: 278.53 | I89: #N/A
F90: 5520 | G90: D* Tetrapotassium Pyrophosphate CAS#7320-34-5 1614086 | H90: 8331.11 | I90: #N/A
F91: 5521 | G91: D* Tetrasodium Pyrophosphate CAS#7722-88-5 KOSHER | H91: 3825.84 | I91: #N/A
F92: 5522 | G92: D* Aloe Barbadensis Leaf JuiceCAS#85507-69-3 KOSHER | H92: 257.89 | I92: #N/A
F93: 5686 | G93: D* Citric Acid CAS# 77-92-9 | H93: 85.64 | I93: #N/A
F94: 5525 | G94: D* AmmoniumGlycyrrhizate Magnasweet 110-2X CAS#53956-04-0 KOSHER | H94: 1033.12 | I94: #N/A
F95: 6901 | G95: D* ASCORBIC ACID CAS# 50-81-7 KOSHER | H95: 76.02 | I95: #N/A
F96: 5527 | G96: D* Mentha Arvensis (Cornmint) Leaf Oil CAS# 68917-18-0 KOSHER | H96: 135.48 | I96: #N/A
F97: 5528 | G97: D* Mentha Viridis (Spearmint) Leaf Oil CAS# 8008-79-5 KOSHER | H97: 367.09 | I97: #N/A
F98: 5530 | G98: D* Sodium Fluoride CAS#7681-49-4 KOSHER | H98: 124.13 | I98: #N/A
... F100: 6323 | G100: MINERALIZ GU/Zn CAS# 4468-02-4 KOSHER | H100: 4961.39 | I100: #N/A
F101: 7224 | G101: GREEN TEA PHYTOBASIC IN PG (3345L) KOSHER | H101: 853.65 | I101: -28.889625
F102: 6327 | G102: ALOE VERA LEAF GEL DECOLORIZED 10X # AG014 CAS#94349-62-9 | H102: 277.54 | I102: #N/A
F103: 6328 | G103: CARBOX WAX SENTRY POLYETHYLENE GLYCOL 600 NF CAS#25322-68-3 | H103: 6977.1 | I103: #N/A
F104: 6330 | G104: MENTHOL CAS#2216-51-5 KOSHER | H104: 867.7 | I104: #N/A
...

Sheet Detail1
A1: Details for Total - ItemSalesClassCode: Default , ItemCode: N-4001 (+)
A3: ScheduledShipDate | B3: PromisedShipDate | C3: SONumber | D3: LineNumber | E3: ShipToCode | F3: ItemCode | G3: ItemDescription | H3: OrderQuantity | I3: UnitPrice | J3: ExtendedLineAmount | K3: CustomerCode | L3: ItemSalesClassCode | M3: DropShip | N3: SOTypeCode | O3: FinalDestination | P3: CustomerName | Q3: ShipToAddress1 | R3: ShipToAddress2 | S3: ShipToStateCode | T3: ShipToZip | U3: ParentDocumentNumber | V3: Weight | W3: OrderMessage | X3: ShipToName | Y3: ShipToCity | Z3: ShippingInstructions | AA3: WarehouseCode | AB3: WarehouseName
A4: 46167 | B4: 46167 | C4: 0000064973 | D4: 2 | E4: Osartis | F4: 7984 | G4: Osteoremedies Branded Gel 0.25 oz, 40 assembly Turnkey | H4: 18500 | I4: 2.57 | J4: 47545 | K4: Next Sci | L4: Default | M4: FALSE | N4: SO | P4: OSARTIS GmbH | Q4: OSARTIS GMBH via GlobalMed Logistix | R4: 1890 Beaver Ridge Circle | S4: GA | T4: 30071 | V4: 0 | X4: Attn. Kyle Holloway/OsteoRemedies | Y4: Norcross | AA4: PCI-01
A5: 46167 | B5: 46167 | C5: 0000064973 | D5: 1 | E5: Osartis | F5: 7983 | G5: Osteoremedies Branded 1.0oz BlastX 12 assembly Turnkey | H5: 43008 | I5: 6.5 | J5: 279552 | K5: Next Sci | L5: Default | M5: FALSE | N5: SO | P5: OSARTIS GmbH | Q5: OSARTIS GMBH via GlobalMed Logistix | R5: 1890 Beaver Ridge Circle | S5: GA | T5: 30071 | V5: 0 | X5: Attn. Kyle Holloway/OsteoRemedies | Y5: Norcross | AA5: PCI-01
A6: 46080 | B6: 46080 | C6: 0000065009 | D6: 2 | E6: LAND | F6: 7224 | G6: GREEN TEA PHYTOBASIC IN PG (3345L) KOSHER | H6: 15375 | I6: 0.055522 | J6: 853.65 | K6: ORORA | L6: Default | M6: FALSE | N6: SO | P6: Orora Business Service Center | Q6: 13397 Marlay Ave Ste A | S6: CA | T6: 92337-6946 | V6: 0 | X6: Landsberg-Fullfillment Solutions | Y6: Fontana | Z6: Need special certificate COA before shipped | AA6: PCI-01
A7: 2 | B7: 2 | C7: 0000064986 | D7: 1 | F7: 7991 | G7: Bloomi Delight 3oz | H7: 5000 | I7: 3.45 | J7: 17250 | K7: Bloomi | L7: Default | M7: FALSE | N7: SO | P7: The Bloomi Inc | Q7: 74 Royal Ridge Ct | S7: CA | T7: 94507 | V7: 0 | X7: The Bloomi Inc | Y7: Alamo | Z7: Bloomi to arrange freight | AA7: PCI-01

Sheet Sales by department
A1: ItemCode | B1: (All) | L1: ScheduledShipDate | M1: (All)
N2: =GETPIVOTDATA("ExtendedLineAmount",$L$2) -> 9065728.6
A3: Department | B3: Total | N3: Data
A4: Filling OP | B4: 3051959.9 | L4: ItemCode | M4: ItemDescription | N4: Site Total Sales Revenue | O4: Sum of Profit
A5: MEDICAL | B5: 5117674 | L5: 7153 | M5: URGO - VASHE 250 ml Flip Top 00313 | N5: 876095.04 | O5: 354378.58
A6: Drape&Mask | B6: 550818 | L6: 7488 | M6: CARDINAL HEALTH TELFA NON-ADHERENT DRESSING 3"x4" 2132 | N6: 552096 | O6: 64155.12
A7: Default | B7: 345200.65 | L7: 7152 | M7: URGO - VASHE 118 ml Flip Top 00312 | N7: 504422.64 | O7: 205928.04
A8: CONSUMER | B8: 76.02 | L8: 7486 | M8: CARDINAL HEALTH TELFA ADHESIVE DRESSING 3"x4" 7643 | N8: 466689.6 | O8: 244230.07
A9: Grand Total | B9: 9065728.6 | L9: 7235 | M9: HARMAC PRTD DRAPE ASSEMBLY P3113231 REV.A (ROW) | N9: 125064 | O9: 76659.84
M10: HARMAC PRTD DRAPE ASSEMBLY P3113231 REV.C (ROW) | N10: 250128 | O10: 153319.68
L11: 7487 | M11: CARDINAL HEALTH TELFA ADHESIVE DRESSING 2"x3" 6017 | N11: 323712 | O11: 166643.73
L12: 7482 | M12: CARDINAL HEALTH TELFA MINI ISLAND DRESSING 2"x3.75" 7539LF | N12: 311866.8 | O12: 39209.463
L13: 7751 | M13: PERIOSCIENCES AO PROVANTAGE GEL 30 mL | N13: 290500 | O13: 114938.25
L14: 7156 | M14: URGO - VASHE 475 ml Instill 00317 | N14: 281940 | O14: 178209.61
L15: 7983 | M15: Osteoremedies Branded 1.0oz BlastX 12 assembly Turnkey | N15: 279552 | O15: 238151.42
L16: 5341 | M16: ISI EXTRA LARGE ALUMI-HAND 761 | N16: 243368 | O16: 100473.45
L17: 5342 | M17: ISI LARGE ALUMI-HAND 760 | N17: 228459 | O17: 85326.394
L18: 3958 | M18: Harmac Filter Disc P3113306 Rev E | N18: 222345 | O18: 116132.44
L19: 7489 | M19: CARDINAL HEALTH TELFA NON-ADHERENT DRESSING 2"x3" 1961 | N19: 194400 | O19: 42425.865
L20: 7236 | M20: HARMAC PRTD DRAPE ASSEMBLY W/LABEL - P3113251 Rev B. | N20: 47898 | O20: 26442.63
M21: HARMAC PRTD DRAPE ASSEMBLY W/LABEL - P3113251 Rev C. | N21: 127728 | O21: 70513.68
L22: 4357 | M22: CURAD MEDIPLAST WART REMOVER CUR01496 | N22: 172836.72 | O22: 68052.95
L23: 5045 | M23: FREUDENBERG 30cm X 47cm Nonwoven Sheets 122P0463 | N23: 163000 | O23: 59640
L24: 7941 | M24: Pause life vulva moisturizer 50mL with Xylitol | N24: 138250 | O24: 65448.45
L25: 1917 | M25: EMED 2.375 X 2.75 PRTD DRESS | N25: 129600 | O25: 55678.32
L26: 3424 | M26: MPM Cool Magic Gel Sheet 6.0"x8.0" OL MP00208 | N26: 126000 | O26: 28533.94
L27: 6010 | M27: MEDLINE CURAD MEDISTRIP 1/2 X 4 IN STERILE NON250412 | N27: 119442 | O27: 38872.905
L28: 1674 | M28: BI OVERLAY #2 - ITALY | N28: 118500 | O28: 11165
L29: 4978 | M29: EMED SOFT-SITE TEGADERM DRESSING 112X51MM MS-0010201 | N29: 114532 | O29: 30995.84
L30: 4152 | M30: McKESSON 61-82044 DRESSING, HYDROGEL SHEET STR LF 4X4 | N30: 104484 | O30: 18490.645
L31: 7738 | M31: PERIOSCIENCES AO PROVANTAGE GEL 15ml | N31: 103200 | O31: 57075.48
L32: 4557 | M32: PREVENA PEEL AND PLACE TEGADERM SHORT (13Cm) # 416129 Rev E | N32: 99760 | O32: 39614
L33: 1673 | M33: BI OVERLAY #1 - ITALY | N33: 94000 | O33: 22146
L34: N-4001 | M34: Set Up Charges | N34: 450 | O34: #N/A
M35: Art & Print Plate Charges | N35: 549 | O35: #N/A
M36: Urgo Rework Item 603073 Lot # 50921 | N36: 1575 | O36: #N/A
M37: 1 of 3 Bulk Validations | N37: 1910 | O37: #N/A
M38: Urgo Rework Item 603073 Lot # 47954 | N38: 1932 | O38: #N/A
M39: 1,000 L Obelix Bulk Wound Wash Solution | N39: 2912 | O39: #N/A
M40: Cleaning validation for Delight production | N40: 3000 | O40: #N/A
M41: Large Filter Discs Samples | N41: 6700 | O41: #N/A
M42: Cleaning Validation | N42: 10000 | O42: #N/A
M43: Excess Material Charges DM-2002 & DM-4009 | N43: 13339.02 | O43: #N/A
M44: Urgo Rework Item 603070 Lot # 49874 | N44: 16212 | O44: #N/A
M45: Urgo Rework Item 603071 Lot # 49875 | N45: 34972 | O45: #N/A
L46: 104 | M46: K-C AVENT TAPE 0.5" ON MASK #ROSU00588 Rev 3 | N46: 87300 | O46: 33494.7
L47: 7154 | M47: URGO - VASHE 475 ml Flip Top 00314 | N47: 77700 | O47: 36058.83
L48: 7940 | M48: Pause life vulva moisturizer 15mL with Xylitol | N48: 75250 | O48: 53751.475
L49: 7157 | M49: URGO - VASHE 1 L Instill 00323 | N49: 68413.68 | O49: 37737.166
L50: 4804 | M50: KCI PEEL AND PLACE PREVENA LONG (35Cm)-416697, Rev D | N50: 68378 | O50: 37319.5
L51: 6370 | M51: TB DRY MOUTH TINGLING RINSE 16 OZ BULK 40101908 | N51: 66664.28 | O51: 24570.221
L52: 6013 | M52: MEDLINE CURAD MEDI STRIP 1 X 5 NON250501 | N52: 61992 | O52: 30267.603
L53: 3752 | M53: MPM 4 x 5 THIN FILM DRESSING STERILE MP00470 | N53: 59660 | O53: 13688.842
L54: 3850 | M54: MEDISTRIP 1/2 IN X 4 IN BULK NONSTERILE 3/CD | N54: 54404 | O54: 21132.222
L55: 6011 | M55: MEDLINE CURAD MEDISTRIP 1/4 X 4 IN STERILE NON250414 | N55: 52890.24 | O55: 24128.362
L56: 7158 | M56: URGO - VASHE 1 L Flip Top 00322 | N56: 52810.56 | O56: 27105.9
L57: 3423 | M57: MPM Cool Magic Gel Sheet 3.75"x3.75" OL MP00206 | N57: 49680 | O57: 13616.376
... L108: 5666 | M108: MPM RadiaPlex Rx Gel 6oz. MP00106 | N108: 9364.4 | O108: 3877.9602
L109: F-22007 | M109: ADVANCED 2" × 200' ROLL SEMI-OCCLUSIVE | N109: 8599.2 | O109: 5045.3715
L110: 5520 | M110: D* Tetrapotassium Pyrophosphate CAS#7320-34-5 1614086 | N110: 8331.11 | O110: #N/A
L111: 7976 | M111: 4" x 8" Therabond 3D Island Dressing 3DAI-48 | N111: 8050 | O111: 8050
L112: 6929 | M112: NEXGEL SILVER SEAL 2X3 HYDROGEL DRESSING | N112: 8029.88 | O112: 5549.3467
L113: 7975 | M113: 4" x 6" Therabond 3D Island Dressing 3DAI-46 | N113: 8005.8 | O113: 8005.8
L114: 5440 | M114: MPM Regenecare HA Gel 0.5oz. MP00112 | N114: 7700 | O114: 4408.87
L115: 7863 | M115: ViaCLYR Flip Top 32oz | N115: 7520 | O115: 5463.174
L116: 6328 | M116: CARBOX WAX SENTRY POLYETHYLENE GLYCOL 600 NF CAS#25322-68-3 | N116: 6977.1 | O116: #N/A
L117: 7982 | M117: 2" x 2" Therabond 3D Island Dressing 3DAI-410 | N117: 1680 | O117: 1680
M118: 2" x 2" Therabond 3D Island Dressing 3DAI-22 | N118: 5040 | O118: 5040
L119: F-22004 | M119: 5 SITE SEMI-OCCLUSIVE STRIP | N119: 6560 | O119: 2378.112
L120: 5671 | M120: MPM OraMagic Rx 12oz MP00213 | N120: 6408 | O120: 2833.7004
L121: 7992 | M121: Port Drape | N121: 6250 | O121: 5600
L122: 3853 | M122: MEDISTRIP 1 IN X 4 IN BULK NON-STERILE | N122: 5895 | O122: 1875.2854
L123: 7980 | M123: 4" x 10" Therabond 3D Island Dressing 3DAI-410 | N123: 5400 | O123: 5400
L124: 6930 | M124: NEXGEL TURF GUARD 2X3 HYDROGEL DRESSING | N124: 5234.95 | O124: 3599.3981
L125: 3851 | M125: MEDISTRIP 1/4 IN X 4 IN BULK NON-STERILE 5/CD | N125: 5070 | O125: -150.83245
L126: 6323 | M126: MINERALIZ GU/Zn CAS# 4468-02-4 KOSHER | N126: 4961.39 | O126: #N/A
L127: 5662 | M127: MPM Regenecare Wound Gel 0.5 oz, MP00101 | N127: 4900 | O127: 1159.305
L128: 5674 | M128: MPM OraMagic Plus 8oz MP00224 | N128: 4900 | O128: 1261.37
L129: F-22008 | M129: ADVANCED 2" × 200' ROLL OCCLUSIVE | N129: 4134.4 | O129: 1782.1717
L130: 5521 | M130: D* Tetrasodium Pyrophosphate CAS#7722-88-5 KOSHER | N130: 3825.84 | O130: #N/A
L131: 7987 | M131: 4" x 10" Therabond 3D Island Dressing 3DAIXS-410 | N131: 2700 | O131: 2700
L132: N-4008 | M132: Expedite Fee for 15ml Bottles | N132: 2556.79 | O132: #N/A
L133: 5515 | M133: D* Dentsil DS 60 HYDRATED SILICA - CAS#112926-00-8 KOSHER | N133: 2414.7 | O133: #N/A
L134: 7979 | M134: 4" x 14" Therabond 3D Island Dressing 3DAIXS-412 | N134: 2200 | O134: 2200
L135: 7217 | M135: DERMACLIP EXT 3 CLIP PAD NS -31005 | N135: 2039.73 | O135: 125.9112
L136: 7794 | M136: PERIOSCIENCES AO ProRinse SENSITIVE 32 oz | N136: 2025 | O136: 850.9122
L137: 3849 | M137: MEDISTRIP 1/4 IN X 1.5 IN BULK NON-STERILE | N137: 1980 | O137: 48.102
L138: 5590 | M138: BAG, AP2390.11 Arena "Air-Evac" Vertex, 3Ply Liquid Liner Bag | N138: 1863.13 | O138: #N/A
L139: 5703 | M139: D* Glycerin 99.7% CAS# 56-81-5 KOSHER | N139: 1661.22 | O139: -310.0944
L140: N-4009 | M140: Artwork Prep/Plate Fee(s) | N140: 1450 | O140: #N/A
L141: 3852 | M141: MEDISTRIP 1/4 IN X 3 IN BULK NON-STERILE | N141: 1428 | O141: 607.602
L142: 7812 | M142: PERIO AO ProRinse WHITE CARE 32 oz | N142: 1390 | O142: 1390
L143: 5639 | M143: D* Sorbitol Crystalline Powder NF, CAS# 50-70-4 KOSHER | N143: 1215.81 | O143: #N/A
L144: 5525 | M144: D* AmmoniumGlycyrrhizate Magnasweet 110-2X CAS#53956-04-0 KOSHER | N144: 1033.12 | O144: #N/A
L145: 8012 | M145: Bloomi Delight 3oz (1K Use Only) | N145: 1000 | O145: 999.26485
L146: 606 | M146: MEDISTRIP 1/8 IN X 3 IN BULK | N146: 969 | O146: 299.45733
L147: 5518 | M147: D* Mint Flavor WONF OS, Natural 113.19228 CAS# 68917-18-0 KOSHER | N147: 963.58 | O147: #N/A
L148: 5713 | M148: Polysorbate 20 CAS# 9005-64-5 | N148: 919.01 | O148: #N/A
L149: 6330 | M149: MENTHOL CAS#2216-51-5 KOSHER | N149: 867.7 | O149: #N/A
L150: 7224 | M150: GREEN TEA PHYTOBASIC IN PG (3345L) KOSHER | N150: 853.65 | O150: -28.889625
...

Sheet Sales Receipts
C2: ItemCode | D2: (All)
T3: Row Labels | U3: Sum of LineAmount
C4: Total | T4: Jan | U4: 1618569
C5: 5091379.4 | T5: Feb | U5: 1926002.6
T6: Grand Total | U6: 3544571.5

Sheet Order receipts
A1: SONumber | B1: OrderDate | C1: CustomerCode | D1: CustomerName | E1: SalesRepName | F1: CustomerPONumber | G1: RequestedShipDate | H1: ItemCode | I1: ItemDescription | J1: LineAmount
A2: 0000064853 | B2: 46024 | C2: MEDL | D2: Medline Industries, Inc. | E2: Brian Davies | F2: 4519453530 | G2: 46112 | H2: 003132 | I2: MEDLINE CURAD NASAL TUBE HOLDER CURNASTUB50 | J2: 165
A3: 0000064854 | B3: 46024 | C3: MEDL | D3: Medline Industries, Inc. | E3: Brian Davies | F3: 4519453531 | G3: 46112 | H3: 003132 | I3: MEDLINE CURAD NASAL TUBE HOLDER CURNASTUB50 | J3: 495
A4: 0000064855 | B4: 46024 | C4: MEDL | D4: Medline Industries, Inc. | E4: Brian Davies | F4: 4519453529 | G4: 46112 | H4: 005116 | I4: MEDLINE OPTIFOAM THIN 2X3 MSC1523EP | J4: 63.42
A5: 0000064856 | B5: 46024 | C5: MEDL | D5: Medline Industries, Inc. | E5: Brian Davies | F5: 4519453534 | G5: 46112 | H5: 005116 | I5: MEDLINE OPTIFOAM THIN 2X3 MSC1523EP | J5: 126.84
A6: 0000064856 | B6: 46024 | C6: MEDL | D6: Medline Industries, Inc. | E6: Brian Davies | F6: 4519453534 | G6: 46112 | H6: 005979 | I6: MEDLINE SUREFILM 4" X 11 YARDS MSC2404 | J6: 32121.6
A7: 0000064858 | B7: 46027 | C7: MEDL | D7: Medline Industries, Inc. | E7: Brian Davies | F7: 4519458618 | G7: 46113 | H7: 003132 | I7: MEDLINE CURAD NASAL TUBE HOLDER CURNASTUB50 | J7: 165
A8: 0000064859 | B8: 46027 | C8: MEDL | D8: Medline Industries, Inc. | E8: Brian Davies | F8: 4519458611 | G8: 46113 | H8: 005116 | I8: MEDLINE OPTIFOAM THIN 2X3 MSC1523EP | J8: 190.26
A9: 0000064859 | B9: 46027 | C9: MEDL | D9: Medline Industries, Inc. | E9: Brian Davies | F9: 4519458611 | G9: 46113 | H9: 005117 | I9: MEDLINE OPTIFOAM THIN 4x4 MSC1544EP | J9: 94.6
A10: 0000064866 | B10: 46027 | C10: MEDL | D10: Medline Industries, Inc. | E10: Brian Davies | F10: 4519458612 | G10: 46113 | H10: 003132 | I10: MEDLINE CURAD NASAL TUBE HOLDER CURNASTUB50 | J10: 220
A11: 0000064867 | B11: 46027 | C11: MEDL | D11: Medline Industries, Inc. | E11: Brian Davies | F11: 4519458620 | G11: 46113 | H11: 003132 | I11: MEDLINE CURAD NASAL TUBE HOLDER CURNASTUB50 | J11: 275
A12: 0000064867 | B12: 46027 | C12: MEDL | D12: Medline Industries, Inc. | E12: Brian Davies | F12: 4519458620 | G12: 46113 | H12: 005117 | I12: MEDLINE OPTIFOAM THIN 4x4 MSC1544EP | J12: 946
A13: 0000064868 | B13: 46027 | C13: MEDL | D13: Medline Industries, Inc. | E13: Brian Davies | F13: 4519458628 | G13: 46113 | H13: 003132 | I13: MEDLINE CURAD NASAL TUBE HOLDER CURNASTUB50 | J13: 55
... A198: 0000064990 | B198: 46064 | C198: HARM IRE | D198: Harmac Medical Products | E198: Jennifer Hurrell | F198: 043926 | G198: 46108 | H198: 007992 | I198: Port Drape | J198: 6250
A199: 0000064987 | B199: 46064 | C199: CLYRA | D199: Clyra Medical Technologies, Inc. | E199: Brian Davies | G199: 2 | H199: N-4001 | I199: Credit for Bottles & Caps | J199: -8084.98
A200: 0000064987 | B200: 46064 | C200: CLYRA | D200: Clyra Medical Technologies, Inc. | E200: Brian Davies | G200: 2 | H200: N-4001 | I200: Cleaning Validation Cost | J200: 8448
A201: 0000064983 | B201: 46064 | C201: MPM | D201: MPM Medical, Inc. | E201: Jennifer Hurrell | F201: 000293 | G201: 46153 | H201: 003423 | I201: MPM Cool Magic Gel Sheet 3.75"x3.75" OL MP00206 | J201: 49680
A202: 0000064989 | B202: 46064 | C202: MPM-COL | D202: MPM Medical LLC - COL | E202: Jennifer Hurrell | F202: 51506 | G202: 2 | H202: 007843 | I202: FIDIA PHARMA 2 x 2 Collagen Drsg Carton 3.625" x 1.5" x 4.625" | J202: 946.5
A203: 0000064985 | B203: 46064 | C203: Bloomi | D203: The Bloomi Inc | E203: PCI House Account | F203: CV-DELIGHT-020626 | G203: 2 | H203: N-4001 | I203: Cleaning validation for Delight production | J203: 3000
A204: 0000064986 | B204: 46064 | C204: Bloomi | D204: The Bloomi Inc | E204: PCI House Account | F204: DELIGHT-121825 | G204: 2 | H204: 007991 | I204: Bloomi Delight 3oz | J204: 17250
A205: 0000064984 | B205: 46064 | C205: ORORA | D205: Orora Business Service Center | E205: Bryan Daniels | F205: 5300704796 | G205: 46064 | H205: 005639 | I205: D* Sorbitol Crystalline Powder NF, CAS# 50-70-4 KOSHER | J205: 1215.8134
A206: 0000064984 | B206: 46064 | C206: ORORA | D206: Orora Business Service Center | E206: Bryan Daniels | F206: 5300704796 | G206: 46064 | H206: 005515 | I206: D* Dentsil DS 60 HYDRATED SILICA - CAS#112926-00-8 KOSHER | J206: 2414.6967
A207: 0000064984 | B207: 46064 | C207: ORORA | D207: Orora Business Service Center | E207: Bryan Daniels | F207: 5300704796 | G207: 46064 | H207: 005703 | I207: D* Glycerin 99.7% CAS# 56-81-5 KOSHER | J207: 1661.22
A208: 0000064984 | B208: 46064 | C208: ORORA | D208: Orora Business Service Center | E208: Bryan Daniels | F208: 5300704796 | G208: 46064 | H208: 005517 | I208: D* Cooling Type Flavor Natural 113.90468 KOSHER | J208: 790.03883
A209: 0000064984 | B209: 46064 | C209: ORORA | D209: Orora Business Service Center | E209: Bryan Daniels | F209: 5300704796 | G209: 46064 | H209: 005518 | I209: D* Mint Flavor WONF OS, Natural 113.19228 CAS# 68917-18-0 KOSHER | J209: 963.57716
A210: 0000064984 | B210: 46064 | C210: ORORA | D210: Orora Business Service Center | E210: Bryan Daniels | F210: 5300704796 | G210: 46064 | H210: 007525 | I210: D* BLANOSE™ CMC 7MF CAS#9004-32-4 KOSHER | J210: 278.5286
A211: 0000064984 | B211: 46064 | C211: ORORA | D211: Orora Business Service Center | E211: Bryan Daniels | F211: 5300704796 | G211: 46064 | H211: 005520 | I211: D* Tetrapotassium Pyrophosphate CAS#7320-34-5 1614086 | J211: 8331.106
A212: 0000064984 | B212: 46064 | C212: ORORA | D212: Orora Business Service Center | E212: Bryan Daniels | F212: 5300704796 | G212: 46064 | H212: 005521 | I212: D* Tetrasodium Pyrophosphate CAS#7722-88-5 KOSHER | J212: 3825.8385
... A259: 0000065014 | B259: 46077 | C259: FREUD | D259: Freudenberg Performance Materials LP | E259: Bryan Daniels | F259: 47036876 | G259: 46237 | H259: 005045 | I259: FREUDENBERG 30cm X 47cm Nonwoven Sheets 122P0463 | J259: 40750
J260: =SUM(J241:J259) -> 346225.89
J1334: =SUM(J1314:J1333) -> 0

Sheet Inventory
G2: Inventory
D3: Part number | E3: Description | F3: WIP | G3: 25-Jan | H3: 6-Feb | I3: 13-Feb | J3: 21-Feb | K3: 28-Feb | L3: 3/6/2024 | M3: 3/13/2024 | N3: 4/3/2024 | O3: 4/10/2024 | P3: 4/19/20242 | Q3: 4/24/2024 | R3: 45413 | S3: 45420 | T3: 45427 | U3: 45434 | V3: 45442 | W3: 45448 | X3: 45467 | Y3: 45476 | Z3: 45483 | AA3: 45504 | AB3: 45510
D4: CELG09 | E4: CelGenera Surgical Matrix Collagen Powder | F4: 0 | G4: 178 | H4: 166 | I4: 166 | J4: 166 | K4: 130 | L4: 1066 | M4: 1066 | N4: 982 | O4: 982 | P4: 970 | Q4: 970 | R4: 970 | S4: 958 | T4: 958 | U4: 958 | V4: 958 | W4: 958 | X4: 958 | Y4: 958 | Z4: 958 | AA4: 958 | AB4: 958
D5: CELG18 | E5: CelGenera Surgical Matrix 8"x12" Collagen Dressing | F5: 0 | G5: 0 | H5: 0 | I5: 0 | J5: 0 | K5: 0 | L5: 0 | M5: 0 | N5: 0 | O5: 0 | P5: 27 | Q5: 27 | R5: 27 | S5: 27 | T5: 27 | U5: 27 | V5: 27 | W5: 27 | X5: 27 | Y5: 27 | Z5: 27 | AA5: 27 | AB5: 27
D6: CELG27 | E6: CelGenera Surgical Matrix 7"x7" Collagen Dressing | F6: 0 | G6: 138 | H6: 128 | I6: 128 | J6: 128 | K6: 100 | L6: 100 | M6: 100 | N6: 80 | O6: 80 | P6: 80 | Q6: 80 | R6: 80 | S6: 80 | T6: 80 | U6: 80 | V6: 80 | W6: 80 | X6: 80 | Y6: 80 | Z6: 80 | AA6: 80 | AB6: 80
D7: ANG09 | E7: AngioGenes Surgical Matrix Collagen Powder 2.5mL | F7: 0 | G7: 480 | H7: 480 | I7: 480 | J7: 480 | K7: 468 | L7: 468 | M7: 468 | N7: 456 | O7: 456 | P7: 456 | Q7: 456 | R7: 456 | S7: 456 | T7: 456 | U7: 456 | V7: 456 | W7: 456 | X7: 456 | Y7: 456 | Z7: 456 | AA7: 456 | AB7: 456
D8: 7495 | E8: Comatryx OTC 1 GRAM | F8: 0 | G8: 0 | H8: 0 | I8: 0 | J8: 0 | K8: 0 | L8: 0 | M8: 0 | N8: 0 | O8: 0 | P8: 0 | Q8: 0 | R8: 0 | S8: 0 | T8: 0 | U8: 0 | V8: 0 | W8: 0 | X8: 0 | Y8: 0 | Z8: 0 | AA8: 0 | AB8: 0
D9: CELG45 | E9: CelGenera Surgical Matrix 4"x5" Collagen Dressing | F9: 0 | G9: 0 | H9: 0 | I9: 0 | J9: 0 | K9: 0 | L9: 0 | M9: 0 | N9: 0 | O9: 0 | P9: 0 | Q9: 0 | R9: 0 | S9: 0 | T9: 0 | U9: 0 | V9: 0 | W9: 0 | X9: 0 | Y9: 0 | Z9: 0 | AA9: 0 | AB9: 0

Sheet Feb shipped
H1: =SUM(H3:H300) -> 531501.01 | I1: To be shipped | J1: 1189209.4
A2: Customer | B2: Ship date | C2: CustomerPONumber | D2: Item# | E2: Description | F2: Order Qty | G2: Ship Qty | H2: ShippedValue2 | I2: Total Shipment for this month | J2: =H1+J1 -> 1720710.4 | K2: =J2-K3 -> 1448095.3
A3: AXI$-2500 | B3: 46057 | C3: 1 | D3: F-22004 | E3: 5 SITE SEMI-OCCLUSIVE STRIP | F3: 4000 | G3: 4000 | H3: 1760 | I3: 7153 | J3: URGO - VASHE 250 ml Flip Top 00313 | K3: 272615.04 | L3: 145008
A4: CENTURION | B4: 46070 | C4: 6000027025 | D4: 609 | E4: MEDISTRIP 1/4 IN X 3 IN BULK | F4: 5 | G4: 5 | H4: 595
A5: CENTURION | B5: 46070 | C5: 6000027025 | D5: 610 | E5: MEDISTRIP 1 IN X 4 IN BULK | F5: 18 | G5: 18 | H5: 3537
A6: CLYRA | B6: 46064 | D6: N-4001 | E6: Credit for Bottles & Caps | F6: 1 | G6: 1 | H6: -8084.98
A7: CLYRA | B7: 46064 | D7: N-4001 | E7: Cleaning Validation Cost | F7: 1 | G7: 1 | H7: 8448
A8: DETEKT | B8: 46063 | C8: 1167 | D8: N-4001 | E8: Sebutape Skin Strip Samples 7500EA | F8: 1 | G8: 1 | H8: 5926.15
A9: DETEKT | B9: 46063 | C9: 1167 | D9: N-4001 | E9: D-Squame Skin Strip Samples 7500EA | F9: 1 | G9: 1 | H9: 6609.91
A10: DETEKT | B10: 46063 | C10: 1167 | D10: N-4003 | E10: Tooling Charges | F10: 1 | G10: 1 | H10: 4500
A11: GlorySun | B11: 46055 | C11: 20251105001 | D11: 6145 | E11: MEDLINE/GLORY SUN SAFE SECURE FOAM BASE | F11: 5400 | G11: 5400 | H11: 1944
A12: IOTECH | B12: 46057 | C12: 2025-09-15-ULTRA | D12: 7560 | E12: ioTech ioRinse Ultra 1 liter | F12: 15000 | G12: 14892 | H12: 25316.4
A13: IOTECH | B13: 46057 | C13: 2025-09-15-ULTRA | D13: 7561 | E13: ioTech ioRinse Ultra 16 oz | F13: 15000 | G13: 14300 | H13: 22451
A14: KCI IRE | B14: 46065 | C14: 1047951 | D14: 4804 | E14: KCI PEEL AND PLACE PREVENA LONG (35Cm)-416697, Rev D | F14: 20000 | G14: 20000 | H14: 68378
A15: MEDL | B15: 46058 | C15: 110445730 | D15: 4831 | E15: MEDLINE 121043 16"x20" Instrument Drape | F15: 1 | G15: 1 | H15: 295
A16: MEDL | B16: 46058 | C16: 4519562462 | D16: 5116 | E16: MEDLINE OPTIFOAM THIN 2X3 MSC1523EP | F16: 4 | G16: 0 | H16: 0
A17: MEDL | B17: 46058 | C17: 4519562462 | D17: 5117 | E17: MEDLINE OPTIFOAM THIN 4x4 MSC1544EP | F17: 18 | G17: 0 | H17: 0
A18: MEDL | B18: 46058 | C18: 4519562462 | D18: 5975 | E18: MEDLINE SUREFILM 2" X 11 YARDS MSC2402 | F18: 1 | G18: 1 | H18: 79.89
A19: MEDL | B19: 46069 | C19: 686078633 | D19: 609 | E19: MEDISTRIP 1/4 IN X 3 IN BULK | F19: 46 | G19: 46 | H19: 5474
A20: MPM | B20: 46056 | C20: 239 | D20: 5668 | E20: MPM Regenecare HA Gel 3oz. MP00107 | F20: 1312 | G20: 1175 | H20: 2749.5
A21: MPM | B21: 46058 | C21: 289 | D21: 7719 | E21: "Purge" D* 4oz Bottle, MPM Regenecare HA Spray MP00117 R0325 | F21: 18380 | G21: 18380 | H21: 4960.17
A22: MPM | B22: 46063 | C22: 51501 | D22: 7842 | E22: FIDIA PHARMA 2 x 2 Chevron Tyvek/Poly Pouch 3.5" x 4.5" | F22: 6800 | G22: 6800 | H22: 734.4
A23: MPM | B23: 46069 | C23: 251 | D23: 5666 | E23: MPM RadiaPlex Rx Gel 6oz. MP00106 | F23: 10000 | G23: 7716 | H23: 31635.6
A24: MPM-COL | B24: 46064 | C24: 51506 | D24: 7843 | E24: FIDIA PHARMA 2 x 2 Collagen Drsg Carton 3.625" x 1.5" x 4.625" | F24: 1500 | G24: 1500 | H24: 946.5
A25: MPM-COL | B25: 46065 | C25: 51507 | D25: R-170061 | E25: Box S-4345 8 X 8 X 5 | F25: 130 | G25: 130 | H25: 92.3
A26: MPM-COL | B26: 46069 | C26: 51509 | D26: 7057 | E26: D* SODIUM HYALURONATE (Hyaluronic Acid) CAS# 9067-32-7 | F26: 1000 | G26: 1000 | H26: 400
A27: MPM-COL | B27: 46069 | C27: 51509 | D27: 7919 | E27: Hyaluronate Acid Powder CAS# 9067-32-7 | F27: 250 | G27: 250 | H27: 31.25
A28: MPM-COL | B28: 46072 | C28: 51508 | D28: 4679 | E28: BM 2110 USA DOMESTIC BOVINE COLLAGEN DOUGH | F28: 1600 | G28: 1600 | H28: 24464
A29: MPM-COL | B29: 46072 | C29: 51508 | D29: N-4001 | E29: Freight Cost | F29: 1 | G29: 1 | H29: 4150
A30: ORORA | B30: 46064 | C30: 4500984616 | D30: 6370 | E30: TB DRY MOUTH TINGLING RINSE 16 OZ BULK 40101908 | F30: 82000 | G30: 44525 | H30: 79205.52
A31: URGO | B31: 46066 | C31: PO00137299 | D31: 7152 | E31: URGO - VASHE 118 ml Flip Top 00312 | F31: 49992 | G31: 49992 | H31: 85486.32
A32: URGO | B32: 46066 | C32: PO00137299 | D32: 7153 | E32: URGO - VASHE 250 ml Flip Top 00313 | F32: 50004 | G32: 0 | H32: 0
A33: URGO | B33: 46066 | C33: PO00137299 | D33: 7152 | E33: URGO - VASHE 118 ml Flip Top 00312 | F33: 75000 | G33: 75048 | H33: 128332.08
A34: URGO | B34: 46073 | C34: Rework_Nov2025 | D34: N-4001 | E34: Urgo Rework Item 603070 Lot # 49874 | F34: 23160 | G34: 0 | H34: 0
A35: URGO | B35: 46073 | C35: Rework_Nov2025 | D35: N-4001 | E35: Urgo Rework Item 603071 Lot # 49875 | F35: 80080 | G35: 30120 | H35: 21084
A36: URGO | B36: 46073 | C36: Rework_Nov2025 | D36: N-4001 | E36: Urgo Rework Item 603073 Lot # 47954 | F36: 2760 | G36: 0 | H36: 0
A37: URGO | B37: 46073 | C37: Rework_Nov2025 | D37: N-4001 | E37: Urgo Rework Item 603073 Lot # 50921 | F37: 2250 | G37: 0 | H37: 0
H59: =SUM(H55:H58) -> 0

Sheet PurchaseOrders_11-26_03-06
A1: PONumber | B1: EntryDate | C1: VendorCode | D1: VendorName | E1: ItemCode | F1: ItemDescription | G1: OrderQuantity | H1: UOM | I1: OriginalOrderQuantity | J1: QtyRecv | K1: DueDate | L1: ReceivedDate | M1: Comments
A2: 0000051426 | B2: 45957 | C2: SHANG YOUS | D2: Shanghai Careus Medical Products Co., Ltd (Youshi) | E2: 007917 | F2: Transparent PE Tape 2.0" | G2: 19000 | H2: LF | I2: 20000 | J2: 1000 | K2: 45987 | L2: 12/03/2025
A3: 0000051679 | B3: 45994 | C3: BSBT | D3: Beijing Sunpu Biochem Tech Co, LTD | E3: 007724 | F3: IPBC (3-Iodo-2-propynyl butylcarbamate) SupGaurd® CAS#55406-53-6 | G3: 1000 | H3: EA | I3: 1000 | J3: 0 | K3: 46056 | L3: 01/01/1900
A4: 0000051877 | B4: 46029 | C4: DERMAMED | D4: DermaMed Coatings | E4: 006146 | F4: DM-5001 4.5" | G4: 37050 | H4: LF | I4: 37050 | J4: 0 | K4: 46076 | L4: 01/01/1900
A5: 0000051987 | B5: 46041 | C5: CROSSTEX | D5: Crosstex | E5: 005350 | F5: Gamma Dot Printed CPI-R03 | G5: 25000 | H5: EA | I5: 25000 | J5: 0 | K5: 46076 | L5: 01/01/1900
A6: 0000051636 | B6: 45986 | C6: LONGGANG | D6: Longgang Zhongchuang Printing Co, Ltd | E6: 007532 | F6: Cohesive Paper Unprinted Latex Free 9.5" | G6: 78170 | H6: LF | I6: 91294 | J6: 13124 | K6: 46077 | L6: 02/16/2026
A7: 0000052250 | B7: 46076 | C7: ULINE | D7: Uline | E7: 005221 | F7: BOX 12X12X10 275 LB. TEST DW #S-15036 | G7: 15 | H7: EA | I7: 15 | J7: 0 | K7: 46077 | L7: 01/01/1900
A8: 0000051936 | B8: 46035 | C8: MEYERS | D8: Meyers Printing | E8: 007163 | F8: URGO - 118 ml (4 oz) Bottle Label Front Vashe / RM7271 | G8: 154400 | H8: EA | I8: 154400 | J8: 0 | K8: 46079 | L8: 01/01/1900
A9: 0000051936 | B9: 46035 | C9: MEYERS | D9: Meyers Printing | E9: 007420 | F9: VASHE - 118 ml (4 oz) Bottle Label Back 00312 201-LB006 REV 9/23 | G9: 154440 | H9: EA | I9: 154440 | J9: 0 | K9: 46079 | L9: 01/01/1900
A10: 0000051936 | B10: 46035 | C10: MEYERS | D10: Meyers Printing | E10: 007424 | F10: VASHE - 250 ml Bottle Label Back 00313 201-LB007 REV 9/23 | G10: 184675 | H10: EA | I10: 184675 | J10: 0 | K10: 46079 | L10: 01/01/1900
A11: 0000052131 | B11: 46063 | C11: EMULTEC | D11: EMULTEC CHEMICAL INNOVATIONS | E11: 005694 | F11: LIPONATE® GC (Caprylic/Capric Triglycerides) CAS# 73398-61-5 | G11: 15880 | H11: GM | I11: 15880 | J11: 0 | K11: 46079 | L11: 01/01/1900
A12: 0000051653 | B12: 45993 | C12: PENNCO | D12: Pennco Container | E12: 007960 | F12: Pauselife 15ml Tube with White cap | G12: 27200 | H12: EA | I12: 27200 | J12: 0 | K12: 46080 | L12: 01/01/1900
A13: 0000051781 | B13: 46007 | C13: PENNCO | D13: Pennco Container | E13: 007168 | F13: URGO - 250 ml Bottle Domed Oval PET, 24/410 | G13: 152340 | H13: EA | I13: 152340 | J13: 0 | K13: 46080 | L13: 01/01/1900
... A98: 0000052202 | B98: 46071 | C98: GARBO | D98: MuseChem | E98: 007807 | F98: Epigallocateechin Gallate CAS# 989-51-5 | G98: 1000 | H98: GM | I98: 1000 | J98: 0 | K98: 46094 | L98: 01/01/1900

Sheet Cost sheet
C2: ItemCode | D2: ItemDescription | E2: Price | F2: Cost | G2: GP | H2: Gp%
C3: 100 | D3: ADROIT FACE SHIELD TAPE 1/2 X 300 LY | E3: 12.158 | F3: 10.12528 | G3: =E3-F3 -> 2.03272 | H3: =G3/E3 -> 0.16719197
C4: 101 | D4: SAF TUBE TAMER | E4: 0.54 | F4: 0.226594 | G4: =E4-F4 -> 0.313406 | H4: =G4/E4 -> 0.58038148
C5: 102 | D5: Carrot-Top Industries Electrode Tape-T8001 30 LY RL | E5: 24.2 | F5: 14.118799 | G5: =E5-F5 -> 10.081201 | H5: =G5/E5 -> 0.41657855
C6: 103 | D6: HYDROMED 4 x 1 TYVEK STRIP W/ADH TAB | E6: 0.45 | F6: 0.022941 | G6: =E6-F6 -> 0.427059 | H6: =G6/E6 -> 0.94902
C7: 104 | D7: K-C AVENT TAPE 0.5" ON MASK #ROSU00588 Rev 3 | E7: 0.243 | F7: 0.131351 | G7: =E7-F7 -> 0.111649 | H7: =G7/E7 -> 0.45946091
C8: 107 | D8: HYDROMED 6 X 7/8 TAPE STRIPS PRTD | E8: 111.2 | F8: 41.447871 | G8: =E8-F8 -> 69.752129 | H8: =G8/E8 -> 0.62726735
C9: 110 | D9: HYDROMED 1 X 9 POLY TAPE TEAR HERE | E9: 0.1779 | F9: 0.0344 | G9: =E9-F9 -> 0.1435 | H9: =G9/E9 -> 0.80663294
C10: 114 | D10: STERIMED 3M 9889EL 1 X 72 LY | E10: 13.81 | F10: 10.39708 | G10: =E10-F10 -> 3.41292 | H10: =G10/E10 -> 0.24713396
C11: 118 | D11: MUELLER 1/4 X 6 X 72 FOAM RL B060252 | E11: 6.58 | F11: 6.401894 | G11: =E11-F11 -> 0.178106 | H11: =G11/E11 -> 0.027067781
C12: 124 | D12: **INACTIVE**MUELLER BULK FOAM VARIETY PACK B060271 | E12: 10.2 | F12: 7.646388 | G12: =E12-F12 -> 2.553612 | H12: =G12/E12 -> 0.25035412
C13: 136 | D13: B BRAUN PAD STAR 140962 | E13: 0.8894 | F13: 0.309326 | G13: =E13-F13 -> 0.580074 | H13: =G13/E13 -> 0.65220823
C14: 137 | D14: STERIMED STRAPS PE 1 X 30 | E14: 0.098 | F14: 0.012478 | G14: =E14-F14 -> 0.085522 | H14: =G14/E14 -> 0.87267347
... C370: 3850 | D370: MEDISTRIP 1/2 IN X 4 IN BULK NONSTERILE 3/CD | E370: 1943 | F370: 1188.2778 | G370: =E370-F370 -> 754.72223 | H370: =G370/E370 -> 0.38843141
C371: 3851 | D371: MEDISTRIP 1/4 IN X 4 IN BULK NON-STERILE 5/CD | E371: 195 | F371: 200.80125 | G371: =E371-F371 -> -5.801248 | H371: =G371/E371 -> -0.02974999 | J371: Standard cost is higher than the unit price.
C372: 3852 | D372: MEDISTRIP 1/4 IN X 3 IN BULK NON-STERILE | E372: 119 | F372: 68.3665 | G372: =E372-F372 -> 50.6335 | H372: =G372/E372 -> 0.4254916
C373: 3853 | D373: MEDISTRIP 1 IN X 4 IN BULK NON-STERILE | E373: 196.5 | F373: 133.99049 | G373: =E373-F373 -> 62.509515 | H373: =G373/E373 -> 0.31811458
C374: 3854 | D374: PSS #4802 Cloth Retention Tape 1", 2 rl/ea, 6 ea/ctn, 8 ctn/cs | E374: 143.5 | F374: 50.208 | G374: =E374-F374 -> 93.292 | H374: =G374/E374 -> 0.65011847
C375: 3855 | D375: PSS #4803 Cloth Retention Tape 2", 1 rl/ea, 12 ea/ctn, 8 ctn/cs | E375: 222.8 | F375: 90.3744 | G375: =E375-F375 -> 132.4256 | H375: =G375/E375 -> 0.59436984
C376: 3856 | D376: PSS #4804 Cloth Retention Tape 3", 1 rl/ea, 12 ea/ctn, 8 ctn/cs | E376: 319.68 | F376: 131.54496 | G376: =E376-F376 -> 188.13504 | H376: =G376/E376 -> 0.58851051
C377: 3857 | D377: PSS #4805 Cloth Retention Tape 4", 1 rl/ea, 12 ea/ctn, 8 ctn/cs | E377: 415.8 | F377: 178.74048 | G377: =E377-F377 -> 237.05952 | H377: =G377/E377 -> 0.57012872
C378: 3858 | D378: PSS #4806 Cloth Retention Tape 6", 1 rl/ea, 12 ea/ctn, 8 ctn/cs | E378: 615.5 | F378: 271.1232 | G378: =E378-F378 -> 344.3768 | H378: =G378/E378 -> 0.55950739
C379: 3871 | D379: GWM 1/8 IN Foam Dressing 4x5 Non-Sterile | E379: 1.1704 | F379: 1.027058 | G379: =E379-F379 -> 0.143342 | H379: =G379/E379 -> 0.12247266
C380: 3879 | D380: GWM 1/8 IN Foam Dressing 4x4 Non-Sterile | E380: 1.0229 | F380: 0.931588 | G380: =E380-F380 -> 0.091312 | H380: =G380/E380 -> 0.089267768
C381: 3882 | D381: SWISS 4X4 (2.5X2.5) SSL P99-044 | E381: 0.3353 | F381: 0.267462 | G381: =E381-F381 -> 0.067838 | H381: =G381/E381 -> 0.20232031
C382: 3900 | D382: MEDLINE FOAM PAD 4x5 MSC1145 | E382: 78.34 | F382: 75.399425 | G382: =E382-F382 -> 2.940575 | H382: =G382/E382 -> 0.037536061
C383: 3901 | D383: MEDLINE FOAM PAD 3x3 MSC1133 | E383: 49.13 | F383: 43.955818 | G383: =E383-F383 -> 5.174182 | H383: =G383/E383 -> 0.10531614
... C1034: 7795 | D1034: PERIO AO ProRinse HYDRATING 10 oz | E1034: 3 | F1034: 1.839036 | G1034: =E1034-F1034 -> 1.160964 | H1034: =G1034/E1034 -> 0.386988
C1035: 7801 | D1035: PERIO AO ProRinse HYDRATING 32 oz | E1035: 9.15 | F1035: 5.721824 | G1035: =E1035-F1035 -> 3.428176 | H1035: =G1035/E1035 -> 0.37466404 | J1035: Email sent to Engineering to correct it.
C1036: 7803 | D1036: PERIO AO ProRinse NATURAL 10 oz | E1036: 2.54 | F1036: 2.653206 | G1036: =E1036-F1036 -> -0.113206 | H1036: =G1036/E1036 -> -0.044569291 | J1036: Unit Price - 2.540000
C1037: 7804 | D1037: PERIO AO ProRinse NATURAL 32 oz | E1037: 6.66 | F1037: 4.512609 | G1037: =E1037-F1037 -> 2.147391 | H1037: =G1037/E1037 -> 0.32243108 | J1037: Standard Cost - 2.653206
C1038: 7905 | D1038: Iotech MR-HA- US 1L | E1038: 1.7 | F1038: 1.465323 | G1038: =E1038-F1038 -> 0.234677 | H1038: =G1038/E1038 -> 0.13804529 | J1038: Standard cost is higher than the unit price.
C1039: 7906 | D1039: Iotech STR-HA 16oz | E1039: 1.57 | F1039: 1.013843 | G1039: =E1039-F1039 -> 0.556157 | H1039: =G1039/E1039 -> 0.35424013
C1040: 7832 | D1040: Remedium SkinCentry Premium Silicone Cream 2oz | E1040: 1.4 | F1040: 1.180371 | G1040: =E1040-F1040 -> 0.219629 | H1040: =G1040/E1040 -> 0.15687786 | J1040: Unit Price - .000000
C1041: 7833 | D1041: Remedium SkinCentry Basic Zinc Paste 4oz | E1041: 1.52 | G1041: =E1041-F1041 -> 1.52 | H1041: =G1041/E1041 -> 1 | J1041: Standard Cost - 29895.018735
C1042: 7862 | D1042: ViaCLYR Flip Top 16oz | E1042: 3.5 | F1042: 1.284706 | G1042: =E1042-F1042 -> 2.215294 | H1042: =G1042/E1042 -> 0.63294114 | J1042: Unit Price - .000000
C1043: 7863 | D1043: ViaCLYR Flip Top 32oz | E1043: 7.52 | F1043: 2.056826 | G1043: =E1043-F1043 -> 5.463174 | H1043: =G1043/E1043 -> 0.7264859 | J1043: Standard Cost - 1.932876
C1044: 7898 | D1044: MP00702 MPM DryMax/DrySAP Super Absorbent Drsg, Sterile, 8X8; | E1044: 0.99 | F1044: 0 | G1044: =E1044-F1044 -> 0.99 | H1044: =G1044/E1044 -> 1
C1045: 7903 | D1045: Spritz wound care spray 4 fl oz | E1045: 2 | F1045: 1.932876 | G1045: =E1045-F1045 -> 0.067124 | H1045: =G1045/E1045 -> 0.033562
C1046: 7940 | D1046: Pause life vulva moisturizer 15mL with Xylitol | E1046: 3.01 | F1046: 0.859941 | G1046: =E1046-F1046 -> 2.150059 | H1046: =G1046/E1046 -> 0.71430532
C1047: 7941 | D1047: Pause life vulva moisturizer 50mL with Xylitol | E1047: 5.53 | F1047: 2.912062 | G1047: =E1047-F1047 -> 2.617938 | H1047: =G1047/E1047 -> 0.47340651
C1048: 7981 | D1048: 4" x 5" Therabond 3D Island Dressing 3DAI-45 | E1048: 1.27 | F1048: 0 | G1048: =E1048-F1048 -> 1.27 | H1048: =G1048/E1048 -> 1 | J1048: Standard Cost - .000000
C1049: 7983 | D1049: Osteoremedies Branded 1.0oz BlastX 12 assembly Turnkey | E1049: 6.5 | F1049: 0.962625 | G1049: =E1049-F1049 -> 5.537375 | H1049: =G1049/E1049 -> 0.85190385
C1050: 7984 | D1050: Osteoremedies Branded Gel 0.25 oz, 40 assembly Turnkey | E1050: 2.57 | F1050: 0.895937 | G1050: =E1050-F1050 -> 1.674063 | H1050: =G1050/E1050 -> 0.65138638
C1051: 7987 | D1051: 4" x 10" Therabond 3D Island Dressing 3DAIXS-410 | E1051: 2.7 | F1051: 0 | G1051: =E1051-F1051 -> 2.7 | H1051: =G1051/E1051 -> 1 | J1051: Standard Cost - .000000
C1052: 7991 | D1052: Bloomi Delight 3oz | E1052: 3.45 | F1052: 0 | G1052: =E1052-F1052 -> 3.45 | H1052: =G1052/E1052 -> 1 | J1052: Standard Cost - .000000
C1053: 7993 | D1053: 200 RC Filter | E1053: 1.675 | F1053: 0 | G1053: =E1053-F1053 -> 1.675 | H1053: =G1053/E1053 -> 1 | J1053: Standard Cost - .000000
C1054: 7997 | D1054: Turn Therapeutics Hexagen Bulk - 55 Gallon Drum | E1054: 1910 | F1054: 0 | G1054: =E1054-F1054 -> 1910 | H1054: =G1054/E1054 -> 1 | J1054: Standard Cost - .000000
C1055: 7811 | D1055: PERIO AO ProRinse WHITE CARE 10 oz | E1055: 2.65 | F1055: 0 | G1055: =E1055-F1055 -> 2.65 | H1055: =G1055/E1055 -> 1 | J1055: Standard Cost - .000000
C1056: 7861 | D1056: ViaCLYR Flip Top 8oz | E1056: 2.7 | F1056: 0.841665 | G1056: =E1056-F1056 -> 1.858335 | H1056: =G1056/E1056 -> 0.68827222
C1057: 7975 | D1057: 4" x 6" Therabond 3D Island Dressing 3DAI-46 | E1057: 1.32 | F1057: 0 | G1057: =E1057-F1057 -> 1.32 | H1057: =G1057/E1057 -> 1 | J1057: Standard Cost - .000000
C1058: 7976 | D1058: 4" x 8" Therabond 3D Island Dressing 3DAI-48 | E1058: 1.75 | F1058: 0 | G1058: =E1058-F1058 -> 1.75 | H1058: =G1058/E1058 -> 1 | J1058: Standard Cost - .000000
C1059: 7978 | D1059: 4" x 12" Therabond 3D Island Dressing 3DAI-412 | E1059: 2.13 | F1059: 0 | G1059: =E1059-F1059 -> 2.13 | H1059: =G1059/E1059 -> 1 | J1059: Standard Cost - .000000 | M1059: SOs Unit Price (2) 2.13 & 3.78
C1060: 7979 | D1060: 4" x 14" Therabond 3D Island Dressing 3DAIXS-414 | E1060: 2.2 | F1060: 0 | G1060: =E1060-F1060 -> 2.2 | H1060: =G1060/E1060 -> 1 | J1060: Standard Cost - .000000
C1061: 7980 | D1061: 4" x 10" Therabond 3D Island Dressing 3DAI-410 | E1061: 2.7 | F1061: 0 | G1061: =E1061-F1061 -> 2.7 | H1061: =G1061/E1061 -> 1 | J1061: Standard Cost - .000000
C1062: 7982 | D1062: 2" x 2" Therabond 3D Island Dressing 3DAI-22 | E1062: 0.56 | F1062: 0 | G1062: =E1062-F1062 -> 0.56 | H1062: =G1062/E1062 -> 1 | J1062: Standard Cost - .000000
C1063: 7992 | D1063: Port Drape | E1063: 0.56 | F1063: 0 | G1063: =E1063-F1063 -> 0.56 | H1063: =G1063/E1063 -> 1 | J1063: Standard Cost - .000000
C1064: 7812 | D1064: PERIO AO ProRinse WHITE CARE 32 oz | E1064: 6.95 | F1064: 0 | G1064: =E1064-F1064 -> 6.95 | H1064: =G1064/E1064 -> 1 | J1064: Standard Cost - .000000
C1065: 8012 | D1065: Bloomi Delight 3oz (1K Use Only) | E1065: 1000 | F1065: 0.73515 | G1065: =E1065-F1065 -> 999.26485 | H1065: =G1065/E1065 -> 0.99926485
C1066: CuDerm - Packing | D1066: CuDerm - Packing | E1066: 30 | F1066: 0 | G1066: =E1066-F1066 -> 30 | H1066: =G1066/E1066 -> 1
C1067: CuDerm - Press | D1067: CuDerm - Press | E1067: 165 | F1067: 0 | G1067: =E1067-F1067 -> 165 | H1067: =G1067/E1067 -> 1
C1068: CuDerm - Rewind | D1068: CuDerm - Rewind | E1068: 75 | F1068: 0 | G1068: =E1068-F1068 -> 75 | H1068: =G1068/E1068 -> 1
C1069: CuDerm - Shippers Whse | D1069: Shippers Warehouse Fee | E1069: 189.1 | F1069: 0 | G1069: =E1069-F1069 -> 189.1 | H1069: =G1069/E1069 -> 1
C1070: F-100004 | D1070: EVALULAB 18 SITE SEMI-OCCLUSIVE /5K ROLL | E1070: 231 | F1070: 42.25489 | G1070: =E1070-F1070 -> 188.74511 | H1070: =G1070/E1070 -> 0.8170784
C1071: F-11016 | D1071: HFT- BEHIND THE SEAMS DRESS SHIELDS | E1071: 2.34 | F1071: 0.747782 | G1071: =E1071-F1071 -> 1.592218 | H1071: =G1071/E1071 -> 0.68043504
C1072: F-17001 | D1072: DERMA SCIENCE CATH-STRIP CS50 | E1072: 1.26 | F1072: 0.727558 | G1072: =E1072-F1072 -> 0.532442 | H1072: =G1072/E1072 -> 0.42257302
C1073: F-22004 | D1073: 5 SITE SEMI-OCCLUSIVE STRIP | E1073: 0.38 | F1073: 0.231368 | G1073: =E1073-F1073 -> 0.148632 | H1073: =G1073/E1073 -> 0.39113684
C1074: F-22005 | D1074: 5 SITE OCCLUSIVE TEST STRIP | E1074: 0.6 | F1074: 0.336953 | G1074: =E1074-F1074 -> 0.263047 | H1074: =G1074/E1074 -> 0.43841167
C1075: F-22007 | D1075: ADVANCED 2" × 200' ROLL SEMI-OCCLUSIVE | E1075: 195.44 | F1075: 69.305713 | G1075: =E1075-F1075 -> 126.13429 | H1075: =G1075/E1075 -> 0.64538624
C1076: F-22008 | D1076: ADVANCED 2" × 200' ROLL OCCLUSIVE | E1076: 103.36 | F1076: 58.805708 | G1076: =E1076-F1076 -> 44.554292 | H1076: =G1076/E1076 -> 0.43105933
C1077: F-239007 | D1077: VASAMED LSA ATTACHMENT PACK | E1077: 1.407 | F1077: 0.55057 | G1077: =E1077-F1077 -> 0.85643 | H1077: =G1077/E1077 -> 0.60869225
... C1232: V-000113 | D1232: S. EAGLE NICOTINE DISSOLVABLE STRIP, 6 PK CARTON | E1232: 18 | F1232: 10.173324 | G1232: =E1232-F1232 -> 7.826676 | H1232: =G1232/E1232 -> 0.43481533
G1233: =E1233-F1233 -> 0 | H1233: =G1233/E1233 -> #DIV/0!
G1234: =E1234-F1234 -> 0 | H1234: =G1234/E1234 -> #DIV/0!
G1235: =E1235-F1235 -> 0 | H1235: =G1235/E1235 -> #DIV/0!
G1236: =E1236-F1236 -> 0 | H1236: =G1236/E1236 -> #DIV/0!
G1237: =E1237-F1237 -> 0 | H1237: =G1237/E1237 -> #DIV/0!
G1238: =E1238-F1238 -> 0 | H1238: =G1238/E1238 -> #DIV/0!
G1239: =E1239-F1239 -> 0 | H1239: =G1239/E1239 -> #DIV/0!
G1240: =E1240-F1240 -> 0 | H1240: =G1240/E1240 -> #DIV/0!
G1241: =E1241-F1241 -> 0 | H1241: =G1241/E1241 -> #DIV/0!
G1242: =E1242-F1242 -> 0 | H1242: =G1242/E1242 -> #DIV/0!
G1243: =E1243-F1243 -> 0 | H1243: =G1243/E1243 -> #DIV/0!
G1244: =E1244-F1244 -> 0 | H1244: =G1244/E1244 -> #DIV/0!
... G8977: =E8977-F8977 -> 0 | H8977: =G8977/E8977 -> #DIV/0!

Sheet Customer Master List
C2: Customer | D2: Category
C3: Harmac Medical Products, Inc | D3: Converting | F3: Harmac Medical Products
C4: Harmac Medical Products | D4: Converting
C5: Gemini Bio-Products, LLC | D5: Converting
C6: Impact Medical | D6: Converting
C7: Derma Sciences Canada Inc. | D7: Converting
C8: Milliken & Company | D8: Converting
C9: Vella Bioscience, Inc | D9: Filling
C10: MPM Medical, Inc. | D10: Collagen/Filling
C11: Orora Business Service Center | D11: Filling
C12: Nutri Tube | D12: Converting
C13: Argentum Medical, LLC | D13: Converting
C14: Turn Therapeutics | D14: Collagen
C15: CharismoUSA,Corp | D15: Filling
... C57: Monaderm | D57: Converting
C58: Amyris Clean Beauty
C60: TatuYou LLC | D60: Converting
C61: Phardevelopment Trials, Ltd | D61: Converting
